Workbook

Sheet Cover
B7: Cover Page | C7: Page
B8: Assumptions | C8: =Assumptions!A1 -> 0
B9: Calcs | C9: =Calcs!A1 -> 0
B10: Income Statement | C10: ='Income Statement'!A1 -> 0
B11: Balance Sheet | C11: ='Balance Sheet'!A1 -> 0
B12: Cash Flow Statement | C12: ='Cash Flow Statement'!A1 -> 0
B13: Debt Schedule | C13: ='Debt Schedule'!A1 -> 0
B14: LTM | C14: =LTMS!A3 -> 0
B15: Comps | C15: =Comps!A1 -> 0
B16: WACC | C16: =WACC!A1 -> 0
B17: DCF | C17: =DCF!A1 -> 0

Sheet Assumptions
B2: Assumptions | C2: Historical | I2: Average % | L2: Projected | S2: Projected | Z2: Projected | AG2: Projected
C3: 2021 | D3: =C3+1 -> 2022 | E3: =D3+1 -> 2023 | F3: =E3+1 -> 2024 | G3: =F3+1 -> 2025 | I3: 3YR AVG | J3: 5YR AVG | L3: =G3+1 -> 2026 | M3: =L3+1 -> 2027 | N3: =M3+1 -> 2028 | O3: =N3+1 -> 2029 | P3: =O3+1 -> 2030 | T3: 2026 | U3: 2027 | V3: 2028 | W3: 2029 | X3: 2030 | AA3: 2026 | AB3: 2027 | AC3: 2028 | AD3: 2029 | AE3: 2030 | AH3: 2026 | AI3: 2027 | AJ3: 2028 | AK3: 2029 | AL3: 2030
B4: Income Statement | N4: Base | S4: Bull | Z4: Bear | AG4: Base
A5: x | B5: Products ( Pharmacy Revenues) (ASC 606) | AO5: Bull
B6: Network Revenues | D6: =('Income Statement'!D6-'Income Statement'!C6)/'Income Statement'!C6 -> -0.00070777942 | E6: =('Income Statement'!E6-'Income Statement'!D6)/'Income Statement'!D6 -> 0.039540541 | F6: =('Income Statement'!F6-'Income Statement'!E6)/'Income Statement'!E6 -> 0.56026898 | G6: =('Income Statement'!G6-'Income Statement'!F6)/'Income Statement'!F6 -> 0.19207329 | I6: =AVERAGE(E6:G6) -> 0.26396094 | J6: =AVERAGE(D6:G6) -> 0.19779376 | L6: {=_xlfn.IFS($N$4="Bull",T6, $N$4="Bear",AA6, $N$4="Base",AH6)} -> 0.14 | M6: {=_xlfn.IFS($N$4="Bull",U6, $N$4="Bear",AB6, $N$4="Base",AI6)} -> 0.12 | N6: {=_xlfn.IFS($N$4="Bull",V6, $N$4="Bear",AC6, $N$4="Base",AJ6)} -> 0.08 | O6: {=_xlfn.IFS($N$4="Bull",W6, $N$4="Bear",AD6, $N$4="Base",AK6)} -> 0.065 | P6: {=_xlfn.IFS($N$4="Bull",X6, $N$4="Bear",AE6, $N$4="Base",AL6)} -> 0.065 | T6: 0.2 | U6: 0.17 | V6: 0.185 | W6: 0.19 | X6: 0.205 | AA6: 0.1 | AB6: 0.075 | AC6: 0.05 | AD6: 0.035 | AE6: 0.035 | AH6: 0.14 | AI6: 0.12 | AJ6: 0.08 | AK6: 0.065 | AL6: 0.065 | AO6: Bear
B7: Home Delivery and Specialty | D7: =('Income Statement'!D7-'Income Statement'!C7)/'Income Statement'!C7 -> 0.12671214 | E7: =('Income Statement'!E7-'Income Statement'!D7)/'Income Statement'!D7 -> 0.072597621 | F7: =('Income Statement'!F7-'Income Statement'!E7)/'Income Statement'!E7 -> 0.10259843 | G7: =('Income Statement'!G7-'Income Statement'!F7)/'Income Statement'!F7 -> 0.11060213 | I7: =AVERAGE(E7:G7) -> 0.09526606 | J7: =AVERAGE(D7:G7) -> 0.10312758 | L7: {=_xlfn.IFS($N$4="Bull",T7, $N$4="Bear",AA7, $N$4="Base",AH7)} -> 0.113 | M7: {=_xlfn.IFS($N$4="Bull",U7, $N$4="Bear",AB7, $N$4="Base",AI7)} -> 0.1 | N7: {=_xlfn.IFS($N$4="Bull",V7, $N$4="Bear",AC7, $N$4="Base",AJ7)} -> 0.095 | O7: {=_xlfn.IFS($N$4="Bull",W7, $N$4="Bear",AD7, $N$4="Base",AK7)} -> 0.08 | P7: {=_xlfn.IFS($N$4="Bull",X7, $N$4="Bear",AE7, $N$4="Base",AL7)} -> 0.08 | T7: 0.115 | U7: 0.11 | V7: 0.105 | W7: 0.1 | X7: 0.095 | AA7: 0.08 | AB7: 0.07 | AC7: 0.06 | AD7: 0.05 | AE7: 0.05 | AH7: 0.113 | AI7: 0.1 | AJ7: 0.095 | AK7: 0.08 | AL7: 0.08 | AO7: Base
B8: Other Revenues | D8: =('Income Statement'!D8-'Income Statement'!C8)/'Income Statement'!C8 -> 0.05056005 | E8: =('Income Statement'!E8-'Income Statement'!D8)/'Income Statement'!D8 -> 0.33970087 | F8: =('Income Statement'!F8-'Income Statement'!E8)/'Income Statement'!E8 -> 0.27611363 | G8: =('Income Statement'!G8-'Income Statement'!F8)/'Income Statement'!F8 -> 0.15452577 | I8: =AVERAGE(E8:G8) -> 0.25678009 | J8: =AVERAGE(D8:G8) -> 0.20522508 | L8: {=_xlfn.IFS($N$4="Bull",T8, $N$4="Bear",AA8, $N$4="Base",AH8)} -> 0.1395 | M8: {=_xlfn.IFS($N$4="Bull",U8, $N$4="Bear",AB8, $N$4="Base",AI8)} -> 0.118 | N8: {=_xlfn.IFS($N$4="Bull",V8, $N$4="Bear",AC8, $N$4="Base",AJ8)} -> 0.11 | O8: {=_xlfn.IFS($N$4="Bull",W8, $N$4="Bear",AD8, $N$4="Base",AK8)} -> 0.105 | P8: {=_xlfn.IFS($N$4="Bull",X8, $N$4="Bear",AE8, $N$4="Base",AL8)} -> 0.105 | T8: 0.16 | U8: 0.14 | V8: 0.13 | W8: 0.11 | X8: 0.108 | AA8: 0.09 | AB8: 0.075 | AC8: 0.065 | AD8: 0.06 | AE8: 0.06 | AH8: 0.1395 | AI8: 0.118 | AJ8: 0.11 | AK8: 0.105 | AL8: 0.105
B9: Other Operations | G9: =('Income Statement'!G9-'Income Statement'!F9)/'Income Statement'!F9 -> -0.1 | I9: =AVERAGE(E9:G9) -> -0.1 | J9: =AVERAGE(D9:G9) -> -0.1 | L9: {=_xlfn.IFS($N$4="Bull",T9, $N$4="Bear",AA9, $N$4="Base",AH9)} -> -0.1 | M9: {=_xlfn.IFS($N$4="Bull",U9, $N$4="Bear",AB9, $N$4="Base",AI9)} -> -0.1 | N9: {=_xlfn.IFS($N$4="Bull",V9, $N$4="Bear",AC9, $N$4="Base",AJ9)} -> -0.1 | O9: {=_xlfn.IFS($N$4="Bull",W9, $N$4="Bear",AD9, $N$4="Base",AK9)} -> -0.1 | P9: {=_xlfn.IFS($N$4="Bull",X9, $N$4="Bear",AE9, $N$4="Base",AL9)} -> -0.1 | T9: -0.1 | U9: -0.1 | V9: -0.1 | W9: -0.1 | X9: -0.1 | AA9: -0.1 | AB9: -0.1 | AC9: -0.1 | AD9: -0.1 | AE9: -0.1 | AH9: -0.1 | AI9: -0.1 | AJ9: -0.1 | AK9: -0.1 | AL9: -0.1
B10: Intercompany Eliminations | D10: =('Income Statement'!D10-'Income Statement'!C10)/'Income Statement'!C10 -> 0.0040927694 | E10: =('Income Statement'!E10-'Income Statement'!D10)/'Income Statement'!D10 -> 0.14356884 | F10: =('Income Statement'!F10-'Income Statement'!E10)/'Income Statement'!E10 -> -0.19623762 | G10: =('Income Statement'!G10-'Income Statement'!F10)/'Income Statement'!F10 -> -0.31608771 | I10: =AVERAGE(E10:G10) -> -0.12291883 | J10: =AVERAGE(D10:G10) -> -0.09116593 | L10: {=_xlfn.IFS($N$4="Bull",T10, $N$4="Bear",AA10, $N$4="Base",AH10)} -> -0.245 | M10: {=_xlfn.IFS($N$4="Bull",U10, $N$4="Bear",AB10, $N$4="Base",AI10)} -> -0.205 | N10: {=_xlfn.IFS($N$4="Bull",V10, $N$4="Bear",AC10, $N$4="Base",AJ10)} -> -0.172 | O10: {=_xlfn.IFS($N$4="Bull",W10, $N$4="Bear",AD10, $N$4="Base",AK10)} -> -0.12 | P10: {=_xlfn.IFS($N$4="Bull",X10, $N$4="Bear",AE10, $N$4="Base",AL10)} -> -0.12 | T10: -0.22 | U10: -0.19 | V10: -0.15 | W10: -0.1 | X10: -0.11 | AA10: -0.32 | AB10: -0.27 | AC10: -0.23 | AD10: -0.18 | AE10: -0.18 | AH10: -0.245 | AI10: -0.205 | AJ10: -0.172 | AK10: -0.12 | AL10: -0.12
B12: Insurance Premiums (ASC 944)
B13: Cigna Healthcare
A14: x | B14: U.S Commercial
B15: Insured | D15: =('Income Statement'!D15-'Income Statement'!C15)/'Income Statement'!C15 -> 0.061753406 | E15: =('Income Statement'!E15-'Income Statement'!D15)/'Income Statement'!D15 -> 0.084939799 | F15: =('Income Statement'!F15-'Income Statement'!E15)/'Income Statement'!E15 -> 0.065858096 | G15: =('Income Statement'!G15-'Income Statement'!F15)/'Income Statement'!F15 -> 0.072598999 | I15: =AVERAGE(E15:G15) -> 0.074465631 | J15: =AVERAGE(D15:G15) -> 0.071287575 | L15: {=_xlfn.IFS($N$4="Bull",T15, $N$4="Bear",AA15, $N$4="Base",AH15)} -> 0.03 | M15: {=_xlfn.IFS($N$4="Bull",U15, $N$4="Bear",AB15, $N$4="Base",AI15)} -> 0.034 | N15: {=_xlfn.IFS($N$4="Bull",V15, $N$4="Bear",AC15, $N$4="Base",AJ15)} -> 0.034 | O15: {=_xlfn.IFS($N$4="Bull",W15, $N$4="Bear",AD15, $N$4="Base",AK15)} -> 0.05 | P15: {=_xlfn.IFS($N$4="Bull",X15, $N$4="Bear",AE15, $N$4="Base",AL15)} -> 0.05 | T15: 0.08 | U15: 0.0775 | V15: 0.075 | W15: 0.0725 | X15: 0.07 | AA15: 0.055 | AB15: 0.05 | AC15: 0.045 | AD15: 0.04 | AE15: 0.04 | AH15: 0.03 | AI15: 0.034 | AJ15: 0.034 | AK15: 0.05 | AL15: 0.05
B16: Stop Loss | D16: =('Income Statement'!D16-'Income Statement'!C16)/'Income Statement'!C16 -> 0.12181594 | E16: =('Income Statement'!E16-'Income Statement'!D16)/'Income Statement'!D16 -> 0.12488555 | F16: =('Income Statement'!F16-'Income Statement'!E16)/'Income Statement'!E16 -> 0.097834934 | G16: =('Income Statement'!G16-'Income Statement'!F16)/'Income Statement'!F16 -> 0.12677936 | I16: =AVERAGE(E16:G16) -> 0.11649995 | J16: =AVERAGE(F16:H16) -> 0.11230715 | L16: {=_xlfn.IFS($N$4="Bull",T16, $N$4="Bear",AA16, $N$4="Base",AH16)} -> 0.125 | M16: {=_xlfn.IFS($N$4="Bull",U16, $N$4="Bear",AB16, $N$4="Base",AI16)} -> 0.115 | N16: {=_xlfn.IFS($N$4="Bull",V16, $N$4="Bear",AC16, $N$4="Base",AJ16)} -> 0.11 | O16: {=_xlfn.IFS($N$4="Bull",W16, $N$4="Bear",AD16, $N$4="Base",AK16)} -> 0.105 | P16: {=_xlfn.IFS($N$4="Bull",X16, $N$4="Bear",AE16, $N$4="Base",AL16)} -> 0.105 | T16: 0.125 | U16: 0.1275 | V16: 0.13 | W16: 0.1325 | X16: 0.135 | AA16: 0.09 | AB16: 0.08 | AC16: 0.07 | AD16: 0.065 | AE16: 0.065 | AH16: 0.125 | AI16: 0.115 | AJ16: 0.11 | AK16: 0.105 | AL16: 0.105
B17: Other | D17: =('Income Statement'!D17-'Income Statement'!C17)/'Income Statement'!C17 -> 0.099224806 | E17: =('Income Statement'!E17-'Income Statement'!D17)/'Income Statement'!D17 -> 2.5881523 | F17: =('Income Statement'!F17-'Income Statement'!E17)/'Income Statement'!E17 -> -0.22346698 | G17: =('Income Statement'!G17-'Income Statement'!F17)/'Income Statement'!F17 -> -0.14679828 | I17: =AVERAGE(E17:G17) -> 0.73929569 | J17: =AVERAGE(F17:H17) -> -0.18513263 | L17: {=_xlfn.IFS($N$4="Bull",T17, $N$4="Bear",AA17, $N$4="Base",AH17)} -> -0.15 | M17: {=_xlfn.IFS($N$4="Bull",U17, $N$4="Bear",AB17, $N$4="Base",AI17)} -> -0.1 | N17: {=_xlfn.IFS($N$4="Bull",V17, $N$4="Bear",AC17, $N$4="Base",AJ17)} -> -0.08 | O17: {=_xlfn.IFS($N$4="Bull",W17, $N$4="Bear",AD17, $N$4="Base",AK17)} -> -0.05 | P17: {=_xlfn.IFS($N$4="Bull",X17, $N$4="Bear",AE17, $N$4="Base",AL17)} -> -0.05 | T17: 0.2771 | U17: 0.2771 | V17: 0.2771 | W17: 0.2771 | X17: 0.2771 | AA17: -0.2 | AB17: -0.15 | AC17: -0.12 | AD17: -0.08 | AE17: -0.08 | AH17: -0.15 | AI17: -0.1 | AJ17: -0.08 | AK17: -0.05 | AL17: -0.05
A19: x | B19: U.S Government
B20: Medicare Advantage | D20: =('Income Statement'!D19-'Income Statement'!C19)/'Income Statement'!C19 -> -0.055728295 | E20: =('Income Statement'!E19-'Income Statement'!D19)/'Income Statement'!D19 -> 0.1108156 | F20: =('Income Statement'!F19-'Income Statement'!E19)/'Income Statement'!E19 -> -0.010489112 | G20: =('Income Statement'!G19-'Income Statement'!F19)/'Income Statement'!F19 -> -0.72773361 | I20: =AVERAGE(E20:G20) -> -0.20913571 | J20: =AVERAGE(D20:G20) -> -0.17078385 | L20: {=_xlfn.IFS($N$4="Bull",AA20, $N$4="Bear",T20, $N$4="Base",AH20)} -> -0.3 | M20: {=_xlfn.IFS($N$4="Bull",AB20, $N$4="Bear",U20, $N$4="Base",AI20)} -> -0.5 | N20: {=_xlfn.IFS($N$4="Bull",AC20, $N$4="Bear",V20, $N$4="Base",AJ20)} -> -1 | O20: {=_xlfn.IFS($N$4="Bull",AD20, $N$4="Bear",W20, $N$4="Base",AK20)} -> 0 | P20: {=_xlfn.IFS($N$4="Bull",AE20, $N$4="Bear",X20, $N$4="Base",AL20)} -> 0 | T20: -0.2 | U20: -0.4 | V20: -0.6 | W20: -0.8 | X20: -1 | AA20: -0.5 | AB20: -0.75 | AC20: -1 | AD20: 0 | AE20: 0 | AH20: -0.3 | AI20: -0.5 | AJ20: -1 | AK20: 0 | AL20: 0
B21: Medicare Part D | D21: =('Income Statement'!D20-'Income Statement'!C20)/'Income Statement'!C19 -> -0.032886869 | E21: =('Income Statement'!E20-'Income Statement'!D20)/'Income Statement'!D19 -> -0.1550152 | F21: =('Income Statement'!F20-'Income Statement'!E20)/'Income Statement'!E19 -> 0 | G21: =('Income Statement'!G20-'Income Statement'!F20)/'Income Statement'!F19 -> 0 | I21: =AVERAGE(E21:G21) -> -0.051671733 | J21: =AVERAGE(D21:G21) -> -0.046975517 | L21: {=_xlfn.IFS($N$4="Bull",AA21, $N$4="Bear",T21, $N$4="Base",AH21)} -> 0.02 | M21: {=_xlfn.IFS($N$4="Bull",AB21, $N$4="Bear",U21, $N$4="Base",AI21)} -> 0.02 | N21: {=_xlfn.IFS($N$4="Bull",AC21, $N$4="Bear",V21, $N$4="Base",AJ21)} -> 0.02 | O21: {=_xlfn.IFS($N$4="Bull",AD21, $N$4="Bear",W21, $N$4="Base",AK21)} -> 0.02 | P21: {=_xlfn.IFS($N$4="Bull",AE21, $N$4="Bear",X21, $N$4="Base",AL21)} -> 0.02 | T21: 0.02 | U21: 0.03 | V21: 0 | W21: 0.01 | X21: 0 | AA21: 0 | AB21: 0.01 | AC21: -0.04 | AD21: -0.06 | AE21: -0.04 | AH21: 0.02 | AI21: 0.02 | AJ21: 0.02 | AK21: 0.02 | AL21: 0.02
B22: Other | D22: =('Income Statement'!D21-'Income Statement'!C21)/'Income Statement'!C21 -> -0.17133956 | E22: =('Income Statement'!E21-'Income Statement'!D21)/'Income Statement'!D21 -> 0.026315789 | F22: =('Income Statement'!F21-'Income Statement'!E21)/'Income Statement'!E21 -> 0.20586081 | G22: =('Income Statement'!G21-'Income Statement'!F21)/'Income Statement'!F21 -> -0.31834751 | I22: =AVERAGE(E22:G22) -> -0.028723638 | J22: =AVERAGE(D22:G22) -> -0.064377619 | L22: {=_xlfn.IFS($N$4="Bull",T22, $N$4="Bear",AA22, $N$4="Base",AH22)} -> 0.01 | M22: {=_xlfn.IFS($N$4="Bull",U22, $N$4="Bear",AB22, $N$4="Base",AI22)} -> 0.01 | N22: {=_xlfn.IFS($N$4="Bull",V22, $N$4="Bear",AC22, $N$4="Base",AJ22)} -> 0.02 | O22: {=_xlfn.IFS($N$4="Bull",W22, $N$4="Bear",AD22, $N$4="Base",AK22)} -> 0.02 | P22: {=_xlfn.IFS($N$4="Bull",X22, $N$4="Bear",AE22, $N$4="Base",AL22)} -> 0.01 | T22: 0.03 | U22: 0.03 | V22: 0.03 | W22: 0.03 | X22: 0.03 | AA22: 0.01 | AB22: 0.01 | AC22: 0.01 | AD22: 0.01 | AE22: 0.01 | AH22: 0.01 | AI22: 0.01 | AJ22: 0.02 | AK22: 0.02 | AL22: 0.01
B23: International Health | D23: =('Income Statement'!D22-'Income Statement'!C22)/'Income Statement'!C22 -> 0.12287481 | E23: =('Income Statement'!E22-'Income Statement'!D22)/'Income Statement'!D22 -> 0.13386098 | F23: =('Income Statement'!F22-'Income Statement'!E22)/'Income Statement'!E22 -> 0.099848255 | G23: =('Income Statement'!G22-'Income Statement'!F22)/'Income Statement'!F22 -> 0.13852097 | I23: =AVERAGE(E23:G23) -> 0.12407673 | J23: =AVERAGE(D23:G23) -> 0.12377625 | L23: {=_xlfn.IFS($N$4="Bull",T23, $N$4="Bear",AA23, $N$4="Base",AH23)} -> 0.08 | M23: {=_xlfn.IFS($N$4="Bull",U23, $N$4="Bear",AB23, $N$4="Base",AI23)} -> 0.08 | N23: {=_xlfn.IFS($N$4="Bull",V23, $N$4="Bear",AC23, $N$4="Base",AJ23)} -> 0.08 | O23: {=_xlfn.IFS($N$4="Bull",W23, $N$4="Bear",AD23, $N$4="Base",AK23)} -> 0.07 | P23: {=_xlfn.IFS($N$4="Bull",X23, $N$4="Bear",AE23, $N$4="Base",AL23)} -> 0.07 | T23: 0.12 | U23: 0.11 | V23: 0.105 | W23: 0.1 | X23: 0.09 | AA23: 0.08 | AB23: 0.075 | AC23: 0.07 | AD23: 0.065 | AE23: 0.06 | AH23: 0.08 | AI23: 0.08 | AJ23: 0.08 | AK23: 0.07 | AL23: 0.07
B24: Divested International Businesses | D24: =('Income Statement'!D24-'Income Statement'!C24)/'Income Statement'!C24 -> -0.50202808 | E24: =('Income Statement'!E24-'Income Statement'!D24)/'Income Statement'!D24 -> -1 | F24: 0 | G24: 0 | I24: =AVERAGE(E24:G24) -> -0.33333333 | J24: =AVERAGE(D24:G24) -> -0.37550702 | L24: {=_xlfn.IFS($N$4="Bull",T24, $N$4="Bear",AA24, $N$4="Base",AH24)} -> 0 | M24: {=_xlfn.IFS($N$4="Bull",U24, $N$4="Bear",AB24, $N$4="Base",AI24)} -> 0 | N24: {=_xlfn.IFS($N$4="Bull",V24, $N$4="Bear",AC24, $N$4="Base",AJ24)} -> 0 | O24: {=_xlfn.IFS($N$4="Bull",W24, $N$4="Bear",AD24, $N$4="Base",AK24)} -> 0 | P24: {=_xlfn.IFS($N$4="Bull",X24, $N$4="Bear",AE24, $N$4="Base",AL24)} -> 0 | T24: 0 | U24: 0 | V24: 0 | W24: 0 | X24: 0 | AA24: 0 | AB24: 0 | AC24: 0 | AD24: 0 | AE24: 0 | AH24: 0 | AI24: 0 | AJ24: 0 | AK24: 0 | AL24: 0
B25: Domestic Disability; Life and accident | D25: ='Income Statement'!C25 -> 0 | E25: ='Income Statement'!D25 -> 0 | F25: ='Income Statement'!E25 -> 0 | G25: ='Income Statement'!F25 -> 0 | I25: =AVERAGE(E25:G25) -> 0 | J25: =AVERAGE(D25:G25) -> 0 | L25: {=_xlfn.IFS($N$4="Bull",T25, $N$4="Bear",AA25, $N$4="Base",AH25)} -> 0 | M25: {=_xlfn.IFS($N$4="Bull",U25, $N$4="Bear",AB25, $N$4="Base",AI25)} -> 0 | N25: {=_xlfn.IFS($N$4="Bull",V25, $N$4="Bear",AC25, $N$4="Base",AJ25)} -> 0 | O25: {=_xlfn.IFS($N$4="Bull",W25, $N$4="Bear",AD25, $N$4="Base",AK25)} -> 0 | P25: {=_xlfn.IFS($N$4="Bull",X25, $N$4="Bear",AE25, $N$4="Base",AL25)} -> 0 | T25: 0 | U25: 0 | V25: 0 | W25: 0 | X25: 0 | AA25: 0 | AB25: 0 | AC25: 0 | AD25: 0 | AE25: 0 | AH25: 0 | AI25: 0 | AJ25: 0 | AK25: 0 | AL25: 0
B26: Other | D26: =('Income Statement'!D26-'Income Statement'!C26)/'Income Statement'!C26 -> 0.013574661 | E26: =('Income Statement'!E26-'Income Statement'!D26)/'Income Statement'!D26 -> 0.25446429 | F26: =('Income Statement'!F26-'Income Statement'!E26)/'Income Statement'!E26 -> 0.35231317 | G26: =('Income Statement'!G26-'Income Statement'!F26)/'Income Statement'!F26 -> -0.24210526 | I26: =AVERAGE(E26:G26) -> 0.1215574 | J26: =AVERAGE(D26:G26) -> 0.094561713 | L26: {=_xlfn.IFS($N$4="Bull",T26, $N$4="Bear",AA26, $N$4="Base",AH26)} -> 0.10805955 | M26: {=_xlfn.IFS($N$4="Bull",U26, $N$4="Bear",AB26, $N$4="Base",AI26)} -> 0.10805955 | N26: {=_xlfn.IFS($N$4="Bull",V26, $N$4="Bear",AC26, $N$4="Base",AJ26)} -> 0.10805955 | O26: {=_xlfn.IFS($N$4="Bull",W26, $N$4="Bear",AD26, $N$4="Base",AK26)} -> 0.10805955 | P26: {=_xlfn.IFS($N$4="Bull",X26, $N$4="Bear",AE26, $N$4="Base",AL26)} -> 0.10805955 | T26: =AVERAGEA($I$26:$J$26) -> 0.10805955 | U26: =AVERAGEA($I$26:$J$26) -> 0.10805955 | V26: =AVERAGEA($I$26:$J$26) -> 0.10805955 | W26: =AVERAGEA($I$26:$J$26) -> 0.10805955 | X26: =AVERAGEA($I$26:$J$26) -> 0.10805955 | AA26: =AVERAGE($I$26:$J$26) -> 0.10805955 | AB26: =AVERAGE($I$26:$J$26) -> 0.10805955 | AC26: =AVERAGE($I$26:$J$26) -> 0.10805955 | AD26: =AVERAGE($I$26:$J$26) -> 0.10805955 | AE26: =AVERAGE($I$26:$J$26) -> 0.10805955 | AH26: =AVERAGE($I$26:$J$26) -> 0.10805955 | AI26: =AVERAGE($I$26:$J$26) -> 0.10805955 | AJ26: =AVERAGE($I$26:$J$26) -> 0.10805955 | AK26: =AVERAGE($I$26:$J$26) -> 0.10805955 | AL26: =AVERAGE($I$26:$J$26) -> 0.10805955
B27: Intercompany Eliminatioons | D27: =('Income Statement'!D27-'Income Statement'!C27)/'Income Statement'!C27 -> -1.1111111 | E27: =('Income Statement'!E27-'Income Statement'!D27)/'Income Statement'!D27 -> 73 | F27: =('Income Statement'!F27-'Income Statement'!E27)/'Income Statement'!E27 -> 0.40540541 | G27: =('Income Statement'!G27-'Income Statement'!F27)/'Income Statement'!F27 -> 1.8461538 | I27: =AVERAGE(E27:G27) -> 25.083853 | J27: =AVERAGE(D27:G27) -> 18.535112 | L27: {=_xlfn.IFS($N$4="Bull",T27, $N$4="Bear",AA27, $N$4="Base",AH27)} -> 0 | M27: {=_xlfn.IFS($N$4="Bull",U27, $N$4="Bear",AB27, $N$4="Base",AI27)} -> 0 | N27: {=_xlfn.IFS($N$4="Bull",V27, $N$4="Bear",AC27, $N$4="Base",AJ27)} -> 0 | O27: {=_xlfn.IFS($N$4="Bull",W27, $N$4="Bear",AD27, $N$4="Base",AK27)} -> 0 | P27: {=_xlfn.IFS($N$4="Bull",X27, $N$4="Bear",AE27, $N$4="Base",AL27)} -> 0 | T27: 0.01 | U27: 0.01 | V27: 0.01 | W27: 0.01 | X27: 0.01 | AA27: -0.01 | AB27: -0.01 | AC27: -0.01 | AD27: -0.01 | AE27: -0.01 | AH27: 0 | AI27: 0 | AJ27: 0 | AK27: 0 | AL27: 0
A29: x | B29: Service (Fees)(ASC 606)
B30: Evernorth Health Services | D30: =('Income Statement'!D30-'Income Statement'!C30)/'Income Statement'!C30 -> 0.19176277 | E30: =('Income Statement'!E30-'Income Statement'!D30)/'Income Statement'!D30 -> 0.51575892 | F30: =('Income Statement'!F30-'Income Statement'!E30)/'Income Statement'!E30 -> 0.14829001 | G30: =('Income Statement'!G30-'Income Statement'!F30)/'Income Statement'!F30 -> 0.22444603 | I30: =AVERAGE(E30:G30) -> 0.29616499 | J30: =AVERAGE(D30:G30) -> 0.27006443 | L30: {=_xlfn.IFS($N$4="Bull",T30, $N$4="Bear",AA30, $N$4="Base",AH30)} -> 0.2 | M30: {=_xlfn.IFS($N$4="Bull",U30, $N$4="Bear",AB30, $N$4="Base",AI30)} -> 0.205 | N30: {=_xlfn.IFS($N$4="Bull",V30, $N$4="Bear",AC30, $N$4="Base",AJ30)} -> 0.21 | O30: {=_xlfn.IFS($N$4="Bull",W30, $N$4="Bear",AD30, $N$4="Base",AK30)} -> 0.215 | P30: {=_xlfn.IFS($N$4="Bull",X30, $N$4="Bear",AE30, $N$4="Base",AL30)} -> 0.22 | T30: 0.26 | U30: 0.27 | V30: 0.28 | W30: 0.29 | X30: 0.3 | AA30: 0.15 | AB30: 0.17 | AC30: 0.15 | AD30: 0.11 | AE30: 0.09 | AH30: 0.2 | AI30: 0.205 | AJ30: 0.21 | AK30: 0.215 | AL30: 0.22
B31: Cigna Healthcare | D31: =('Income Statement'!D31-'Income Statement'!C31)/'Income Statement'!C31 -> 0.053978757 | E31: =('Income Statement'!E31-'Income Statement'!D31)/'Income Statement'!D31 -> 0.10176772 | F31: =('Income Statement'!F31-'Income Statement'!E31)/'Income Statement'!E31 -> 0.047833258 | G31: =('Income Statement'!G31-'Income Statement'!F31)/'Income Statement'!F31 -> 0.023755009 | I31: =AVERAGE(E31:G31) -> 0.057785328 | J31: =AVERAGE(D31:G31) -> 0.056833686 | L31: {=_xlfn.IFS($N$4="Bull",T31, $N$4="Bear",AA31, $N$4="Base",AH31)} -> 0.032 | M31: {=_xlfn.IFS($N$4="Bull",U31, $N$4="Bear",AB31, $N$4="Base",AI31)} -> 0.034 | N31: {=_xlfn.IFS($N$4="Bull",V31, $N$4="Bear",AC31, $N$4="Base",AJ31)} -> 0.041 | O31: {=_xlfn.IFS($N$4="Bull",W31, $N$4="Bear",AD31, $N$4="Base",AK31)} -> 0.055 | P31: {=_xlfn.IFS($N$4="Bull",X31, $N$4="Bear",AE31, $N$4="Base",AL31)} -> 0.055 | T31: 0.03 | U31: 0.032 | V31: 0.038 | W31: 0.041 | X31: 0.044 | AA31: 0.02 | AB31: 0.022 | AC31: 0.025 | AD31: 0.025 | AE31: 0.02 | AH31: 0.032 | AI31: 0.034 | AJ31: 0.041 | AK31: 0.055 | AL31: 0.055
B32: Other Operations | D32: =('Income Statement'!D32-'Income Statement'!C32)/'Income Statement'!C32 -> -0.52631579 | E32: =('Income Statement'!E32-'Income Statement'!D32)/'Income Statement'!D32 -> 0.11111111 | F32: =('Income Statement'!F32-'Income Statement'!E32)/'Income Statement'!E32 -> 6.9 | G32: =('Income Statement'!G32-'Income Statement'!F32)/'Income Statement'!F32 -> -0.56962025 | I32: =AVERAGE(E32:G32) -> 2.1471636 | J32: =AVERAGE(D32:G32) -> 1.4787938 | L32: {=_xlfn.IFS($N$4="Bull",T32, $N$4="Bear",AA32, $N$4="Base",AH33)} -> 0 | M32: {=_xlfn.IFS($N$4="Bull",U32, $N$4="Bear",AB32, $N$4="Base",AI33)} -> 0 | N32: {=_xlfn.IFS($N$4="Bull",V32, $N$4="Bear",AC32, $N$4="Base",AJ33)} -> 0 | O32: {=_xlfn.IFS($N$4="Bull",W32, $N$4="Bear",AD32, $N$4="Base",AK33)} -> 0 | P32: {=_xlfn.IFS($N$4="Bull",X32, $N$4="Bear",AE32, $N$4="Base",AL33)} -> 0 | T32: -0.15 | U32: -0.1 | V32: 0.05 | W32: 0 | X32: 0.03 | AA32: 0 | AB32: 0 | AC32: 0 | AD32: -0.05 | AE32: -0.1 | AH32: -0.2 | AI32: -0.15 | AJ32: -0.13 | AK32: -0.1 | AL32: -0.07
B33: Other Revenues | D33: =('Income Statement'!D33-'Income Statement'!C33)/'Income Statement'!C33 -> -0.15228426 | E33: =('Income Statement'!E33-'Income Statement'!D33)/'Income Statement'!D33 -> -1 | F33: ='Income Statement'!F33 -> 0 | G33: ='Income Statement'!G33 -> 0 | I33: =AVERAGE(E33:G33) -> -0.33333333 | J33: =AVERAGE(D33:G33) -> -0.28807107 | L33: {=_xlfn.IFS($N$4="Bull",T33, $N$4="Bear",AA33, $N$4="Base",AH33)} -> 0 | M33: {=_xlfn.IFS($N$4="Bull",U33, $N$4="Bear",AB33, $N$4="Base",AI33)} -> 0 | N33: {=_xlfn.IFS($N$4="Bull",V33, $N$4="Bear",AC33, $N$4="Base",AJ33)} -> 0 | O33: {=_xlfn.IFS($N$4="Bull",W33, $N$4="Bear",AD33, $N$4="Base",AK33)} -> 0 | P33: {=_xlfn.IFS($N$4="Bull",X33, $N$4="Bear",AE33, $N$4="Base",AL33)} -> 0 | T33: 0 | U33: 0 | V33: 0 | W33: 0 | X33: 0 | AA33: 0 | AB33: 0 | AC33: 0 | AD33: 0 | AE33: 0 | AH33: =G33 -> 0 | AI33: =G33 -> 0 | AJ33: =G33 -> 0 | AK33: =G33 -> 0 | AL33: =G33 -> 0
B34: Intercompany Eliminations | D34: =('Income Statement'!D34-'Income Statement'!C34)/'Income Statement'!C34 -> 0.24963716 | E34: =('Income Statement'!E34-'Income Statement'!D34)/'Income Statement'!D34 -> 0.94541231 | F34: =('Income Statement'!F34-'Income Statement'!E34)/'Income Statement'!E34 -> -0.031243781 | G34: =('Income Statement'!G34-'Income Statement'!F34)/'Income Statement'!F34 -> 0.16762531 | I34: =AVERAGE(E34:G34) -> 0.36059795 | J34: =AVERAGE(D34:G34) -> 0.33285775 | L34: {=_xlfn.IFS($N$4="Bull",T34, $N$4="Bear",AA34, $N$4="Base",AH34)} -> 0 | M34: {=_xlfn.IFS($N$4="Bull",U34, $N$4="Bear",AB34, $N$4="Base",AI34)} -> 0 | N34: {=_xlfn.IFS($N$4="Bull",V34, $N$4="Bear",AC34, $N$4="Base",AJ34)} -> 0 | O34: {=_xlfn.IFS($N$4="Bull",W34, $N$4="Bear",AD34, $N$4="Base",AK34)} -> 0 | P34: {=_xlfn.IFS($N$4="Bull",X34, $N$4="Bear",AE34, $N$4="Base",AL34)} -> 0 | T34: 0.3329 | U34: 0.3329 | V34: 0.3329 | W34: 0.3329 | X34: 0.3329 | AA34: 0 | AB34: 0 | AC34: 0 | AD34: 0.02 | AE34: 0.03
B35: Net investment income | D35: =('Income Statement'!D37-'Income Statement'!C37)/'Income Statement'!C37 -> -0.25435765 | E35: =('Income Statement'!E37-'Income Statement'!D37)/'Income Statement'!D37 -> 0.0095238095 | F35: =('Income Statement'!F37-'Income Statement'!E37)/'Income Statement'!E37 -> -0.16552316 | G35: =('Income Statement'!G37-'Income Statement'!F37)/'Income Statement'!F37 -> 0.075025694 | I35: =AVERAGE(E35:G35) -> -0.026991218 | J35: =AVERAGE(D35:G35) -> -0.083832826 | L35: {=_xlfn.IFS($N$4="Bull",T35, $N$4="Bear",AA35, $N$4="Base",AH35)} -> 0.055 | M35: {=_xlfn.IFS($N$4="Bull",U35, $N$4="Bear",AB35, $N$4="Base",AI35)} -> 0.042 | N35: {=_xlfn.IFS($N$4="Bull",V35, $N$4="Bear",AC35, $N$4="Base",AJ35)} -> 0.035 | O35: {=_xlfn.IFS($N$4="Bull",W35, $N$4="Bear",AD35, $N$4="Base",AK35)} -> 0.02 | P35: {=_xlfn.IFS($N$4="Bull",X35, $N$4="Bear",AE35, $N$4="Base",AL35)} -> -0.03 | AA35: 0.03 | AB35: 0.02 | AC35: 0.01 | AD35: 0 | AE35: -0.05 | AH35: 0.055 | AI35: 0.042 | AJ35: 0.035 | AK35: 0.02 | AL35: -0.03
A37: x | B37: Benefits and expenses
B38: Pharmacy and other service costs | C38: ='Income Statement'!C40/'Income Statement'!C38 -> 0.67528924 | D38: ='Income Statement'!D40/'Income Statement'!D38 -> 0.69153981 | E38: ='Income Statement'!E40/'Income Statement'!E38 -> 0.68522777 | F38: ='Income Statement'!F40/'Income Statement'!F38 -> 0.73854104 | G38: ='Income Statement'!G40/'Income Statement'!G38 -> 0.78206984 | I38: =AVERAGE(E38:G38) -> 0.73527955 | J38: =AVERAGE(C38:G38) -> 0.71453354 | L38: {=_xlfn.IFS($N$4="Bull",T38, $N$4="Bear",AA38, $N$4="Base",AH38)} -> 0.77 | M38: {=_xlfn.IFS($N$4="Bull",V38, $N$4="Bear",AB38, $N$4="Base",AI38)} -> 0.76 | N38: {=_xlfn.IFS($N$4="Bull",W38, $N$4="Bear",AC38, $N$4="Base",AJ38)} -> 0.75 | O38: {=_xlfn.IFS($N$4="Bull",W38, $N$4="Bear",AD38, $N$4="Base",AK38)} -> 0.74 | P38: {=_xlfn.IFS($N$4="Bull",X38, $N$4="Bear",AE38, $N$4="Base",AL38)} -> 0.73 | T38: 0.73 | U38: 0.74 | V38: 0.72 | W38: 0.7075 | X38: 0.7075 | AA38: 0.79 | AB38: 0.795 | AC38: 0.8 | AD38: 0.805 | AE38: 0.81 | AH38: 0.77 | AI38: 0.76 | AJ38: 0.75 | AK38: 0.74 | AL38: 0.73
B39: Medical costs and other benefit expenses | C39: ='Income Statement'!C41/'Income Statement'!C38 -> 0.19279863 | D39: ='Income Statement'!D41/'Income Statement'!D38 -> 0.17841078 | E39: ='Income Statement'!E41/'Income Statement'!E38 -> 0.18583463 | F39: ='Income Statement'!F41/'Income Statement'!F38 -> 0.15639302 | G39: ='Income Statement'!G41/'Income Statement'!G38 -> 0.12495089 | I39: =AVERAGE(E39:G39) -> 0.15572618 | J39: =AVERAGE(C39:G39) -> 0.16767759 | L39: {=_xlfn.IFS($N$4="Bull",T39, $N$4="Bear",AA39, $N$4="Base",AH39)} -> 0.14 | M39: {=_xlfn.IFS($N$4="Bull",U39, $N$4="Bear",AB39, $N$4="Base",AI39)} -> 0.14 | N39: {=_xlfn.IFS($N$4="Bull",V39, $N$4="Bear",AC39, $N$4="Base",AJ39)} -> 0.13 | O39: {=_xlfn.IFS($N$4="Bull",W39, $N$4="Bear",AD39, $N$4="Base",AK39)} -> 0.12 | P39: {=_xlfn.IFS($N$4="Bull",X39, $N$4="Bear",AE39, $N$4="Base",AL39)} -> 0.13 | T39: 0.124 | U39: 0.123 | V39: 0.121 | W39: 0.12 | X39: 0.119 | AA39: 0.13 | AB39: 0.132 | AC39: 0.135 | AD39: 0.137 | AE39: 0.14 | AH39: 0.14 | AI39: 0.14 | AJ39: 0.13 | AK39: 0.12 | AL39: 0.13
B40: Selling, general and administrative expenses | C40: ='Income Statement'!C42/'Income Statement'!C38 -> 0.074851503 | D40: ='Income Statement'!D42/'Income Statement'!D38 -> 0.073046157 | E40: ='Income Statement'!E42/'Income Statement'!E38 -> 0.075907101 | F40: ='Income Statement'!F42/'Income Statement'!F38 -> 0.06006774 | G40: ='Income Statement'!G42/'Income Statement'!G38 -> 0.053172063 | I40: =AVERAGE(E40:G40) -> 0.063048968 | J40: =AVERAGE(C40:G40) -> 0.067408913 | L40: {=_xlfn.IFS($N$4="Bull",T40, $N$4="Bear",AA40, $N$4="Base",AH40)} -> 0.06 | M40: {=_xlfn.IFS($N$4="Bull",U40, $N$4="Bear",AB40, $N$4="Base",AI40)} -> 0.063 | N40: {=_xlfn.IFS($N$4="Bull",V40, $N$4="Bear",AC40, $N$4="Base",AJ40)} -> 0.062 | O40: {=_xlfn.IFS($N$4="Bull",W40, $N$4="Bear",AD40, $N$4="Base",AK40)} -> 0.054 | P40: {=_xlfn.IFS($N$4="Bull",X40, $N$4="Bear",AE40, $N$4="Base",AL40)} -> 0.051 | T40: 0.051 | U40: 0.0495 | V40: 0.048 | W40: 0.047 | X40: 0.047 | AA40: 0.056 | AB40: 0.057 | AC40: 0.058 | AD40: 0.059 | AE40: 0.06 | AH40: 0.06 | AI40: 0.063 | AJ40: 0.062 | AK40: 0.054 | AL40: 0.051
B41: Amortization of acquired intangible assets | C41: ='Income Statement'!C43/'Income Statement'!C38 -> 0.011477613 | D41: ='Income Statement'!D43/'Income Statement'!D38 -> 0.010392431 | E41: ='Income Statement'!E43/'Income Statement'!E38 -> 0.0093155455 | F41: ='Income Statement'!F43/'Income Statement'!F38 -> 0.0068913609 | G41: ='Income Statement'!G43/'Income Statement'!G38 -> 0.0063404874 | I41: =AVERAGE(E41:G41) -> 0.007515798 | J41: =AVERAGE(C41:G41) -> 0.0088834876 | L41: {=_xlfn.IFS($N$4="Bull",T41, $N$4="Bear",AA41, $N$4="Base",AH41)} -> 0.0062 | M41: {=_xlfn.IFS($N$4="Bull",U41, $N$4="Bear",AB41, $N$4="Base",AI41)} -> 0.006 | N41: {=_xlfn.IFS($N$4="Bull",V41, $N$4="Bear",AC41, $N$4="Base",AJ41)} -> 0.0058 | O41: {=_xlfn.IFS($N$4="Bull",W41, $N$4="Bear",AD41, $N$4="Base",AK41)} -> 0.0056 | P41: {=_xlfn.IFS($N$4="Bull",X41, $N$4="Bear",AE41, $N$4="Base",AL41)} -> 0.0056 | T41: 0.0055 | U41: 0.005 | V41: 0.0045 | W41: 0.004 | X41: 0.0038 | AA41: 0.0065 | AB41: 0.0063 | AC41: 0.0061 | AD41: 0.006 | AE41: 0.006 | AH41: 0.0062 | AI41: 0.006 | AJ41: 0.0058 | AK41: 0.0056 | AL41: 0.0056
B42: Debt extinguishment costs | C42: ='Income Statement'!C46/'Income Statement'!C38 -> -0.00080998173 | D42: ='Income Statement'!D46/'Income Statement'!D38 -> 0 | E42: ='Income Statement'!E46/'Income Statement'!E38 -> 0 | F42: ='Income Statement'!F46/'Income Statement'!F38 -> 0 | G42: ='Income Statement'!G46/'Income Statement'!G38 -> 0 | I42: =AVERAGE(E42:G42) -> 0 | J42: =AVERAGE(C42:G42) -> -0.00016199635 | L42: {=_xlfn.IFS($N$4="Bull",T42, $N$4="Bear",AA42, $N$4="Base",AH42)} -> 0 | M42: {=_xlfn.IFS($N$4="Bull",U42, $N$4="Bear",AB42, $N$4="Base",AI42)} -> 0 | N42: {=_xlfn.IFS($N$4="Bull",V42, $N$4="Bear",AC42, $N$4="Base",AJ42)} -> 0 | O42: {=_xlfn.IFS($N$4="Bull",W42, $N$4="Bear",AD42, $N$4="Base",AK42)} -> -0.00016199635 | P42: {=_xlfn.IFS($N$4="Bull",X42, $N$4="Bear",AE42, $N$4="Base",AL42)} -> 0 | T42: 0 | U42: 0 | V42: 0 | W42: 0 | X42: 0 | AA42: 0 | AB42: 0 | AC42: 0 | AD42: -0.0002 | AE42: 0 | AH42: =G42 -> 0 | AI42: =H42 -> 0 | AJ42: =I42 -> 0 | AK42: =J42 -> -0.00016199635 | AL42: =K42 -> 0
B43: Interest expense and other | C43: ='Income Statement'!C47/'Income Statement'!C38 -> -0.006939418 | D43: ='Income Statement'!D47/'Income Statement'!D38 -> -0.0068027211 | E43: ='Income Statement'!E47/'Income Statement'!E38 -> -0.007405321 | F43: ='Income Statement'!F47/'Income Statement'!F38 -> -0.0058068719 | G43: ='Income Statement'!G47/'Income Statement'!G38 -> -0.0051218625 | I43: =AVERAGE(E43:G43) -> -0.0061113518 | J43: =AVERAGE(C43:G43) -> -0.0064152389 | L43: {=_xlfn.IFS($N$4="Bull",T43, $N$4="Bear",AA43, $N$4="Base",AH43)} -> 1272.7944 | M43: {=_xlfn.IFS($N$4="Bull",U43, $N$4="Bear",AB43, $N$4="Base",AI43)} -> 1070.5444 | N43: {=_xlfn.IFS($N$4="Bull",V43, $N$4="Bear",AC43, $N$4="Base",AJ43)} -> 890.56893 | O43: {=_xlfn.IFS($N$4="Bull",W43, $N$4="Bear",AD43, $N$4="Base",AK43)} -> 760.51813 | P43: {=_xlfn.IFS($N$4="Bull",X43, $N$4="Bear",AE43, $N$4="Base",AL43)} -> 664.34232 | T43: ='Debt Schedule'!F266 -> 1272.7944 | U43: ='Debt Schedule'!G266 -> 1070.5444 | V43: ='Debt Schedule'!H266 -> 890.56893 | W43: ='Debt Schedule'!I266 -> 760.51813 | X43: ='Debt Schedule'!J266 -> 664.34232 | AA43: ='Debt Schedule'!F266 -> 1272.7944 | AB43: ='Debt Schedule'!G266 -> 1070.5444 | AC43: ='Debt Schedule'!H266 -> 890.56893 | AD43: ='Debt Schedule'!I266 -> 760.51813 | AE43: ='Debt Schedule'!J266 -> 664.34232 | AH43: ='Debt Schedule'!F266 -> 1272.7944 | AI43: ='Debt Schedule'!G266 -> 1070.5444 | AJ43: ='Debt Schedule'!H266 -> 890.56893 | AK43: ='Debt Schedule'!I266 -> 760.51813 | AL43: ='Debt Schedule'!J266 -> 664.34232
B44: Net gain (loss) on sale of businesses | C44: ='Income Statement'!C48/'Income Statement'!C38 -> 0 | D44: ='Income Statement'!D48/'Income Statement'!D38 -> 0.0092069401 | E44: ='Income Statement'!E48/'Income Statement'!E38 -> -0.007676747 | F44: ='Income Statement'!F48/'Income Statement'!F38 -> 9.7118416e-05 | G44: ='Income Statement'!G48/'Income Statement'!G38 -> 4.7289924e-05 | I44: =AVERAGE(E44:G44) -> -0.0025107795 | J44: =AVERAGE(C44:G44) -> 0.00033492029 | L44: {=_xlfn.IFS($N$4="Bull",T44, $N$4="Bear",AA44, $N$4="Base",AH44)} -> -0.001 | M44: {=_xlfn.IFS($N$4="Bull",U44, $N$4="Bear",AB44, $N$4="Base",AI44)} -> -0.001 | N44: {=_xlfn.IFS($N$4="Bull",V44, $N$4="Bear",AC44, $N$4="Base",AJ44)} -> -0.001 | O44: {=_xlfn.IFS($N$4="Bull",W44, $N$4="Bear",AD44, $N$4="Base",AK44)} -> -0.001 | P44: {=_xlfn.IFS($N$4="Bull",X44, $N$4="Bear",AE44, $N$4="Base",AL44)} -> -0.001 | T44: 0.1 | U44: 0.1 | V44: 0.1 | W44: 0.1 | X44: 0.1 | AA44: 0 | AB44: 0 | AC44: 0 | AD44: 0 | AE44: 0 | AH44: -0.001 | AI44: -0.001 | AJ44: -0.001 | AK44: -0.001 | AL44: -0.001
B45: Net investment losses | C45: ='Income Statement'!C49/'Income Statement'!C38 -> 0.0011259321 | D45: ='Income Statement'!D49/'Income Statement'!D38 -> -0.0027421392 | E45: ='Income Statement'!E49/'Income Statement'!E38 -> -0.00039945715 | F45: ='Income Statement'!F49/'Income Statement'!F38 -> -0.011075546 | G45: ='Income Statement'!G49/'Income Statement'!G38 -> -8.7304474e-05 | I45: =AVERAGE(E45:G45) -> -0.0038541025 | J45: =AVERAGE(C45:G45) -> -0.002635703 | L45: {=_xlfn.IFS($N$4="Bull",T45, $N$4="Bear",AA45, $N$4="Base",AH45)} -> -0.002 | M45: {=_xlfn.IFS($N$4="Bull",U45, $N$4="Bear",AB45, $N$4="Base",AI45)} -> -0.003 | N45: {=_xlfn.IFS($N$4="Bull",V45, $N$4="Bear",AC45, $N$4="Base",AJ45)} -> -0.004 | O45: {=_xlfn.IFS($N$4="Bull",W45, $N$4="Bear",AD45, $N$4="Base",AK45)} -> -0.005 | P45: {=_xlfn.IFS($N$4="Bull",X45, $N$4="Bear",AE45, $N$4="Base",AL45)} -> -0.006 | T45: -0.15 | U45: -0.2 | V45: -0.25 | W45: -0.3 | X45: -0.35 | AA45: -0.15 | AB45: -0.25 | AC45: -0.3 | AD45: -0.45 | AE45: -0.55 | AH45: -0.002 | AI45: -0.003 | AJ45: -0.004 | AK45: -0.005 | AL45: -0.006
A47: x | B47: TOTAL INCOME TAXES | C47: ='Income Statement'!C51/'Income Statement'!C50 -> 0.20156296 | D47: ='Income Statement'!D51/'Income Statement'!D50 -> 0.19238597 | E47: ='Income Statement'!E51/'Income Statement'!E50 -> 0.025575911 | F47: ='Income Statement'!F51/'Income Statement'!F50 -> 0.2829759 | G47: ='Income Statement'!G51/'Income Statement'!G50 -> 0.19187765 | I47: =AVERAGE(E47:G47) -> 0.16680982 | J47: =AVERAGE(C47:G47) -> 0.17887568 | L47: {=_xlfn.IFS($N$4="Bull",T47, $N$4="Bear",AA47, $N$4="Base",AH47)} -> 0.17 | M47: {=_xlfn.IFS($N$4="Bull",U47, $N$4="Bear",AB47, $N$4="Base",AI47)} -> 0.1725 | N47: {=_xlfn.IFS($N$4="Bull",V47, $N$4="Bear",AC47, $N$4="Base",AJ47)} -> 0.175 | O47: {=_xlfn.IFS($N$4="Bull",W47, $N$4="Bear",AD47, $N$4="Base",AK47)} -> 0.1775 | P47: {=_xlfn.IFS($N$4="Bull",X47, $N$4="Bear",AE47, $N$4="Base",AL47)} -> 0.18 | T47: 0.2 | U47: 0.2125 | V47: 0.225 | W47: 0.2375 | X47: 0.25 | AA47: 0.15 | AB47: 0.1525 | AC47: 0.155 | AD47: 0.1575 | AE47: 0.16 | AH47: 0.17 | AI47: 0.1725 | AJ47: 0.175 | AK47: 0.1775 | AL47: 0.18
B49: Less: Net income attributable to noncontrolling interests | C49: ='Income Statement'!C53/'Income Statement'!C52 -> 0.0092336103 | D49: ='Income Statement'!D53/'Income Statement'!D52 -> 0.011562407 | E49: ='Income Statement'!E53/'Income Statement'!E52 -> 0.038719285 | F49: ='Income Statement'!F53/'Income Statement'!F52 -> 0.091053467 | G49: ='Income Statement'!G53/'Income Statement'!G52 -> 0.052639949 | I49: =AVERAGE(E49:G49) -> 0.060804234 | J49: =AVERAGE(C49:G49) -> 0.040641744 | L49: {=_xlfn.IFS($N$4="Bull",T49, $N$4="Bear",AA49, $N$4="Base",AH49)} -> 0.05 | M49: {=_xlfn.IFS($N$4="Bull",U49, $N$4="Bear",AB49, $N$4="Base",AI49)} -> 0.05 | N49: {=_xlfn.IFS($N$4="Bull",V49, $N$4="Bear",AC49, $N$4="Base",AJ49)} -> 0.05 | O49: {=_xlfn.IFS($N$4="Bull",W49, $N$4="Bear",AD49, $N$4="Base",AK49)} -> 0.05 | P49: {=_xlfn.IFS($N$4="Bull",X49, $N$4="Bear",AE49, $N$4="Base",AL49)} -> 0.05 | T49: 0.05 | U49: 0.05 | V49: 0.05 | W49: 0.05 | X49: 0.05 | AA49: 0.05 | AB49: 0.05 | AC49: 0.05 | AD49: 0.05 | AE49: 0.05 | AH49: 0.05 | AI49: 0.05 | AJ49: 0.05 | AK49: 0.05 | AL49: 0.05
B51: Depreciation | C51: =Calcs!C15/'Income Statement'!C38 -> 0.007898758 | D51: =Calcs!D15/'Income Statement'!D38 -> 0.0073733076 | E51: =Calcs!E15/'Income Statement'!E38 -> 0.0062274345 | F51: =Calcs!F15/'Income Statement'!F38 -> 0.0053900721 | G51: =Calcs!G15/'Income Statement'!G38 -> 0.0046998909 | I51: =AVERAGE(E51:G51) -> 0.0054391325 | J51: =AVERAGE(C51:G51) -> 0.0063178926 | L51: {=_xlfn.IFS($N$4="Bull",T51, $N$4="Bear",AA51, $N$4="Base",AH51)} -> 0.0063178926 | M51: {=_xlfn.IFS($N$4="Bull",U51, $N$4="Bear",AB51, $N$4="Base",AI51)} -> 0.0063178926 | N51: {=_xlfn.IFS($N$4="Bull",V51, $N$4="Bear",AC51, $N$4="Base",AJ51)} -> 0.0063178926 | O51: {=_xlfn.IFS($N$4="Bull",W51, $N$4="Bear",AD51, $N$4="Base",AK51)} -> 0.0063178926 | P51: {=_xlfn.IFS($N$4="Bull",X51, $N$4="Bear",AE51, $N$4="Base",AL51)} -> 0.0063178926 | T51: =J51 -> 0.0063178926 | U51: =T51 -> 0.0063178926 | V51: =U51 -> 0.0063178926 | W51: =V51 -> 0.0063178926 | X51: =W51 -> 0.0063178926 | AA51: 0.0062 | AB51: 0.0062 | AC51: 0.0062 | AD51: 0.0062 | AE51: 0.0062 | AH51: =J51 -> 0.0063178926 | AI51: =AH51 -> 0.0063178926 | AJ51: =AI51 -> 0.0063178926 | AK51: =AJ51 -> 0.0063178926 | AL51: =AK51 -> 0.0063178926
B52: Capital Expenditures | C52: =Calcs!C14/'Income Statement'!C38 -> 0.0066292122 | D52: =Calcs!D14/'Income Statement'!D38 -> 0.0071738793 | E52: =Calcs!E14/'Income Statement'!E38 -> 0.0080557192 | F52: =Calcs!F14/'Income Statement'!F38 -> 0.0056895205 | G52: =Calcs!G14/'Income Statement'!G38 -> 0.004408876 | I52: =AVERAGE(E52:G52) -> 0.0060513719 | J52: =AVERAGE(C52:G52) -> 0.0063914414 | L52: {=_xlfn.IFS($N$4="Bull",T52, $N$4="Bear",AA52, $N$4="Base",AH52)} -> 0.0063914414 | M52: {=_xlfn.IFS($N$4="Bull",U52, $N$4="Bear",AB52, $N$4="Base",AI52)} -> 0.0063914414 | N52: {=_xlfn.IFS($N$4="Bull",V52, $N$4="Bear",AC52, $N$4="Base",AJ52)} -> 0.0063914414 | O52: {=_xlfn.IFS($N$4="Bull",W52, $N$4="Bear",AD52, $N$4="Base",AK52)} -> 0.0063914414 | P52: {=_xlfn.IFS($N$4="Bull",X52, $N$4="Bear",AE52, $N$4="Base",AL52)} -> 0.0063914414 | T52: 0.0063914414 | U52: 0.0063914414 | V52: 0.0063914414 | W52: 0.0063914414 | X52: 0.0063914414 | AA52: =J52 -> 0.0063914414 | AB52: =AA52 -> 0.0063914414 | AC52: =AB52 -> 0.0063914414 | AD52: =AC52 -> 0.0063914414 | AE52: =AD52 -> 0.0063914414 | AH52: =J52 -> 0.0063914414 | AI52: =AH52 -> 0.0063914414 | AJ52: =AI52 -> 0.0063914414 | AK52: =AJ52 -> 0.0063914414 | AL52: =AK52 -> 0.0063914414
B53: Total Long Term Debt / Revenue | G53: ='Debt Schedule'!E262/'Income Statement'!G38 -> 0.11229902
B55: Balance Sheet
A56: x | B56: Assets
B57: Cash and cash equivalents | C57: ='Balance Sheet'!C5/'Income Statement'!C38 -> 0.029188065 | D57: ='Balance Sheet'!D5/'Income Statement'!D38 -> 0.032817036 | E57: ='Balance Sheet'!E5/'Income Statement'!E38 -> 0.040058382 | F57: ='Balance Sheet'!F5/'Income Statement'!F38 -> 0.030551835 | G57: ='Balance Sheet'!G5/'Income Statement'!G38 -> 0.027922881 | I57: =AVERAGE(E57:G57) -> 0.032844366 | J57: =AVERAGE(C57:G57) -> 0.03210764 | L57: 0.03 | M57: 0.0275 | N57: 0.025 | O57: 0.0225 | P57: 0.0225
B58: Investments | C58: ='Balance Sheet'!C7/'Income Statement'!C38 -> 0.0052849872 | D58: ='Balance Sheet'!D7/'Income Statement'!D38 -> 0.005013406 | E58: ='Balance Sheet'!E7/'Income Statement'!E38 -> 0.0047371521 | F58: ='Balance Sheet'!F7/'Income Statement'!F38 -> 0.0026909894 | G58: ='Balance Sheet'!G7/'Income Statement'!G38 -> 0.0038413969 | I58: =AVERAGE(E58:G58) -> 0.0037565128 | J58: =AVERAGE(C58:G58) -> 0.0043135863 | L58: 0.003 | M58: 0.0035 | N58: 0.0035 | O58: 0.004 | P58: 0.004
B59: Accounts receivable, net | C59: ='Balance Sheet'!C8/'Income Statement'!C38 -> 0.086576133 | D59: ='Balance Sheet'!D8/'Income Statement'!D38 -> 0.095382127 | E59: ='Balance Sheet'!E8/'Income Statement'!E38 -> 0.090758713 | F59: ='Balance Sheet'!F8/'Income Statement'!F38 -> 0.098036994 | G59: ='Balance Sheet'!G8/'Income Statement'!G38 -> 0.10464896 | I59: =AVERAGE(E59:G59) -> 0.09781489 | J59: =AVERAGE(C59:G59) -> 0.095080586 | L59: 0.095 | M59: 0.0975 | N59: 0.1 | O59: 0.1025 | P59: 0.1025 | T59: `
B60: Inventories | C60: ='Balance Sheet'!C9/'Income Statement'!C40 -> 0.031662314 | D60: ='Balance Sheet'!D9/'Income Statement'!D40 -> 0.038266818 | E60: ='Balance Sheet'!E9/'Income Statement'!E40 -> 0.04218952 | F60: ='Balance Sheet'!F9/'Income Statement'!F40 -> 0.036666685 | G60: ='Balance Sheet'!G9/'Income Statement'!G40 -> 0.034131661 | I60: =AVERAGE(E60:G60) -> 0.037662622 | J60: =AVERAGE(C60:G60) -> 0.0365834 | L60: 0.03 | M60: 0.032 | N60: 0.034 | O60: 0.036 | P60: 0.038
B61: Other current assets | C61: ='Balance Sheet'!C10/'Income Statement'!C38 -> 0.0073702593 | D61: ='Balance Sheet'!D10/'Income Statement'!D38 -> 0.007179419 | E61: ='Balance Sheet'!E10/'Income Statement'!E38 -> 0.011107981 | F61: ='Balance Sheet'!F10/'Income Statement'!F38 -> 0.011055313 | G61: ='Balance Sheet'!G10/'Income Statement'!G38 -> 0.010825755 | I61: =AVERAGE(E61:G61) -> 0.01099635 | J61: =AVERAGE(C61:G61) -> 0.0095077455 | L61: 0.01 | M61: 0.0103 | N61: 0.0106 | O61: 0.0109 | P61: 0.0112
B62: Assets of businesses held for sale | C62: ='Balance Sheet'!C11/'Income Statement'!C38 -> 0.057772952 | D62: ='Balance Sheet'!D11/'Income Statement'!D38 -> 0 | E62: ='Balance Sheet'!E11/'Income Statement'!E38 -> 0.015711981 | F62: ='Balance Sheet'!F11/'Income Statement'!F38 -> 0.028342391 | G62: ='Balance Sheet'!G11/'Income Statement'!G38 -> 0 | I62: =AVERAGE(E62:G62) -> 0.014684791 | J62: =AVERAGE(C62:G62) -> 0.020365465 | L62: 0 | M62: 0 | N62: 0 | O62: 0 | P62: 0
B63: Long-term investments | C63: ='Balance Sheet'!C13/'Income Statement'!C36 -> 0.10686899 | D63: ='Balance Sheet'!D13/'Income Statement'!D36 -> 0.090811269 | E63: ='Balance Sheet'!E13/'Income Statement'!E36 -> 0.092658901 | F63: ='Balance Sheet'!F13/'Income Statement'!F36 -> 0.06145896 | G63: ='Balance Sheet'!G13/'Income Statement'!G36 -> 0.067448348 | I63: =AVERAGE(E63:G63) -> 0.073855403 | J63: =AVERAGE(C63:G63) -> 0.083849294 | L63: 0.080010256 | M63: 0.080010256 | N63: 0.080010256 | O63: 0.080010256 | P63: 0.080010256
B64: Reinsurance recoverables | C64: ='Balance Sheet'!C14/'Income Statement'!C38 -> 0.02855042 | D64: ='Balance Sheet'!D14/'Income Statement'!D38 -> 0.026274679 | E64: ='Balance Sheet'!E14/'Income Statement'!E38 -> 0.024761222 | F64: ='Balance Sheet'!F14/'Income Statement'!F38 -> 0.017716018 | G64: ='Balance Sheet'!G14/'Income Statement'!G38 -> 0.014925427 | I64: =AVERAGE(E64:G64) -> 0.019134222 | J64: =AVERAGE(C64:G64) -> 0.022445553 | L64: 0.013964 | M64: 0.0175 | N64: 0.02 | O64: 0.0225 | P64: 0.025
B65: Property and equipment | C65: ='Balance Sheet'!C15/'Balance Sheet'!C21 -> 0.023836425 | D65: ='Balance Sheet'!D15/'Balance Sheet'!D21 -> 0.026220715 | E65: ='Balance Sheet'!E15/'Balance Sheet'!E21 -> 0.024188111 | F65: ='Balance Sheet'!F15/'Balance Sheet'!F21 -> 0.023440958 | G65: ='Balance Sheet'!G15/'Balance Sheet'!G21 -> 0.023119447 | I65: =AVERAGE(E65:G65) -> 0.023582839 | J65: =AVERAGE(C65:G65) -> 0.024161131 | L65: =Calcs!H16 -> 4321.6993 | M65: =Calcs!I16 -> 4326.5317 | N65: =Calcs!J16 -> 4226.9421 | O65: =Calcs!K16 -> 3951.0496 | P65: =Calcs!L16 -> 3644.2804
B66: Goodwill | C66: ='Balance Sheet'!C16 -> 45811 | D66: ='Balance Sheet'!D16 -> 45811 | E66: ='Balance Sheet'!E16 -> 44259 | F66: ='Balance Sheet'!F16 -> 44370 | G66: ='Balance Sheet'!G16 -> 44924 | I66: =AVERAGE(E66:G66) -> 44517.667 | J66: =AVERAGE(C66:G66) -> 45035 | L66: =$G$66 -> 44924 | M66: =$G$66 -> 44924 | N66: =$G$66 -> 44924 | O66: =$G$66 -> 44924 | P66: =$G$66 -> 44924
B67: Other intangible assets | C67: ='Balance Sheet'!C17/'Income Statement'!C38 -> 0.19590069 | D67: ='Balance Sheet'!D17/'Income Statement'!D38 -> 0.17999513 | E67: ='Balance Sheet'!E17/'Income Statement'!E38 -> 0.158057 | F67: ='Balance Sheet'!F17/'Income Statement'!F38 -> 0.11903885 | G67: ='Balance Sheet'!G17/'Income Statement'!G38 -> 0.10389232 | I67: =AVERAGE(E67:G67) -> 0.12699606 | J67: =AVERAGE(C67:G67) -> 0.1513768 | L67: 0.105 | M67: 0.1075 | N67: 0.11 | O67: 0.1125 | P67: 0.115
B68: Other assets | C68: ='Balance Sheet'!C18/'Income Statement'!C38 -> 0.019560197 | D68: ='Balance Sheet'!D18/'Income Statement'!D38 -> 0.018978927 | E68: ='Balance Sheet'!E18/'Income Statement'!E38 -> 0.017519781 | F68: ='Balance Sheet'!F18/'Income Statement'!F38 -> 0.011273829 | G68: ='Balance Sheet'!G18/'Income Statement'!G38 -> 0.010494725 | I68: =AVERAGE(E68:G68) -> 0.013096112 | J68: =AVERAGE(C68:G68) -> 0.015565492 | L68: 0.01 | M68: 0.009 | N68: 0.008 | O68: 0.007 | P68: 0.0065
B69: Separate account assets | C69: ='Balance Sheet'!C19/'Income Statement'!C38 -> 0.047892324 | D69: ='Balance Sheet'!D19/'Income Statement'!D38 -> 0.040317756 | E69: ='Balance Sheet'!E19/'Income Statement'!E38 -> 0.038050854 | F69: ='Balance Sheet'!F19/'Income Statement'!F38 -> 0.02945116 | G69: ='Balance Sheet'!G19/'Income Statement'!G38 -> 0.027322663 | I69: =AVERAGE(E69:G69) -> 0.031608225 | J69: =AVERAGE(C69:G69) -> 0.036606951 | L69: 0.025 | M69: 0.026 | N69: 0.027 | O69: 0.028 | P69: 0.029
B70: Assets of businesses held for sale, non-current | C70: ='Balance Sheet'!C20/'Income Statement'!C38 -> 0 | D70: ='Balance Sheet'!D20/'Income Statement'!D38 -> 0 | E70: ='Balance Sheet'!E20/'Income Statement'!E38 -> 0.014964279 | F70: ='Balance Sheet'!F20/'Income Statement'!F38 -> 0 | G70: ='Balance Sheet'!G20/'Income Statement'!G38 -> 0 | I70: =AVERAGE(E70:G70) -> 0.0049880931 | J70: =AVERAGE(C70:G70) -> 0.0029928559 | L70: 0 | M70: 0 | N70: 0 | O70: 0 | P70: 0
A72: x | B72: Liabilities
B73: Current insurance and contractholder liabilities | C73: ='Balance Sheet'!C23/'Income Statement'!C38 -> 0.030549524 | D73: ='Balance Sheet'!D23/'Income Statement'!D38 -> 0.029831151 | E73: ='Balance Sheet'!E23/'Income Statement'!E38 -> 0.028238548 | F73: ='Balance Sheet'!F23/'Income Statement'!F38 -> 0.021803084 | G73: ='Balance Sheet'!G23/'Income Statement'!G38 -> 0.02077119 | I73: =AVERAGE(E73:G73) -> 0.023604274 | J73: =AVERAGE(C73:G73) -> 0.026238699 | L73: 0.0205 | M73: 0.02 | N73: 0.0195 | O73: 0.019 | P73: 0.019
B74: Pharmacy and other service costs payable | C74: ='Balance Sheet'!C24/'Income Statement'!C38 -> 0.087943336 | D74: ='Balance Sheet'!D24/'Income Statement'!D38 -> 0.094562255 | E74: ='Balance Sheet'!E24/'Income Statement'!E38 -> 0.10147748 | F74: ='Balance Sheet'!F24/'Income Statement'!F38 -> 0.11518649 | G74: ='Balance Sheet'!G24/'Income Statement'!G38 -> 0.11034194 | I74: =AVERAGE(E74:G74) -> 0.10900197 | J74: =AVERAGE(C74:G74) -> 0.1019023 | L74: 0.1019 | M74: 0.1019 | N74: 0.1019 | O74: 0.1019 | P74: 0.1019
B75: Accounts payable | C75: ='Balance Sheet'!C25/'Income Statement'!C44 -> 0.040055855 | D75: ='Balance Sheet'!D25/'Income Statement'!D44 -> 0.045176698 | E75: ='Balance Sheet'!E25/'Income Statement'!E44 -> 0.045804347 | F75: ='Balance Sheet'!F25/'Income Statement'!F44 -> 0.039099048 | G75: ='Balance Sheet'!G25/'Income Statement'!G44 -> 0.040116673 | I75: =AVERAGE(E75:G75) -> 0.041673356 | J75: =AVERAGE(C75:G75) -> 0.042050524 | L75: 0.04 | M75: 0.041 | N75: 0.042 | O75: 0.043 | P75: 0.044
B76: Accrued expenses and other liabilities | C76: ='Balance Sheet'!C27/'Income Statement'!C40 -> 0.062286798 | D76: ='Balance Sheet'!D27/'Income Statement'!D40 -> 0.064133169 | E76: ='Balance Sheet'!E27/'Income Statement'!E40 -> 0.074401537 | F76: ='Balance Sheet'!F27/'Income Statement'!F40 -> 0.05143308 | G76: ='Balance Sheet'!G27/'Income Statement'!G40 -> 0.042085483 | I76: =AVERAGE(E76:G76) -> 0.055973366 | J76: =AVERAGE(C76:G76) -> 0.058868013 | L76: 0.04 | M76: 0.04 | N76: 0.04 | O76: 0.04 | P76: 0.04
B77: Liabilities of businesses held for sale | C77: ='Balance Sheet'!C31/'Income Statement'!C38 -> 0.036897253 | D77: ='Balance Sheet'!D31/'Income Statement'!D38 -> 0 | E77: ='Balance Sheet'!E31/'Income Statement'!E38 -> 0.010775101 | F77: ='Balance Sheet'!F31/'Income Statement'!F38 -> 0.0097523076 | G77: ='Balance Sheet'!G31/'Income Statement'!G38 -> 0 | I77: =AVERAGE(E77:G77) -> 0.0068424694 | J77: =AVERAGE(C77:G77) -> 0.011484932 | L77: 0 | M77: 0 | N77: 0 | O77: 0 | P77: 0
B78: Non-current insurance and contractholder liabilities | C78: ='Balance Sheet'!C33/'Income Statement'!C38 -> 0.072168798 | D78: ='Balance Sheet'!D33/'Income Statement'!D38 -> 0.06360101 | E78: ='Balance Sheet'!E33/'Income Statement'!E38 -> 0.055842061 | F78: ='Balance Sheet'!F33/'Income Statement'!F38 -> 0.041493843 | G78: ='Balance Sheet'!G33/'Income Statement'!G38 -> 0.036151328 | I78: =AVERAGE(E78:G78) -> 0.044495744 | J78: =AVERAGE(C78:G78) -> 0.053851408 | L78: 0.035 | M78: 0.034 | N78: 0.033 | O78: 0.0325 | P78: 0.0325
B79: Deferred tax liabilities, net | C79: ='Balance Sheet'!C34/'Income Statement'!C38 -> 0.047944025 | D79: ='Balance Sheet'!D34/'Income Statement'!D38 -> 0.042938022 | E79: ='Balance Sheet'!E34/'Income Statement'!E38 -> 0.036734694 | F79: ='Balance Sheet'!F34/'Income Statement'!F38 -> 0.02822504 | G79: ='Balance Sheet'!G34/'Income Statement'!G38 -> 0.02599127 | I79: =AVERAGE(E79:G79) -> 0.030317001 | J79: =AVERAGE(C79:G79) -> 0.03636661 | L79: 0.025 | M79: 0.024 | N79: 0.023 | O79: 0.0225 | P79: 0.0225
B80: Other non-current liabilities | C80: ='Balance Sheet'!C35/'Income Statement'!C38 -> 0.021611002 | D80: ='Balance Sheet'!D35/'Income Statement'!D38 -> 0.017405659 | E80: ='Balance Sheet'!E35/'Income Statement'!E38 -> 0.017622206 | F80: ='Balance Sheet'!F35/'Income Statement'!F38 -> 0.013009821 | G80: ='Balance Sheet'!G35/'Income Statement'!G38 -> 0.015416515 | I80: =AVERAGE(E80:G80) -> 0.015349514 | J80: =AVERAGE(C80:G80) -> 0.017013041 | L80: 0.015 | M80: 0.0148 | N80: 0.0145 | O80: 0.0145 | P80: 0.0145
B81: Separate account liabilities | C81: ='Balance Sheet'!C67/'Income Statement'!C38 -> 0.047892324 | D81: ='Balance Sheet'!D67/'Income Statement'!D38 -> 0.040317756 | E81: ='Balance Sheet'!E67/'Income Statement'!E38 -> 0.038050854 | F81: ='Balance Sheet'!F67/'Income Statement'!F38 -> 0.02945116 | G81: ='Balance Sheet'!G67/'Income Statement'!G38 -> 0.027322663 | I81: =AVERAGE(E81:G81) -> 0.031608225 | J81: =AVERAGE(C81:G81) -> 0.036606951 | L81: 0.0265 | M81: 0.026 | N81: 0.0255 | O81: 0.025 | P81: 0.025
B82: Liabilities of businesses held for sale, non-current | C82: ='Balance Sheet'!C68/'Income Statement'!C38 -> 0 | D82: ='Balance Sheet'!D68/'Income Statement'!D38 -> 0 | E82: ='Balance Sheet'!E68/'Income Statement'!E38 -> 0.0030266561 | F82: ='Balance Sheet'!F68/'Income Statement'!F38 -> 0 | G82: ='Balance Sheet'!G68/'Income Statement'!G38 -> 0 | I82: =AVERAGE(E82:G82) -> 0.0010088854 | J82: =AVERAGE(C82:G82) -> 0.00060533122 | L82: 0 | M82: 0 | N82: 0 | O82: 0 | P82: 0
A84: x | B84: Shareholders' equity
B85: Redeemable noncontrolling interests | C85: ='Balance Sheet'!C71 -> 54 | D85: ='Balance Sheet'!D71 -> 66 | E85: ='Balance Sheet'!E71 -> 107 | F85: ='Balance Sheet'!F71 -> 0 | G85: ='Balance Sheet'!G71 -> 0 | I85: =AVERAGE(E85:G85) -> 35.666667 | J85: =AVERAGE(C85:G85) -> 45.4 | L85: =G85 -> 0 | M85: =L85 -> 0 | N85: =M85 -> 0 | O85: =N85 -> 0 | P85: =O85 -> 0
B86: Common stock | C86: ='Balance Sheet'!C72 -> 4 | D86: ='Balance Sheet'!D72 -> 4 | E86: ='Balance Sheet'!E72 -> 4 | F86: ='Balance Sheet'!F72 -> 4 | G86: ='Balance Sheet'!G72 -> 4 | I86: =AVERAGE(E86:G86) -> 4 | J86: =AVERAGE(C86:G86) -> 4 | L86: =G86 -> 4 | M86: =L86 -> 4 | N86: =M86 -> 4 | O86: =N86 -> 4 | P86: =O86 -> 4
B87: Additional paid-in capital | C87: ='Balance Sheet'!C73 -> 29574 | D87: ='Balance Sheet'!D73 -> 30233 | E87: ='Balance Sheet'!E73 -> 30669 | F87: ='Balance Sheet'!F73 -> 31288 | G87: ='Balance Sheet'!G73 -> 31790 | I87: =AVERAGE(E87:G87) -> 31249 | J87: =AVERAGE(C87:G87) -> 30710.8 | L87: =G87+648 -> 32438 | M87: =L87 -> 32438 | N87: =M87 -> 32438 | O87: =N87 -> 32438 | P87: =O87 -> 32438
B88: Accumulated other comprehensive loss | C88: ='Balance Sheet'!C74 -> -884 | D88: ='Balance Sheet'!D74 -> -1395 | E88: ='Balance Sheet'!E74 -> -1864 | F88: ='Balance Sheet'!F74 -> -2341 | G88: ='Balance Sheet'!G74 -> -2806 | I88: =AVERAGE(E88:G88) -> -2337 | J88: =AVERAGE(C88:G88) -> -1858 | L88: =G88 -> -2806 | M88: =L88 -> -2806 | N88: =M88 -> -2806 | O88: =N88 -> -2806 | P88: =O88 -> -2806
B89: Retained earnings | C89: ='Balance Sheet'!C75 -> 32593 | D89: ='Balance Sheet'!D75 -> 37874 | E89: ='Balance Sheet'!E75 -> 41652 | F89: ='Balance Sheet'!F75 -> 43519 | G89: ='Balance Sheet'!G75 -> 47865 | I89: =AVERAGE(E89:G89) -> 44345.333 | J89: =AVERAGE(C89:G89) -> 40700.6 | L89: =Calcs!H9 -> 51876.584 | M89: =Calcs!I9 -> 60372.402 | N89: =Calcs!J9 -> 75236.733 | O89: =Calcs!K9 -> 99399.826 | P89: =Calcs!L9 -> 125976.25
B90: Less: Treasury stock, at cost | C90: ='Balance Sheet'!C76 -> -14175 | D90: ='Balance Sheet'!D76 -> -21844 | E90: ='Balance Sheet'!E76 -> -24238 | F90: ='Balance Sheet'!F76 -> -31437 | G90: ='Balance Sheet'!G76 -> -35140 | I90: =AVERAGE(E90:G90) -> -30271.667 | J90: =AVERAGE(C90:G90) -> -25366.8 | L90: =G90 -> -35140 | M90: =L90 -> -35140 | N90: =M90 -> -35140 | O90: =N90 -> -35140 | P90: =O90 -> -35140
B91: Other noncontrolling interests | C91: ='Balance Sheet'!C78 -> 18 | D91: ='Balance Sheet'!D78 -> 13 | E91: ='Balance Sheet'!E78 -> 21 | F91: ='Balance Sheet'!F78 -> 210 | G91: ='Balance Sheet'!G78 -> 161 | I91: =AVERAGE(E91:G91) -> 130.66667 | J91: =AVERAGE(C91:G91) -> 84.6 | L91: =G91 -> 161 | M91: =L91 -> 161 | N91: =M91 -> 161 | O91: =N91 -> 161 | P91: =O91 -> 161

Sheet Income Statement
B2: Consolidated Statements of Income | C2: Historical | H2: Projected
B3: $ in Millions except Per Share Data | C3: 2021 | D3: =C3+1 -> 2022 | E3: =D3+1 -> 2023 | F3: =E3+1 -> 2024 | G3: =F3+1 -> 2025 | H3: =G3+1 -> 2026 | I3: =H3+1 -> 2027 | J3: =I3+1 -> 2028 | K3: =J3+1 -> 2029 | L3: =K3+1 -> 2030
B4: Revenues
B5: Products ( Pharmacy Revenues) (ASC 606)
B6: Network Revenues | C6: 64992 | D6: 64946 | E6: 67514 | F6: 105340 | G6: 125573 | H6: =(Assumptions!L6*'Income Statement'!G6)+'Income Statement'!G6 -> 143153.22 | I6: =(Assumptions!M6*'Income Statement'!H6)+'Income Statement'!H6 -> 160331.61 | J6: =(Assumptions!N6*'Income Statement'!I6)+'Income Statement'!I6 -> 173158.13 | K6: =(Assumptions!O6*'Income Statement'!J6)+'Income Statement'!J6 -> 184413.41 | L6: =(Assumptions!P6*'Income Statement'!K6)+'Income Statement'!K6 -> 196400.29
B7: Home Delivery and Specialty | C7: 54391 | D7: 61283 | E7: 65732 | F7: 72476 | G7: 80492 | H7: =(Assumptions!L7*'Income Statement'!G7)+'Income Statement'!G7 -> 89587.596 | I7: =(Assumptions!M7*'Income Statement'!H7)+'Income Statement'!H7 -> 98546.356 | J7: =(Assumptions!N7*'Income Statement'!I7)+'Income Statement'!I7 -> 107908.26 | K7: =(Assumptions!O7*'Income Statement'!J7)+'Income Statement'!J7 -> 116540.92 | L7: =(Assumptions!P7*'Income Statement'!K7)+'Income Statement'!K7 -> 125864.19
B8: Other Revenues | C8: 6428 | D8: 6753 | E8: 9047 | F8: 11545 | G8: 13329 | H8: =(Assumptions!L8*'Income Statement'!G8)+'Income Statement'!G8 -> 15188.396 | I8: =(Assumptions!M8*'Income Statement'!H8)+'Income Statement'!H8 -> 16980.626 | J8: =(Assumptions!N8*'Income Statement'!I8)+'Income Statement'!I8 -> 18848.495 | K8: =(Assumptions!O8*'Income Statement'!J8)+'Income Statement'!J8 -> 20827.587 | L8: =(Assumptions!P8*'Income Statement'!K8)+'Income Statement'!K8 -> 23014.484
B9: Other Operations | C9: 0 | D9: 0 | E9: 0 | F9: 60 | G9: 54 | H9: =(Assumptions!L9*'Income Statement'!G9)+'Income Statement'!G9 -> 48.6 | I9: =(Assumptions!M9*'Income Statement'!H9)+'Income Statement'!H9 -> 43.74 | J9: =(Assumptions!N9*'Income Statement'!I9)+'Income Statement'!I9 -> 39.366 | K9: =(Assumptions!O9*'Income Statement'!J9)+'Income Statement'!J9 -> 35.4294 | L9: =(Assumptions!P9*'Income Statement'!K9)+'Income Statement'!K9 -> 31.88646
B10: Intercompany Eliminatioons | C10: -4398 | D10: -4416 | E10: -5050 | F10: -4059 | G10: -2776 | H10: =(Assumptions!L10*'Income Statement'!G10)+'Income Statement'!G10 -> -2095.88 | I10: =(Assumptions!M10*'Income Statement'!H10)+'Income Statement'!H10 -> -1666.2246 | J10: =(Assumptions!N10*'Income Statement'!I10)+'Income Statement'!I10 -> -1379.634 | K10: =(Assumptions!O10*'Income Statement'!J10)+'Income Statement'!J10 -> -1214.0779 | L10: =(Assumptions!P10*'Income Statement'!K10)+'Income Statement'!K10 -> -1068.3885
B11: Total Pharmacy Revenue | C11: =SUM(C6:C10) -> 121413 | D11: =SUM(D6:D10) -> 128566 | E11: =SUM(E6:E10) -> 137243 | F11: =SUM(F6:F10) -> 185362 | G11: =SUM(G6:G10) -> 216672 | H11: =SUM(H6:H10) -> 245881.93 | I11: =SUM(I6:I10) -> 274236.1 | J11: =SUM(J6:J10) -> 298574.62 | ... L11: =SUM(L6:L10) -> 344242.46
B12: Insurance Premiums (ASC 944)
B13: Cigna Healthcare
B14: U.S Commercial
B15: Insured | C15: 14315 | D15: 15199 | E15: 16490 | F15: 17576 | G15: 18852 | H15: =(Assumptions!L15*'Income Statement'!G15)+'Income Statement'!G15 -> 19417.56 | I15: =(Assumptions!M15*'Income Statement'!H15)+'Income Statement'!H15 -> 20077.757 | J15: =(Assumptions!N15*'Income Statement'!I15)+'Income Statement'!I15 -> 20760.401 | K15: =(Assumptions!O15*'Income Statement'!J15)+'Income Statement'!J15 -> 21798.421 | L15: =(Assumptions!P15*'Income Statement'!K15)+'Income Statement'!K15 -> 22888.342
B16: Stop Loss | C16: 4868 | D16: 5461 | E16: 6143 | F16: 6744 | G16: 7599 | H16: =(Assumptions!L16*'Income Statement'!G16)+'Income Statement'!G16 -> 8548.875 | I16: =(Assumptions!M16*'Income Statement'!H16)+'Income Statement'!H16 -> 9531.9956 | J16: =(Assumptions!N16*'Income Statement'!I16)+'Income Statement'!I16 -> 10580.515 | K16: =(Assumptions!O16*'Income Statement'!J16)+'Income Statement'!J16 -> 11691.469 | L16: =(Assumptions!P16*'Income Statement'!K16)+'Income Statement'!K16 -> 12919.074
B17: Other | C17: 1290 | D17: 1418 | E17: 5088 | F17: 3951 | G17: 3371 | H17: =(Assumptions!L17*'Income Statement'!G17)+'Income Statement'!G17 -> 2865.35 | I17: =(Assumptions!M17*'Income Statement'!H17)+'Income Statement'!H17 -> 2578.815 | J17: =(Assumptions!N17*'Income Statement'!I17)+'Income Statement'!I17 -> 2372.5098 | K17: =(Assumptions!O17*'Income Statement'!J17)+'Income Statement'!J17 -> 2253.8843 | L17: =(Assumptions!P17*'Income Statement'!K17)+'Income Statement'!K17 -> 2141.1901
B18: U.S Government
B19: Medicare Advantage | C19: 8362 | D19: 7896 | E19: 8771 | F19: 8679 | G19: 2363 | H19: =(Assumptions!L19*'Income Statement'!G19)+'Income Statement'!G19 -> 2363 | I19: =(Assumptions!M19*'Income Statement'!H19)+'Income Statement'!H19 -> 2363 | J19: =(Assumptions!N19*'Income Statement'!I19)+'Income Statement'!I19 -> 2363 | K19: =(Assumptions!O19*'Income Statement'!J19)+'Income Statement'!J19 -> 2363 | L19: =(Assumptions!P19*'Income Statement'!K19)+'Income Statement'!K19 -> 2363
B20: Medicare Part D | C20: 1499 | D20: 1224 | E20: 0 | F20: 0 | G20: 0 | H20: =(Assumptions!L20*'Income Statement'!G20)+'Income Statement'!G20 -> 0 | I20: =(Assumptions!M20*'Income Statement'!H20)+'Income Statement'!H20 -> 0 | J20: =(Assumptions!N20*'Income Statement'!I20)+'Income Statement'!I20 -> 0 | K20: =(Assumptions!O20*'Income Statement'!J20)+'Income Statement'!J20 -> 0 | L20: =(Assumptions!P20*'Income Statement'!K20)+'Income Statement'!K20 -> 0
B21: Other | C21: 4815 | D21: 3990 | E21: 4095 | F21: 4938 | G21: 3366 | H21: =(Assumptions!L21*'Income Statement'!G21)+'Income Statement'!G21 -> 3433.32 | I21: =(Assumptions!M21*'Income Statement'!H21)+'Income Statement'!H21 -> 3501.9864 | J21: =(Assumptions!N21*'Income Statement'!I21)+'Income Statement'!I21 -> 3572.0261 | K21: =(Assumptions!O21*'Income Statement'!J21)+'Income Statement'!J21 -> 3643.4667 | L21: =(Assumptions!P21*'Income Statement'!K21)+'Income Statement'!K21 -> 3716.336
B22: International Health | C22: 2588 | D22: 2906 | E22: 3295 | F22: 3624 | G22: 4126 | H22: =(Assumptions!L22*'Income Statement'!G22)+'Income Statement'!G22 -> 4167.26 | I22: =(Assumptions!M22*'Income Statement'!H22)+'Income Statement'!H22 -> 4208.9326 | J22: =(Assumptions!N22*'Income Statement'!I22)+'Income Statement'!I22 -> 4293.1113 | K22: =(Assumptions!O22*'Income Statement'!J22)+'Income Statement'!J22 -> 4378.9735 | L22: =(Assumptions!P22*'Income Statement'!K22)+'Income Statement'!K22 -> 4422.7632
B23: Total Cigna Healthcare | C23: =SUM(C15:C22) -> 37737 | D23: =SUM(D15:D22) -> 38094 | E23: =SUM(E15:E22) -> 43882 | F23: =SUM(F15:F22) -> 45512 | G23: =SUM(G15:G22) -> 39677 | H23: =SUM(H15:H22) -> 40795.365 | I23: =SUM(I15:I22) -> 42262.487 | J23: =SUM(J15:J22) -> 43941.563 | ... L23: =SUM(L15:L22) -> 48450.705
B24: Divested International Businesses | C24: 3205 | D24: 1596 | E24: 0 | F24: 0 | G24: 0 | H24: =(Assumptions!L24*'Income Statement'!G24)+'Income Statement'!G24 -> 0 | I24: =(Assumptions!M24*'Income Statement'!H24)+'Income Statement'!H24 -> 0 | J24: =(Assumptions!N24*'Income Statement'!I24)+'Income Statement'!I24 -> 0 | K24: =(Assumptions!O24*'Income Statement'!J24)+'Income Statement'!J24 -> 0 | L24: =(Assumptions!P24*'Income Statement'!K24)+'Income Statement'!K24 -> 0
B25: Domestic Disability; Life and accident | C25: 0 | D25: 0 | E25: 0 | F25: 0 | G25: 0 | H25: =(Assumptions!L25*'Income Statement'!G25)+'Income Statement'!G25 -> 0 | I25: =(Assumptions!M25*'Income Statement'!H25)+'Income Statement'!H25 -> 0 | J25: =(Assumptions!N25*'Income Statement'!I25)+'Income Statement'!I25 -> 0 | K25: =(Assumptions!O25*'Income Statement'!J25)+'Income Statement'!J25 -> 0 | L25: =(Assumptions!P25*'Income Statement'!K25)+'Income Statement'!K25 -> 0
B26: Other | C26: 221 | D26: 224 | E26: 281 | F26: 380 | G26: 288 | H26: =(Assumptions!L26*'Income Statement'!G26)+'Income Statement'!G26 -> 319.12115 | I26: =(Assumptions!M26*'Income Statement'!H26)+'Income Statement'!H26 -> 353.60524 | J26: =(Assumptions!N26*'Income Statement'!I26)+'Income Statement'!I26 -> 391.81567 | K26: =(Assumptions!O26*'Income Statement'!J26)+'Income Statement'!J26 -> 434.15509 | L26: =(Assumptions!P26*'Income Statement'!K26)+'Income Statement'!K26 -> 481.0697
B27: Intercompany Eliminations | C27: -9 | D27: 1 | E27: 74 | F27: 104 | G27: 296 | H27: =(Assumptions!L27*'Income Statement'!G27)+'Income Statement'!G27 -> 296 | I27: =(Assumptions!M27*'Income Statement'!H27)+'Income Statement'!H27 -> 296 | J27: =(Assumptions!N27*'Income Statement'!I27)+'Income Statement'!I27 -> 296 | K27: =(Assumptions!O27*'Income Statement'!J27)+'Income Statement'!J27 -> 296 | L27: =(Assumptions!P27*'Income Statement'!K27)+'Income Statement'!K27 -> 296
B28: Total Premiums | C28: =SUM(C23:C27) -> 41154 | D28: =SUM(D23:D27) -> 39915 | E28: =SUM(E23:E27) -> 44237 | F28: =SUM(F23:F27) -> 45996 | G28: =SUM(G23:G27) -> 40261 | H28: =SUM(H23:H27) -> 41410.486 | I28: =SUM(I23:I27) -> 42912.092 | J28: =SUM(J23:J27) -> 44629.379 | ... L28: =SUM(L23:L27) -> 49227.774
B29: Service (Fees)(ASC 606)
B30: Evernorth Health Services | C30: 6070 | D30: 7234 | E30: 10965 | F30: 12591 | G30: 15417 | H30: =(Assumptions!L30*'Income Statement'!G30)+'Income Statement'!G30 -> 18500.4 | I30: =(Assumptions!M30*'Income Statement'!H30)+'Income Statement'!H30 -> 22292.982 | J30: =(Assumptions!N30*'Income Statement'!I30)+'Income Statement'!I30 -> 26974.508 | K30: =(Assumptions!O30*'Income Statement'!J30)+'Income Statement'!J30 -> 32774.027 | L30: =(Assumptions!P30*'Income Statement'!K30)+'Income Statement'!K30 -> 39984.314
B31: Cigna Healthcare | C31: 5743 | D31: 6053 | E31: 6669 | F31: 6988 | G31: 7154 | H31: =(Assumptions!L31*'Income Statement'!G31)+'Income Statement'!G31 -> 7382.928 | I31: =(Assumptions!M31*'Income Statement'!H31)+'Income Statement'!H31 -> 7633.9476 | J31: =(Assumptions!N31*'Income Statement'!I31)+'Income Statement'!I31 -> 7946.9394 | K31: =(Assumptions!O31*'Income Statement'!J31)+'Income Statement'!J31 -> 8384.0211 | L31: =(Assumptions!P31*'Income Statement'!K31)+'Income Statement'!K31 -> 8845.1422
B32: Other Operations | C32: 19 | D32: 9 | E32: 10 | F32: 79 | G32: 34 | H32: =(Assumptions!L32*'Income Statement'!G32)+'Income Statement'!G32 -> 34 | I32: =(Assumptions!M32*'Income Statement'!H32)+'Income Statement'!H32 -> 34 | J32: =(Assumptions!N32*'Income Statement'!I32)+'Income Statement'!I32 -> 34 | K32: =(Assumptions!O32*'Income Statement'!J32)+'Income Statement'!J32 -> 34 | L32: =(Assumptions!P32*'Income Statement'!K32)+'Income Statement'!K32 -> 34
B33: Other Revenues | C33: 197 | D33: 167 | E33: 0 | F33: 0 | G33: 0 | H33: =(Assumptions!L33*'Income Statement'!G33)+'Income Statement'!G33 -> 0 | I33: =(Assumptions!M33*'Income Statement'!H33)+'Income Statement'!H33 -> 0 | J33: =(Assumptions!N33*'Income Statement'!I33)+'Income Statement'!I33 -> 0 | K33: =(Assumptions!O33*'Income Statement'!J33)+'Income Statement'!J33 -> 0 | L33: =(Assumptions!P33*'Income Statement'!K33)+'Income Statement'!K33 -> 0
B34: Intercompany Eliminations | C34: -2067 | D34: -2583 | E34: -5025 | F34: -4868 | G34: -5684 | H34: =(Assumptions!L34*'Income Statement'!G34)+'Income Statement'!G34 -> -5684 | I34: =(Assumptions!M34*'Income Statement'!H34)+'Income Statement'!H34 -> -5684 | J34: =(Assumptions!N34*'Income Statement'!I34)+'Income Statement'!I34 -> -5684 | K34: =(Assumptions!O34*'Income Statement'!J34)+'Income Statement'!J34 -> -5684 | L34: =(Assumptions!P34*'Income Statement'!K34)+'Income Statement'!K34 -> -5684
B35: Total Fees and other Revenues | C35: =SUM(C30:C34) -> 9962 | D35: =SUM(D30:D34) -> 10880 | E35: =SUM(E30:E34) -> 12619 | F35: =SUM(F30:F34) -> 14790 | G35: =SUM(G30:G34) -> 16921 | H35: =SUM(H30:H34) -> 20233.328 | I35: =SUM(I30:I34) -> 24276.93 | J35: =SUM(J30:J34) -> 29271.448 | ... L35: =SUM(L30:L34) -> 43179.456
B36: Total Revenues from External Customers | C36: =C35+C28+C11 -> 172529 | D36: =D35+D28+D11 -> 179361 | E36: =E35+E28+E11 -> 194099 | F36: =F35+F28+F11 -> 246148 | G36: =G35+G28+G11 -> 273854 | H36: =H35+H28+H11 -> 307525.75 | I36: =I35+I28+I11 -> 341425.13 | J36: =J35+J28+J11 -> 372475.45 | ... L36: =L35+L28+L11 -> 436649.69
B37: Net investment income | C37: 1549 | D37: 1155 | E37: 1166 | F37: 973 | G37: 1046 | H37: =(Assumptions!L35*'Income Statement'!G37)+'Income Statement'!G37 -> 1103.53 | I37: =(Assumptions!M35*'Income Statement'!H37)+'Income Statement'!H37 -> 1149.8783 | J37: =(Assumptions!N35*'Income Statement'!I37)+'Income Statement'!I37 -> 1190.124 | K37: =(Assumptions!O35*'Income Statement'!J37)+'Income Statement'!J37 -> 1213.9265 | L37: =(Assumptions!P35*'Income Statement'!K37)+'Income Statement'!K37 -> 1177.5087
A38: x | B38: TOTAL REVENUES | C38: =C36+C37 -> 174078 | D38: =D36+D37 -> 180516 | E38: =E36+E37 -> 195265 | F38: =F36+F37 -> 247121 | G38: =G36+G37 -> 274900 | H38: =H36+H37 -> 308629.28 | I38: =I36+I37 -> 342575 | J38: =J36+J37 -> 373665.57 | ... L38: =L36+L37 -> 437827.2
B39: Benefits and expenses
B40: Pharmacy and other service costs | C40: 117553 | D40: 124834 | E40: 133801 | F40: 182509 | G40: 214991 | H40: =Assumptions!L38*'Income Statement'!H38 -> 237644.54 | I40: =Assumptions!M38*'Income Statement'!I38 -> 260357 | J40: =Assumptions!N38*'Income Statement'!J38 -> 280249.18 | K40: =Assumptions!O38*'Income Statement'!K38 -> 299096.62 | L40: =Assumptions!P38*'Income Statement'!L38 -> 319613.86
B41: Medical costs and other benefit expenses | C41: 33562 | D41: 32206 | E41: 36287 | F41: 38648 | G41: 34349 | H41: =Assumptions!L39*'Income Statement'!H38 -> 43208.099 | I41: =Assumptions!M39*'Income Statement'!I38 -> 47960.5 | J41: =Assumptions!N39*'Income Statement'!J38 -> 48576.524 | K41: =Assumptions!O39*'Income Statement'!K38 -> 48502.154 | L41: =Assumptions!P39*'Income Statement'!L38 -> 56917.536
B42: Selling, general and administrative expenses | C42: 13030 | D42: 13186 | E42: 14822 | F42: 14844 | G42: 14617 | H42: =Assumptions!L40*'Income Statement'!H38 -> 18517.757 | I42: =Assumptions!M40*'Income Statement'!I38 -> 21582.225 | J42: =Assumptions!N40*'Income Statement'!J38 -> 23167.265 | K42: =Assumptions!O40*'Income Statement'!K38 -> 21825.969 | L42: =Assumptions!P40*'Income Statement'!L38 -> 22329.187
B43: Amortization of acquired intangible assets | C43: 1998 | D43: 1876 | E43: 1819 | F43: 1703 | G43: 1743 | H43: =Assumptions!L41*'Income Statement'!H38 -> 1913.5015 | I43: =Assumptions!M41*'Income Statement'!I38 -> 2055.45 | J43: =Assumptions!N41*'Income Statement'!J38 -> 2167.2603 | K43: =Assumptions!O41*'Income Statement'!K38 -> 2263.4339 | L43: =Assumptions!P41*'Income Statement'!L38 -> 2451.8323
A44: x | B44: TOTAL BENEFITS AND EXPENSES | C44: =SUM(C40:C43) -> 166143 | D44: =SUM(D40:D43) -> 172102 | E44: =SUM(E40:E43) -> 186729 | F44: =SUM(F40:F43) -> 237704 | G44: =SUM(G40:G43) -> 265700 | H44: =SUM(H40:H43) -> 301283.9 | I44: =SUM(I40:I43) -> 331955.18 | J44: =SUM(J40:J43) -> 354160.23 | ... L44: =SUM(L40:L43) -> 401312.41
A45: x | B45: Income from operations | C45: =C38-C44 -> 7935 | D45: =D38-D44 -> 8414 | E45: =E38-E44 -> 8536 | F45: =F38-F44 -> 9417 | G45: =G38-G44 -> 9200 | H45: =H38-H44 -> 7345.3768 | I45: =I38-I44 -> 10619.825 | J45: =J38-J44 -> 19505.343 | ... L45: =L38-L44 -> 36514.788
B46: Debt extinguishment costs | C46: -141 | D46: 0 | E46: 0 | F46: 0 | G46: 0 | H46: =Assumptions!L42*H38 -> 0 | I46: =Assumptions!M42*I38 -> 0 | J46: =Assumptions!N42*J38 -> 0 | K46: =Assumptions!O42*K38 -> -65.476431 | L46: =Assumptions!P42*L38 -> 0
B47: Interest expense and other | C47: -1208 | D47: -1228 | E47: -1446 | F47: -1435 | G47: -1408 | H47: =-'Debt Schedule'!F267+'Debt Schedule'!F277 -> -1331.8741 | I47: ='Debt Schedule'!G267 -> 1557.6848 | J47: ='Debt Schedule'!H267 -> 1328.6379 | K47: ='Debt Schedule'!I267 -> 917.95243 | L47: ='Debt Schedule'!J267 -> 666.07292
B48: Net gain (loss) on sale of businesses | C48: 0 | D48: 1662 | E48: -1499 | F48: 24 | G48: 13 | H48: =Assumptions!L44*'Income Statement'!H38 -> -308.62928 | I48: =Assumptions!M44*'Income Statement'!I38 -> -342.575 | J48: =Assumptions!N44*'Income Statement'!J38 -> -373.66557 | K48: =Assumptions!O44*'Income Statement'!K38 -> -404.18462 | L48: =Assumptions!P44*'Income Statement'!L38 -> -437.8272
B49: Net investment losses | C49: 196 | D49: -495 | E49: -78 | F49: -2737 | G49: -24 | H49: =Assumptions!L45*'Income Statement'!H38 -> -617.25855 | I49: =Assumptions!M45*'Income Statement'!I38 -> -1027.725 | J49: =Assumptions!N45*'Income Statement'!J38 -> -1494.6623 | K49: =Assumptions!O45*'Income Statement'!K38 -> -2020.9231 | L49: =Assumptions!P45*'Income Statement'!L38 -> -2626.9632
A50: x | B50: Income before income taxes | C50: =SUM(C45:C49) -> 6782 | D50: =SUM(D45:D49) -> 8353 | E50: =SUM(E45:E49) -> 5513 | F50: =SUM(F45:F49) -> 5269 | G50: =SUM(G45:G49) -> 7781 | H50: =SUM(H45:H49) -> 5087.6148 | I50: =SUM(I45:I49) -> 10807.21 | J50: =SUM(J45:J49) -> 18965.653 | ... L50: =SUM(L45:L49) -> 34116.071
B51: TOTAL INCOME TAXES | C51: 1367 | D51: 1607 | E51: 141 | F51: 1491 | G51: 1493 | H51: =Assumptions!L47*'Income Statement'!H50 -> 864.89452 | I51: =Assumptions!M47*'Income Statement'!I50 -> 1864.2437 | J51: =Assumptions!N47*'Income Statement'!J50 -> 3318.9893 | K51: =Assumptions!O47*'Income Statement'!K50 -> 5488.9765 | L51: =Assumptions!P47*'Income Statement'!L50 -> 6140.8928
A52: x | B52: Net income | C52: =C50-C51 -> 5415 | D52: =D50-D51 -> 6746 | E52: =E50-E51 -> 5372 | F52: =F50-F51 -> 3778 | G52: =G50-G51 -> 6288 | H52: =H50-H51 -> 4222.7203 | I52: =I50-I51 -> 8942.9662 | J52: =J50-J51 -> 15646.664 | ... L52: =L50-L51 -> 27975.178
B53: Less: Net income attributable to noncontrolling interests | C53: 50 | D53: 78 | E53: 208 | F53: 344 | G53: 331 | H53: =Assumptions!L49*'Income Statement'!H52 -> 211.13601 | I53: =Assumptions!M49*'Income Statement'!I52 -> 447.14831 | J53: =Assumptions!N49*'Income Statement'!J52 -> 782.33318 | K53: =Assumptions!O49*'Income Statement'!K52 -> 1271.7417 | L53: =Assumptions!P49*'Income Statement'!L52 -> 1398.7589
A54: x | B54: SHAREHOLDERS' NET INCOME | C54: =C52-C53 -> 5365 | D54: =D52-D53 -> 6668 | E54: =E52-E53 -> 5164 | F54: =F52-F53 -> 3434 | G54: =G52-G53 -> 5957 | H54: =H52-H53 -> 4011.5843 | I54: =I52-I53 -> 8495.8178 | J54: =J52-J53 -> 14864.33 | ... L54: =L52-L53 -> 26576.419
B55: Shareholders' net income per share
B56: Basic (in dollars per share) | C56: 15.87 | D56: 21.54 | E56: 17.57 | F56: 12.25 | G56: 22.33 | H56: =H52/Comps!$E$4 -> 1.6025504 | I56: =I52/Comps!$E$4 -> 3.393915 | J56: =J52/Comps!$E$4 -> 5.9380128 | K56: =K52/Comps!$E$4 -> 9.6526888 | L56: =L52/Comps!$E$4 -> 10.616766
B57: Diluted (in dollars per share) | C57: 15.73 | D57: 21.3 | E57: 17.39 | F57: 12.12 | G57: 22.18 | H57: 22.18 | I57: 22.18 | J57: 22.18 | K57: 22.18 | L57: 22.18

Sheet Balance Sheet
B2: Consolidated Balance Sheets | C2: Historical | H2: Projected
B3: $ in Millions | C3: 2021 | D3: =C3+1 -> 2022 | E3: =D3+1 -> 2023 | F3: =E3+1 -> 2024 | G3: =F3+1 -> 2025 | H3: =G3+1 -> 2026 | I3: =H3+1 -> 2027 | J3: =I3+1 -> 2028 | K3: =J3+1 -> 2029 | L3: =K3+1 -> 2030
B4: Assets
B5: Cash and cash equivalents | C5: 5081 | D5: 5924 | E5: 7822 | F5: 7550 | G5: 7676 | H5: =Assumptions!L57*'Income Statement'!H38 -> 9258.8783 | I5: =Assumptions!M57*'Income Statement'!I38 -> 9420.8126 | J5: =Assumptions!N57*'Income Statement'!J38 -> 9341.6393 | K5: =Assumptions!O57*'Income Statement'!K38 -> 9094.1539 | L5: =Assumptions!P57*'Income Statement'!L38 -> 9851.112
B6: Excess Cash | H6: =IF('Cash Flow Statement'!D75>0,'Cash Flow Statement'!D75,0) -> 0 | I6: =IF('Cash Flow Statement'!E75>0,'Cash Flow Statement'!E75,0) -> 0 | J6: =IF('Cash Flow Statement'!F75>0,'Cash Flow Statement'!F75,0) -> 0 | K6: =IF('Cash Flow Statement'!G75>0,'Cash Flow Statement'!G75,0) -> 9444.3024 | L6: =IF('Cash Flow Statement'!H75>0,'Cash Flow Statement'!H75,0) -> 27509.901
B7: Investments | C7: 920 | D7: 905 | E7: 925 | F7: 665 | G7: 1056 | H7: =Assumptions!L58*'Income Statement'!H38 -> 925.88783 | I7: =Assumptions!M58*'Income Statement'!I38 -> 1199.0125 | J7: =Assumptions!N58*'Income Statement'!J38 -> 1307.8295 | K7: =Assumptions!O58*'Income Statement'!K38 -> 1616.7385 | L7: =Assumptions!P58*'Income Statement'!L38 -> 1751.3088
B8: Accounts receivable, net | C8: 15071 | D8: 17218 | E8: 17722 | F8: 24227 | G8: 28768 | H8: =Assumptions!L59*'Income Statement'!H38 -> 29319.781 | I8: =Assumptions!M59*'Income Statement'!I38 -> 33401.063 | J8: =Assumptions!N59*'Income Statement'!J38 -> 37366.557 | K8: =Assumptions!O59*'Income Statement'!K38 -> 41428.923 | L8: =Assumptions!P59*'Income Statement'!L38 -> 44877.288
B9: Inventories | C9: 3722 | D9: 4777 | E9: 5645 | F9: 6692 | G9: 7338 | H9: =Assumptions!L60*'Income Statement'!H40 -> 7129.3363 | I9: =Assumptions!M60*'Income Statement'!I40 -> 8331.4241 | J9: =Assumptions!N60*'Income Statement'!J40 -> 9528.4721 | K9: =Assumptions!O60*'Income Statement'!K40 -> 10767.478 | L9: =Assumptions!P60*'Income Statement'!L40 -> 12145.327
B10: Other current assets | C10: 1283 | D10: 1296 | E10: 2169 | F10: 2732 | G10: 2976 | H10: =Assumptions!L61*'Income Statement'!H38 -> 3086.2928 | I10: =Assumptions!M61*'Income Statement'!I38 -> 3528.5225 | J10: =Assumptions!N61*'Income Statement'!J38 -> 3960.8551 | K10: =Assumptions!O61*'Income Statement'!K38 -> 4405.6123 | L10: =Assumptions!P61*'Income Statement'!L38 -> 4903.6646
B11: Assets of businesses held for sale | C11: 10057 | D11: 0 | E11: 3068 | F11: 7004 | G11: 0 | H11: 0 | I11: 0 | J11: 0 | K11: 0 | L11: 0
A12: x | B12: Total current assets | C12: =SUM(C5:C11) -> 36134 | D12: =SUM(D5:D11) -> 30120 | E12: =SUM(E5:E11) -> 37351 | F12: =SUM(F5:F11) -> 48870 | G12: =SUM(G5:G11) -> 47814 | H12: =SUM(H5:H11) -> 49720.176 | I12: =SUM(I5:I11) -> 55880.835 | J12: =SUM(J5:J11) -> 61505.353 | ... L12: =SUM(L5:L11) -> 101038.6
B13: Long-term investments | C13: 18438 | D13: 16288 | E13: 17985 | F13: 15128 | G13: 18471 | H13: =Assumptions!L63*'Income Statement'!H38 -> 24693.508 | I13: =Assumptions!M63*'Income Statement'!I38 -> 27409.514 | J13: =Assumptions!N63*'Income Statement'!J38 -> 29897.078 | K13: =Assumptions!O63*'Income Statement'!K38 -> 32338.915 | L13: =Assumptions!P63*'Income Statement'!L38 -> 35030.667 | M13: x
B14: Reinsurance recoverables | C14: 4970 | D14: 4743 | E14: 4835 | F14: 4378 | G14: 4103 | H14: =Assumptions!L64*'Income Statement'!H38 -> 4309.6992 | I14: =Assumptions!M64*'Income Statement'!I38 -> 5995.0626 | J14: =Assumptions!N64*'Income Statement'!J38 -> 7473.3114 | K14: =Assumptions!O64*'Income Statement'!K38 -> 9094.1539 | L14: =Assumptions!P64*'Income Statement'!L38 -> 10945.68
B15: Property and equipment | C15: 3692 | D15: 3774 | E15: 3695 | F15: 3654 | G15: 3651 | H15: =Assumptions!L65 -> 4321.6993 | I15: =Assumptions!M65 -> 4326.5317 | J15: =Assumptions!N65 -> 4226.9421 | K15: =Assumptions!O65 -> 3951.0496 | L15: =Assumptions!P65 -> 3644.2804
B16: Goodwill | C16: 45811 | D16: 45811 | E16: 44259 | F16: 44370 | G16: 44924 | H16: =Assumptions!$L$66 -> 44924 | I16: =Assumptions!$L$66 -> 44924 | J16: =Assumptions!$L$66 -> 44924 | K16: =Assumptions!$L$66 -> 44924 | L16: =Assumptions!$L$66 -> 44924
B17: Other intangible assets | C17: 34102 | D17: 32492 | E17: 30863 | F17: 29417 | G17: 28560 | H17: =Assumptions!L67*'Income Statement'!H38 -> 32406.074 | I17: =Assumptions!M67*'Income Statement'!I38 -> 36826.813 | J17: =Assumptions!N67*'Income Statement'!J38 -> 41103.213 | K17: =Assumptions!O67*'Income Statement'!K38 -> 45470.769 | L17: =Assumptions!P67*'Income Statement'!L38 -> 50350.128
B18: Other assets | C18: 3405 | D18: 3426 | E18: 3421 | F18: 2786 | G18: 2885 | H18: =Assumptions!L68*'Income Statement'!H38 -> 3086.2928 | I18: =Assumptions!M68*'Income Statement'!I38 -> 3083.175 | J18: =Assumptions!N68*'Income Statement'!J38 -> 2989.3246 | K18: =Assumptions!O68*'Income Statement'!K38 -> 2829.2923 | L18: =Assumptions!P68*'Income Statement'!L38 -> 2845.8768
B19: Separate account assets | C19: 8337 | D19: 7278 | E19: 7430 | F19: 7278 | G19: 7511 | H19: =Assumptions!L81*'Income Statement'!H38 -> 8178.6758 | I19: =Assumptions!M81*'Income Statement'!I38 -> 8906.9501 | J19: =Assumptions!N81*'Income Statement'!J38 -> 9528.4721 | K19: =Assumptions!O81*'Income Statement'!K38 -> 10104.615 | L19: =Assumptions!P81*'Income Statement'!L38 -> 10945.68
B20: Assets of businesses held for sale, non-current | C20: 0 | D20: 0 | E20: 2922 | F20: 0 | G20: 0 | H20: =Assumptions!L70*'Income Statement'!H38 -> 0 | I20: =Assumptions!M70*'Income Statement'!I38 -> 0 | J20: =Assumptions!N70*'Income Statement'!J38 -> 0 | K20: =Assumptions!O70*'Income Statement'!K38 -> 0 | L20: =Assumptions!P70*'Income Statement'!L38 -> 0
A21: x | B21: TOTAL ASSETS | C21: =SUM(C12:C20) -> 154889 | D21: =SUM(D12:D20) -> 143932 | E21: =SUM(E12:E20) -> 152761 | F21: =SUM(F12:F20) -> 155881 | G21: =SUM(G12:G20) -> 157919 | H21: =SUM(H12:H20) -> 171640.12 | I21: =SUM(I12:I20) -> 187352.88 | J21: =SUM(J12:J20) -> 201647.69 | ... L21: =SUM(L12:L20) -> 259724.91
B22: Liabilities
B23: Current insurance and contractholder liabilities | C23: 5318 | D23: 5385 | E23: 5514 | F23: 5388 | G23: 5710 | H23: =Assumptions!L73*'Income Statement'!H38 -> 6326.9002 | I23: =Assumptions!M73*'Income Statement'!I38 -> 6851.5001 | J23: =Assumptions!N73*'Income Statement'!J38 -> 7286.4786 | K23: =Assumptions!O73*'Income Statement'!K38 -> 7679.5077 | L23: =Assumptions!P73*'Income Statement'!L38 -> 8318.7168
B24: Pharmacy and other service costs payable | C24: 15309 | D24: 17070 | E24: 19815 | F24: 28465 | G24: 30333 | H24: =Assumptions!L74*'Income Statement'!H38 -> 31449.323 | I24: =Assumptions!M74*'Income Statement'!I38 -> 34908.393 | J24: =Assumptions!N74*'Income Statement'!J38 -> 38076.522 | K24: =Assumptions!O74*'Income Statement'!K38 -> 41186.412 | L24: =Assumptions!P74*'Income Statement'!L38 -> 44614.592
B25: Accounts payable | C25: 6655 | D25: 7775 | E25: 8553 | F25: 9294 | G25: 10659 | H25: =Assumptions!L75*'Income Statement'!H40 -> 9505.7817 | I25: =Assumptions!M75*'Income Statement'!I40 -> 10674.637 | J25: =Assumptions!N75*'Income Statement'!J40 -> 11770.466 | K25: =Assumptions!O75*'Income Statement'!K40 -> 12861.155 | L25: =Assumptions!P75*'Income Statement'!L40 -> 14063.01
B26: Revolver | H26: =IF('Cash Flow Statement'!D75<0,'Cash Flow Statement'!D75,0)*(-1) -> 8038.1749 | I26: =IF('Cash Flow Statement'!E75<0,'Cash Flow Statement'!E75,0)*(-1) -> 11022.902 | J26: =IF('Cash Flow Statement'!F75<0,'Cash Flow Statement'!F75,0)*(-1) -> 6114.0237 | K26: =IF('Cash Flow Statement'!G75<0,'Cash Flow Statement'!G75,0) -> 0 | L26: =IF('Cash Flow Statement'!H75<0,'Cash Flow Statement'!H75,0) -> 0
B27: Accrued expenses and other liabilities | C27: 7322 | D27: 8006 | E27: 9955 | F27: 9387 | G27: 9048 | H27: =Assumptions!L76*'Income Statement'!H38 -> 12345.171 | I27: =Assumptions!M76*'Income Statement'!I38 -> 13703 | J27: =Assumptions!N76*'Income Statement'!J38 -> 14946.623 | K27: =Assumptions!O76*'Income Statement'!K38 -> 16167.385 | L27: =Assumptions!P76*'Income Statement'!L38 -> 17513.088
B28: Short-term debt | C28: 2545 | D28: 2993 | E28: 2775 | F28: 3035
B29: Term March 2026 | G29: ='Debt Schedule'!E8 -> 549 | H29: ='Debt Schedule'!F8 -> 0 | I29: ='Debt Schedule'!G8 -> 0 | J29: ='Debt Schedule'!H8 -> 0 | K29: ='Debt Schedule'!I8 -> 0 | L29: ='Debt Schedule'!J8 -> 0
B30: Other, including finance leases | G30: ='Debt Schedule'!E16 -> 43 | H30: ='Debt Schedule'!F16 -> 41 | I30: ='Debt Schedule'!G16 -> 39 | J30: ='Debt Schedule'!H16 -> 37 | K30: ='Debt Schedule'!I16 -> 35 | L30: ='Debt Schedule'!J16 -> 33
B31: Liabilities of businesses held for sale | C31: 6423 | D31: 0 | E31: 2104 | F31: 2410 | G31: 0 | H31: =Assumptions!L77*'Income Statement'!H38 -> 0 | I31: =Assumptions!M77*'Income Statement'!I38 -> 0 | J31: =Assumptions!N77*'Income Statement'!J38 -> 0 | K31: =Assumptions!O77*'Income Statement'!K38 -> 0 | L31: =Assumptions!P77*'Income Statement'!L38 -> 0
A32: x | B32: Total current liabilities | C32: =SUM(C23:C31) -> 43572 | D32: =SUM(D23:D31) -> 41229 | E32: =SUM(E23:E31) -> 48716 | F32: =SUM(F23:F31) -> 57979 | G32: =SUM(G23:G31) -> 56342 | H32: =SUM(H23:H31) -> 67706.351 | I32: =SUM(I23:I31) -> 77199.432 | J32: =SUM(J23:J31) -> 78231.113 | ... L32: =SUM(L23:L31) -> 84542.406
B33: Non-current insurance and contractholder liabilities | C33: 12563 | D33: 11481 | E33: 10904 | F33: 10254 | G33: 9938 | H33: =Assumptions!L78*'Income Statement'!H38 -> 10802.025 | I33: =Assumptions!M78*'Income Statement'!I38 -> 11647.55 | J33: =Assumptions!N78*'Income Statement'!J38 -> 12330.964 | K33: =Assumptions!O78*'Income Statement'!K38 -> 13136 | L33: =Assumptions!P78*'Income Statement'!L38 -> 14229.384
B34: Deferred tax liabilities, net | C34: 8346 | D34: 7751 | E34: 7173 | F34: 6975 | G34: 7145 | H34: =Assumptions!L79*'Income Statement'!H38 -> 7715.7319 | I34: =Assumptions!M79*'Income Statement'!I38 -> 8221.8001 | J34: =Assumptions!N79*'Income Statement'!J38 -> 8594.3082 | K34: =Assumptions!O79*'Income Statement'!K38 -> 9094.1539 | L34: =Assumptions!P79*'Income Statement'!L38 -> 9851.112
B35: Other non-current liabilities | C35: 3762 | D35: 3142 | E35: 3441 | F35: 3215 | G35: 4238 | H35: =Assumptions!L80*'Income Statement'!H38 -> 4629.4391 | I35: =Assumptions!M80*'Income Statement'!I38 -> 5070.11 | J35: =Assumptions!N80*'Income Statement'!J38 -> 5418.1508 | K35: =Assumptions!O80*'Income Statement'!K38 -> 5860.6769 | L35: =Assumptions!P80*'Income Statement'!L38 -> 6348.4944
B36: Long-term debt | C36: 31125 | D36: 28100 | E36: 28155 | F36: 28937
B37: Term March 2026
B38: Finance Leases
B39: Term March 2027 | G39: ='Debt Schedule'!E34 -> 1481 | H39: ='Debt Schedule'!F34 -> 740.5 | I39: ='Debt Schedule'!G34 -> 0 | J39: ='Debt Schedule'!H34 -> 0 | K39: ='Debt Schedule'!I34 -> 0 | L39: ='Debt Schedule'!J34 -> 0
B40: Term May 2027 | G40: ='Debt Schedule'!E42 -> 260 | H40: ='Debt Schedule'!F42 -> 130 | I40: ='Debt Schedule'!G42 -> 0 | J40: ='Debt Schedule'!H42 -> 0 | K40: ='Debt Schedule'!I42 -> 0 | L40: ='Debt Schedule'!J42 -> 0
B41: Term October 2027 | G41: ='Debt Schedule'!E50 -> 599 | H41: ='Debt Schedule'!F50 -> 299.5 | I41: ='Debt Schedule'!G50 -> 0 | J41: ='Debt Schedule'!H50 -> 0 | K41: ='Debt Schedule'!I50 -> 0 | L41: ='Debt Schedule'!J50 -> 0
B42: Term October 2028 | G42: ='Debt Schedule'!E58 -> 3792 | H42: ='Debt Schedule'!F58 -> 2528 | I42: ='Debt Schedule'!G58 -> 1264 | J42: ='Debt Schedule'!H58 -> 0 | K42: ='Debt Schedule'!I58 -> 0 | L42: ='Debt Schedule'!J58 -> 0
B43: Term May 2029 | G43: ='Debt Schedule'!E66 -> 996 | H43: ='Debt Schedule'!F66 -> 747 | I43: ='Debt Schedule'!G66 -> 498 | J43: ='Debt Schedule'!H66 -> 249 | K43: ='Debt Schedule'!I66 -> 0 | L43: ='Debt Schedule'!J66 -> 0
B44: Term March 2030 | G44: ='Debt Schedule'!E74 -> 1406 | H44: ='Debt Schedule'!F74 -> 1124.8 | I44: ='Debt Schedule'!G74 -> 843.6 | J44: ='Debt Schedule'!H74 -> 562.4 | K44: ='Debt Schedule'!I74 -> 281.2 | L44: ='Debt Schedule'!J74 -> 0
B45: Term September 2030 | G45: ='Debt Schedule'!E82 -> 993 | H45: ='Debt Schedule'!F82 -> 794.4 | I45: ='Debt Schedule'!G82 -> 595.8 | J45: ='Debt Schedule'!H82 -> 397.2 | K45: ='Debt Schedule'!I82 -> 198.6 | L45: ='Debt Schedule'!J82 -> 0
B46: Term March 2031 | G46: ='Debt Schedule'!E90 -> 1420 | H46: ='Debt Schedule'!F90 -> 1183.3333 | I46: ='Debt Schedule'!G90 -> 946.66667 | J46: ='Debt Schedule'!H90 -> 710 | K46: ='Debt Schedule'!I90 -> 473.33333 | L46: ='Debt Schedule'!J90 -> 236.66667
B47: Term May 2031 | G47: ='Debt Schedule'!E98 -> 750 | H47: ='Debt Schedule'!F98 -> 625 | I47: ='Debt Schedule'!G98 -> 500 | J47: ='Debt Schedule'!H98 -> 375 | K47: ='Debt Schedule'!I98 -> 250 | L47: ='Debt Schedule'!J98 -> 125
B48: Term September 2032 | G48: ='Debt Schedule'!E106 -> 1243 | H48: ='Debt Schedule'!F106 -> 1065.4286 | I48: ='Debt Schedule'!G106 -> 887.85714 | J48: ='Debt Schedule'!H106 -> 710.28571 | K48: ='Debt Schedule'!I106 -> 532.71429 | L48: ='Debt Schedule'!J106 -> 355.14286
B49: Term January 2033 | G49: ='Debt Schedule'!E114 -> 45 | H49: ='Debt Schedule'!F114 -> 39.375 | I49: ='Debt Schedule'!G114 -> 33.75 | J49: ='Debt Schedule'!H114 -> 28.125 | K49: ='Debt Schedule'!I114 -> 22.5 | L49: ='Debt Schedule'!J114 -> 16.875
B50: Term March 2033 | G50: ='Debt Schedule'!E122 -> 796 | H50: ='Debt Schedule'!F122 -> 696.5 | I50: ='Debt Schedule'!G122 -> 597 | J50: ='Debt Schedule'!H122 -> 497.5 | K50: ='Debt Schedule'!I122 -> 398 | L50: ='Debt Schedule'!J122 -> 298.5
B51: Term February 2034 | G51: ='Debt Schedule'!E130 -> 1250 | H51: ='Debt Schedule'!F130 -> 1111.1111 | I51: ='Debt Schedule'!G130 -> 972.22222 | J51: ='Debt Schedule'!H130 -> 833.33333 | K51: ='Debt Schedule'!I130 -> 694.44444 | L51: ='Debt Schedule'!J130 -> 555.55556
B52: Term January 2036 | G52: ='Debt Schedule'!E138 -> 1488 | H52: ='Debt Schedule'!F138 -> 1352.7273 | I52: ='Debt Schedule'!G138 -> 1217.4545 | J52: ='Debt Schedule'!H138 -> 1082.1818 | K52: ='Debt Schedule'!I138 -> 946.90909 | L52: ='Debt Schedule'!J138 -> 811.63636
B53: Term November 2036 | G53: ='Debt Schedule'!E146 -> 190 | H53: ='Debt Schedule'!F146 -> 172.72727 | I53: ='Debt Schedule'!G146 -> 155.45455 | J53: ='Debt Schedule'!H146 -> 138.18182 | K53: ='Debt Schedule'!I146 -> 120.90909 | L53: ='Debt Schedule'!J146 -> 103.63636
B54: Term August 2038 | G54: ='Debt Schedule'!E154 -> 2194 | H54: ='Debt Schedule'!F154 -> 2025.2308 | I54: ='Debt Schedule'!G154 -> 1856.4615 | J54: ='Debt Schedule'!H154 -> 1687.6923 | K54: ='Debt Schedule'!I154 -> 1518.9231 | L54: ='Debt Schedule'!J154 -> 1350.1538
B55: Term March 2040 | G55: ='Debt Schedule'!E162 -> 748 | H55: ='Debt Schedule'!F162 -> 698.13333 | I55: ='Debt Schedule'!G162 -> 648.26667 | J55: ='Debt Schedule'!H162 -> 598.4 | K55: ='Debt Schedule'!I162 -> 548.53333 | L55: ='Debt Schedule'!J162 -> 498.66667
B56: Term March 2041 | G56: ='Debt Schedule'!E170 -> 119 | H56: ='Debt Schedule'!F170 -> 111.5625 | I56: ='Debt Schedule'!G170 -> 104.125 | J56: ='Debt Schedule'!H170 -> 96.6875 | K56: ='Debt Schedule'!I170 -> 89.25 | L56: ='Debt Schedule'!J170 -> 81.8125
B57: Term November 2041 | G57: ='Debt Schedule'!E178 -> 484 | H57: ='Debt Schedule'!F178 -> 453.75 | I57: ='Debt Schedule'!G178 -> 423.5 | J57: ='Debt Schedule'!H178 -> 393.25 | K57: ='Debt Schedule'!I178 -> 363 | L57: ='Debt Schedule'!J178 -> 332.75
B58: Term February 2042 | G58: ='Debt Schedule'!E186 -> 315 | H58: ='Debt Schedule'!F186 -> 296.47059 | I58: ='Debt Schedule'!G186 -> 277.94118 | J58: ='Debt Schedule'!H186 -> 259.41176 | K58: ='Debt Schedule'!I186 -> 240.88235 | L58: ='Debt Schedule'!J186 -> 222.35294
B59: Term July 2046 | G59: ='Debt Schedule'!E194 -> 1469 | H59: ='Debt Schedule'!F194 -> 1399.0476 | I59: ='Debt Schedule'!G194 -> 1329.0952 | J59: ='Debt Schedule'!H194 -> 1259.1429 | K59: ='Debt Schedule'!I194 -> 1189.1905 | L59: ='Debt Schedule'!J194 -> 1119.2381
B60: Term October 2047 | G60: ='Debt Schedule'!E202 -> 990 | H60: ='Debt Schedule'!F202 -> 945 | I60: ='Debt Schedule'!G202 -> 900 | J60: ='Debt Schedule'!H202 -> 855 | K60: ='Debt Schedule'!I202 -> 810 | L60: ='Debt Schedule'!J202 -> 765
B61: Term December 2048 | G61: ='Debt Schedule'!E210 -> 2972 | H61: ='Debt Schedule'!F210 -> 2842.7826 | I61: ='Debt Schedule'!G210 -> 2713.5652 | J61: ='Debt Schedule'!H210 -> 2584.3478 | K61: ='Debt Schedule'!I210 -> 2455.1304 | L61: ='Debt Schedule'!J210 -> 2325.913
B62: Term March 2050 | G62: ='Debt Schedule'!E218 -> 1172 | H62: ='Debt Schedule'!F218 -> 1125.12 | I62: ='Debt Schedule'!G218 -> 1078.24 | J62: ='Debt Schedule'!H218 -> 1031.36 | K62: ='Debt Schedule'!I218 -> 984.48 | L62: ='Debt Schedule'!J218 -> 937.6
B63: Term March 2051 | G63: ='Debt Schedule'!E226 -> 1410 | H63: ='Debt Schedule'!F226 -> 1355.7692 | I63: ='Debt Schedule'!G226 -> 1301.5385 | J63: ='Debt Schedule'!H226 -> 1247.3077 | K63: ='Debt Schedule'!I226 -> 1193.0769 | L63: ='Debt Schedule'!J226 -> 1138.8462
B64: Term February 2054 | G64: ='Debt Schedule'!E234 -> 1486 | H64: ='Debt Schedule'!F234 -> 1434.7586 | I64: ='Debt Schedule'!G234 -> 1383.5172 | J64: ='Debt Schedule'!H234 -> 1332.2759 | K64: ='Debt Schedule'!I234 -> 1281.0345 | L64: ='Debt Schedule'!J234 -> 1229.7931
B65: Term January 2056 | G65: ='Debt Schedule'!E242 -> 735 | H65: ='Debt Schedule'!F242 -> 711.29032 | I65: ='Debt Schedule'!G242 -> 687.58065 | J65: ='Debt Schedule'!H242 -> 663.87097 | K65: ='Debt Schedule'!I242 -> 640.16129 | L65: ='Debt Schedule'!J242 -> 616.45161
B66: Other, including finance leases | G66: ='Debt Schedule'!E254 -> 68 | H66: ='Debt Schedule'!F254 -> 65 | I66: ='Debt Schedule'!G254 -> 62 | J66: ='Debt Schedule'!H254 -> 59 | K66: ='Debt Schedule'!I254 -> 56 | L66: ='Debt Schedule'!J254 -> 53
B67: Separate account liabilities | C67: 8337 | D67: 7278 | E67: 7430 | F67: 7278 | G67: 7511 | H67: =Assumptions!L81*'Income Statement'!H38 -> 8178.6758 | I67: =Assumptions!M81*'Income Statement'!I38 -> 8906.9501 | J67: =Assumptions!N81*'Income Statement'!J38 -> 9528.4721 | K67: =Assumptions!O81*'Income Statement'!K38 -> 10104.615 | L67: =Assumptions!P81*'Income Statement'!L38 -> 10945.68
B68: Liabilities of businesses held for sale, non-current | C68: 0 | D68: 0 | E68: 591 | F68: 0 | G68: 0 | H68: =Assumptions!L82*'Income Statement'!H38 -> 0 | I68: =Assumptions!M82*'Income Statement'!I38 -> 0 | J68: =Assumptions!N82*'Income Statement'!J38 -> 0 | K68: =Assumptions!O82*'Income Statement'!K38 -> 0 | L68: =Assumptions!P82*'Income Statement'!L38 -> 0
A69: x | B69: TOTAL LIABILITIES | C69: =SUM(C32:C68) -> 107705 | D69: =SUM(D32:D68) -> 98981 | E69: =SUM(E32:E68) -> 106410 | F69: =SUM(F32:F68) -> 114638 | G69: =SUM(G32:G68) -> 116045 | H69: =SUM(H32:H68) -> 125106.54 | I69: =SUM(I32:I68) -> 132323.48 | J69: =SUM(J32:J68) -> 131753.96 | ... L69: =SUM(L32:L68) -> 139091.67
B70: Shareholders' equity
B71: Redeemable noncontrolling interests | C71: 54 | D71: 66 | E71: 107 | F71: 0 | G71: 0 | H71: =Assumptions!L85 -> 0 | I71: =Assumptions!M85 -> 0 | J71: =Assumptions!N85 -> 0 | K71: =Assumptions!O85 -> 0 | L71: =Assumptions!P85 -> 0
B72: Common stock | C72: 4 | D72: 4 | E72: 4 | F72: 4 | G72: 4 | H72: =Assumptions!L86 -> 4 | I72: =Assumptions!M86 -> 4 | J72: =Assumptions!N86 -> 4 | K72: =Assumptions!O86 -> 4 | L72: =Assumptions!P86 -> 4
B73: Additional paid-in capital | C73: 29574 | D73: 30233 | E73: 30669 | F73: 31288 | G73: 31790 | H73: =Assumptions!L87 -> 32438 | I73: =Assumptions!M87 -> 32438 | J73: =Assumptions!N87 -> 32438 | K73: =Assumptions!O87 -> 32438 | L73: =Assumptions!P87 -> 32438
B74: Accumulated other comprehensive loss | C74: -884 | D74: -1395 | E74: -1864 | F74: -2341 | G74: -2806 | H74: =Assumptions!L88 -> -2806 | I74: =Assumptions!M88 -> -2806 | J74: =Assumptions!N88 -> -2806 | K74: =Assumptions!O88 -> -2806 | L74: =Assumptions!P88 -> -2806
B75: Retained earnings | C75: 32593 | D75: 37874 | E75: 41652 | F75: 43519 | G75: 47865 | H75: =Assumptions!L89 -> 51876.584 | I75: =Assumptions!M89 -> 60372.402 | J75: =Assumptions!N89 -> 75236.733 | K75: =Assumptions!O89 -> 99399.826 | L75: =Assumptions!P89 -> 125976.25
B76: Less: Treasury stock, at cost | C76: -14175 | D76: -21844 | E76: -24238 | F76: -31437 | G76: -35140 | H76: =Assumptions!L90 -> -35140 | I76: =Assumptions!M90 -> -35140 | J76: =Assumptions!N90 -> -35140 | K76: =Assumptions!O90 -> -35140 | L76: =Assumptions!P90 -> -35140
A77: x | B77: TOTAL SHAREHOLDERS' EQUITY | C77: =SUM(C71:C76) -> 47166 | D77: =SUM(D71:D76) -> 44938 | E77: =SUM(E71:E76) -> 46330 | F77: =SUM(F71:F76) -> 41033 | G77: =SUM(G71:G76) -> 41713 | H77: =SUM(H71:H76) -> 46372.584 | I77: =SUM(I71:I76) -> 54868.402 | J77: =SUM(J71:J76) -> 69732.733 | ... L77: =SUM(L71:L76) -> 120472.25
B78: Other noncontrolling interests | C78: 18 | D78: 13 | E78: 21 | F78: 210 | G78: 161 | H78: =Assumptions!L91 -> 161 | I78: =Assumptions!M91 -> 161 | J78: =Assumptions!N91 -> 161 | K78: =Assumptions!O91 -> 161 | L78: =Assumptions!P91 -> 161
A79: x | B79: Total equity | C79: =C77+C78 -> 47184 | D79: =D77+D78 -> 44951 | E79: =E77+E78 -> 46351 | F79: =F77+F78 -> 41243 | G79: =G77+G78 -> 41874 | H79: =H77+H78 -> 46533.584 | I79: =I77+I78 -> 55029.402 | J79: =J77+J78 -> 69893.733 | ... L79: =L77+L78 -> 120633.25
A80: x | B80: Total liabilities and equity | C80: =C69+C79 -> 154889 | D80: =D69+D79 -> 143932 | E80: =E69+E79 -> 152761 | F80: =F69+F79 -> 155881 | G80: =G69+G79 -> 157919 | H80: =H69+H79 -> 171640.12 | I80: =I69+I79 -> 187352.88 | J80: =J69+J79 -> 201647.69 | ... L80: =L69+L79 -> 259724.91
B81: Check | C81: =C21-C80 -> 0 | D81: =D21-D80 -> 0 | E81: =E21-E80 -> 0 | F81: =F21-F80 -> 0 | G81: =G21-G80 -> 0 | H81: =H21-H80 -> 0 | I81: =I21-I80 -> 0 | J81: =J21-J80 -> 0 | ... L81: =L21-L80 -> 0

Sheet Cash Flow Statement
B2: Cash Flow Statement | D2: Projected
B3: $ in Millions | C3: 2025 | D3: 2026 | E3: 2027 | F3: 2028 | G3: 2029 | H3: 2030
B4: Cash Flow Operations
B5: Net Income | D5: ='Income Statement'!H54 -> 4011.5843 | E5: ='Income Statement'!I54 -> 8495.8178 | F5: ='Income Statement'!J54 -> 14864.33 | G5: ='Income Statement'!K54 -> 24163.093 | H5: ='Income Statement'!L54 -> 26576.419
B6: Depreciation | D6: =Calcs!H15 -> 1949.8866 | E6: =Calcs!I15 -> 2164.3521 | F6: =Calcs!J15 -> 2360.779 | G6: =Calcs!K15 -> 2553.595 | H6: =Calcs!L15 -> 2766.1452
B7: Investments | D7: =-('Balance Sheet'!H7-'Balance Sheet'!G7) -> 130.11217 | E7: =-('Balance Sheet'!I7-'Balance Sheet'!H7) -> -273.12468 | F7: =-('Balance Sheet'!J7-'Balance Sheet'!I7) -> -108.81699 | G7: =-('Balance Sheet'!K7-'Balance Sheet'!J7) -> -308.90897 | H7: =-('Balance Sheet'!L7-'Balance Sheet'!K7) -> -134.57033
B8: Receivables | D8: =-('Balance Sheet'!H8-'Balance Sheet'!G8) -> -551.78119 | E8: =-('Balance Sheet'!I8-'Balance Sheet'!H8) -> -4081.2816 | F8: =-('Balance Sheet'!J8-'Balance Sheet'!I8) -> -3965.4944 | G8: =-('Balance Sheet'!K8-'Balance Sheet'!J8) -> -4062.3661 | H8: =-('Balance Sheet'!L8-'Balance Sheet'!K8) -> -3448.3647
B9: Inventories | D9: =-('Balance Sheet'!H9-'Balance Sheet'!G9) -> 208.66373 | E9: =-('Balance Sheet'!I9-'Balance Sheet'!H9) -> -1202.0878 | F9: =-('Balance Sheet'!J9-'Balance Sheet'!I9) -> -1197.048 | G9: =-('Balance Sheet'!K9-'Balance Sheet'!J9) -> -1239.0061 | H9: =-('Balance Sheet'!L9-'Balance Sheet'!K9) -> -1377.8483
B10: Other Current Assets | D10: =-('Balance Sheet'!H10-'Balance Sheet'!G10) -> -110.29276 | E10: =-('Balance Sheet'!I10-'Balance Sheet'!H10) -> -442.22978 | F10: =-('Balance Sheet'!J10-'Balance Sheet'!I10) -> -432.33253 | G10: =-('Balance Sheet'!K10-'Balance Sheet'!J10) -> -444.75726 | H10: =-('Balance Sheet'!L10-'Balance Sheet'!K10) -> -498.05231
B11: Assets of Businesses | D11: =-('Balance Sheet'!H11-'Balance Sheet'!G11) -> 0 | E11: =-('Balance Sheet'!I11-'Balance Sheet'!H11) -> 0 | F11: =-('Balance Sheet'!J11-'Balance Sheet'!I11) -> 0 | G11: =-('Balance Sheet'!K11-'Balance Sheet'!J11) -> 0 | H11: =-('Balance Sheet'!L11-'Balance Sheet'!K11) -> 0
B12: Insurance Liabilities | D12: ='Balance Sheet'!H23-'Balance Sheet'!G23 -> 616.90015 | E12: ='Balance Sheet'!I23-'Balance Sheet'!H23 -> 524.59991 | F12: ='Balance Sheet'!J23-'Balance Sheet'!I23 -> 434.97858 | G12: ='Balance Sheet'!K23-'Balance Sheet'!J23 -> 393.02907 | H12: ='Balance Sheet'!L23-'Balance Sheet'!K23 -> 639.20907
B13: Pharamcy payable | D13: ='Balance Sheet'!H24-'Balance Sheet'!G24 -> 1116.3232 | E13: ='Balance Sheet'!I24-'Balance Sheet'!H24 -> 3459.0696 | F13: ='Balance Sheet'!J24-'Balance Sheet'!I24 -> 3168.1289 | G13: ='Balance Sheet'!K24-'Balance Sheet'!J24 -> 3109.8907 | H13: ='Balance Sheet'!L24-'Balance Sheet'!K24 -> 3428.1792
B14: Accts Payable | D14: ='Balance Sheet'!H25-'Balance Sheet'!G25 -> -1153.2183 | E14: ='Balance Sheet'!I25-'Balance Sheet'!H25 -> 1168.8554 | F14: ='Balance Sheet'!J25-'Balance Sheet'!I25 -> 1095.8284 | G14: ='Balance Sheet'!K25-'Balance Sheet'!J25 -> 1090.689 | H14: ='Balance Sheet'!L25-'Balance Sheet'!K25 -> 1201.8551
B15: Accrued expense | D15: ='Balance Sheet'!H27-'Balance Sheet'!G27 -> 3297.171 | E15: ='Balance Sheet'!I27-'Balance Sheet'!H27 -> 1357.8291 | F15: ='Balance Sheet'!J27-'Balance Sheet'!I27 -> 1243.6227 | G15: ='Balance Sheet'!K27-'Balance Sheet'!J27 -> 1220.7618 | H15: ='Balance Sheet'!L27-'Balance Sheet'!K27 -> 1345.7033
A16: x | B16: CFO | D16: =SUM(D5:D15) -> 9515.3489 | E16: =SUM(E5:E15) -> 11171.8 | F16: =SUM(F5:F15) -> 17463.976 | G16: =SUM(G5:G15) -> 26476.02 | H16: =SUM(H5:H15) -> 30498.676
B17: Cash Flow Investing
B18: Capital Expenditures | D18: =-Calcs!H14 -> -1972.5859 | E18: =-Calcs!I14 -> -2169.1845 | F18: =-Calcs!J14 -> -2261.1893 | G18: =-Calcs!K14 -> -2277.7026 | H18: =-Calcs!L14 -> -2459.376
B19: Long Investments | D19: =-('Balance Sheet'!H13-'Balance Sheet'!G13) -> -6222.5075 | E19: =-('Balance Sheet'!I13-'Balance Sheet'!H13) -> -2716.0064 | F19: =-('Balance Sheet'!J13-'Balance Sheet'!I13) -> -2487.5644 | G19: =-('Balance Sheet'!K13-'Balance Sheet'!J13) -> -2441.8366 | H19: =-('Balance Sheet'!L13-'Balance Sheet'!K13) -> -2691.7517
B20: Reinsurance | D20: =-('Balance Sheet'!H14-'Balance Sheet'!G14) -> -206.69921 | E20: =-('Balance Sheet'!I14-'Balance Sheet'!H14) -> -1685.3634 | F20: =-('Balance Sheet'!J14-'Balance Sheet'!I14) -> -1478.2489 | G20: =-('Balance Sheet'!K14-'Balance Sheet'!J14) -> -1620.8424 | H20: =-('Balance Sheet'!L14-'Balance Sheet'!K14) -> -1851.5261
B21: Goodwill | D21: =-('Balance Sheet'!H16-'Balance Sheet'!G16) -> 0 | E21: =-('Balance Sheet'!I16-'Balance Sheet'!H16) -> 0 | F21: =-('Balance Sheet'!J16-'Balance Sheet'!I16) -> 0 | G21: =-('Balance Sheet'!K16-'Balance Sheet'!J16) -> 0 | H21: =-('Balance Sheet'!L16-'Balance Sheet'!K16) -> 0
B22: Other intangible | D22: =-('Balance Sheet'!H17-'Balance Sheet'!G17) -> -3846.0739 | E22: =-('Balance Sheet'!I17-'Balance Sheet'!H17) -> -4420.7389 | F22: =-('Balance Sheet'!J17-'Balance Sheet'!I17) -> -4276.4 | G22: =-('Balance Sheet'!K17-'Balance Sheet'!J17) -> -4367.5565 | H22: =-('Balance Sheet'!L17-'Balance Sheet'!K17) -> -4879.3586
B23: Other assets | D23: =-('Balance Sheet'!H18-'Balance Sheet'!G18) -> -201.29276 | E23: =-('Balance Sheet'!I18-'Balance Sheet'!H18) -> 3.1177269 | F23: =-('Balance Sheet'!J18-'Balance Sheet'!I18) -> 93.850455 | G23: =-('Balance Sheet'!K18-'Balance Sheet'!J18) -> 160.03226 | H23: =-('Balance Sheet'!L18-'Balance Sheet'!K18) -> -16.584479
B24: Separate acct assets | D24: =-('Balance Sheet'!H19-'Balance Sheet'!G19) -> -667.6758 | E24: =-('Balance Sheet'!I19-'Balance Sheet'!H19) -> -728.27428 | F24: =-('Balance Sheet'!J19-'Balance Sheet'!I19) -> -621.52199 | G24: =-('Balance Sheet'!K19-'Balance Sheet'!J19) -> -576.14334 | H24: =-('Balance Sheet'!L19-'Balance Sheet'!K19) -> -841.06457
B25: Ins. Liabilities | D25: ='Balance Sheet'!H33-'Balance Sheet'!G33 -> 864.02465 | E25: ='Balance Sheet'!I33-'Balance Sheet'!H33 -> 845.52546 | F25: ='Balance Sheet'!J33-'Balance Sheet'!I33 -> 683.41376 | G25: ='Balance Sheet'!K33-'Balance Sheet'!J33 -> 805.03618 | H25: ='Balance Sheet'!L33-'Balance Sheet'!K33 -> 1093.3839
B26: Tax Liabilities | D26: ='Balance Sheet'!H34-'Balance Sheet'!G34 -> 570.73189 | E26: ='Balance Sheet'!I34-'Balance Sheet'!H34 -> 506.06819 | F26: ='Balance Sheet'!J34-'Balance Sheet'!I34 -> 372.50807 | G26: ='Balance Sheet'!K34-'Balance Sheet'!J34 -> 499.84573 | H26: ='Balance Sheet'!L34-'Balance Sheet'!K34 -> 756.95811
B27: Other non-current | D27: ='Balance Sheet'!H35-'Balance Sheet'!G35 -> 391.43913 | E27: ='Balance Sheet'!I35-'Balance Sheet'!H35 -> 440.67091 | F27: ='Balance Sheet'!J35-'Balance Sheet'!I35 -> 348.04074 | G27: ='Balance Sheet'!K35-'Balance Sheet'!J35 -> 442.52616 | H27: ='Balance Sheet'!L35-'Balance Sheet'!K35 -> 487.81745
B28: Sep acct liabilities | D28: ='Balance Sheet'!H67-'Balance Sheet'!G67 -> 667.6758 | E28: ='Balance Sheet'!I67-'Balance Sheet'!H67 -> 728.27428 | F28: ='Balance Sheet'!J67-'Balance Sheet'!I67 -> 621.52199 | G28: ='Balance Sheet'!K67-'Balance Sheet'!J67 -> 576.14334 | H28: ='Balance Sheet'!L67-'Balance Sheet'!K67 -> 841.06457
A29: x | B29: CFI | D29: =SUM(D18:D28) -> -10622.964 | E29: =SUM(E18:E28) -> -9195.9108 | F29: =SUM(F18:F28) -> -9005.5896 | G29: =SUM(G18:G28) -> -8800.4978 | H29: =SUM(H18:H28) -> -9560.4373
B30: Cash Flow Financing
B31: Term March 2026 | D31: ='Balance Sheet'!H29-'Balance Sheet'!G29 -> -549 | E31: ='Balance Sheet'!I29-'Balance Sheet'!H29 -> 0 | F31: ='Balance Sheet'!J29-'Balance Sheet'!I29 -> 0 | G31: ='Balance Sheet'!K29-'Balance Sheet'!J29 -> 0 | H31: ='Balance Sheet'!L29-'Balance Sheet'!K29 -> 0
B32: Finance Leases | D32: ='Balance Sheet'!H30-'Balance Sheet'!G30 -> -2 | E32: ='Balance Sheet'!I30-'Balance Sheet'!H30 -> -2 | F32: ='Balance Sheet'!J30-'Balance Sheet'!I30 -> -2 | G32: ='Balance Sheet'!K30-'Balance Sheet'!J30 -> -2 | H32: ='Balance Sheet'!L30-'Balance Sheet'!K30 -> -2
B33: Term March 2027 | D33: -740.5 | E33: -740.5 | F33: 0 | G33: 0 | H33: 0
B34: Term May 207 | D34: -130 | E34: -130 | F34: 0 | G34: 0 | H34: 0
B35: Term October 2027 | D35: -299.5 | E35: -299.5 | F35: 0 | G35: 0 | H35: 0
B36: Term October 2028 | D36: -1264 | E36: -1264 | F36: -1264 | G36: 0 | H36: 0
B37: Term May 2029 | D37: -249 | E37: -249 | F37: -249 | G37: -249 | H37: 0
B38: Term March 2030 | D38: -281.2 | E38: -281.2 | F38: -281.2 | G38: -281.2 | H38: -281.2
B39: Term September 2030 | D39: -198.6 | E39: -198.6 | F39: -198.6 | G39: -198.6 | H39: -198.6
B40: Term March 2031 | D40: -236.66667 | E40: -236.66667 | F40: -236.66667 | G40: -236.66667 | H40: -236.66667
B41: Term May 2031 | D41: -125 | E41: -125 | F41: -125 | G41: -125 | H41: -125
B42: Term September 2032 | D42: -177.57143 | E42: -177.57143 | F42: -177.57143 | G42: -177.57143 | H42: -177.57143
B43: Term January 2033 | D43: -5.625 | E43: -5.625 | F43: -5.625 | G43: -5.625 | H43: -5.625
B44: Term March 2033 | D44: -99.5 | E44: -99.5 | F44: -99.5 | G44: -99.5 | H44: -99.5
... B65: Less: Treasury stock, at cost | D65: 0 | E65: 0 | F65: 0 | G65: 0 | H65: 0
A66: x | B66: CFF | D66: =SUM(D31:D65) -> -5347.6818 | E66: =SUM(E31:E65) -> -4798.6818 | F66: =SUM(F31:F65) -> -3628.6818 | G66: =SUM(G31:G65) -> -2364.6818 | H66: =SUM(H31:H65) -> -2115.6818
A68: x | B68: Net Change in Cash | D68: =D66+D29+D16 -> -6455.2966 | E68: =E66+E29+E16 -> -2822.7926 | F68: =F66+F29+F16 -> 4829.7048 | G68: =G66+G29+G16 -> 15310.841 | H68: =H66+H29+H16 -> 18822.556
B70: Beg Cash | D70: =C72 -> 7676 | E70: =D72 -> 1220.7034 | F70: =E72 -> -1602.0892 | G70: =F72 -> 3227.6156 | H70: =G72 -> 18538.456
B71: Change in CFS | D71: =D68 -> -6455.2966 | E71: =E68 -> -2822.7926 | F71: =F68 -> 4829.7048 | G71: =G68 -> 15310.841 | H71: =H68 -> 18822.556
B72: Net Available | C72: ='Balance Sheet'!G5 -> 7676 | D72: =D70+D71 -> 1220.7034 | E72: =E70+E71 -> -1602.0892 | F72: =F70+F71 -> 3227.6156 | G72: =G70+G71 -> 18538.456 | H72: =H70+H71 -> 37361.013
B74: Req Cash | D74: ='Balance Sheet'!H5 -> 9258.8783 | E74: ='Balance Sheet'!I5 -> 9420.8126 | F74: ='Balance Sheet'!J5 -> 9341.6393 | G74: ='Balance Sheet'!K5 -> 9094.1539 | H74: ='Balance Sheet'!L5 -> 9851.112
A75: x | B75: Excess Cash/(Revolver) | D75: =D72-D74 -> -8038.1749 | E75: =E72-E74 -> -11022.902 | F75: =F72-F74 -> -6114.0237 | G75: =G72-G74 -> 9444.3024 | H75: =H72-H74 -> 27509.901

Sheet Calcs
B2: Calcs | C2: Historical | H2: Projected
B3: $ in Millions | C3: 2021 | D3: 2022 | E3: 2023 | F3: 2024 | G3: 2025 | H3: 2026 | I3: 2027 | J3: 2028 | K3: 2029 | L3: 2030
A4: x | B4: Retained Earnings
B5: Beginning Balance | C5: 28575 | D5: =C9 -> 32593 | E5: =D9 -> 37874 | F5: =E9 -> 41652 | G5: =F9 -> 43519 | H5: =G9 -> 47865 | I5: =H9 -> 51876.584 | J5: =I9 -> 60372.402 | K5: =J9 -> 75236.733 | L5: =K9 -> 99399.826
B6: Net Income | C6: ='Income Statement'!C54 -> 5365 | D6: ='Income Statement'!D54 -> 6668 | E6: ='Income Statement'!E54 -> 5164 | F6: ='Income Statement'!F54 -> 3434 | G6: ='Income Statement'!G54 -> 5957 | H6: ='Income Statement'!H54 -> 4011.5843 | I6: ='Income Statement'!I54 -> 8495.8178 | J6: ='Income Statement'!J54 -> 14864.33 | ... L6: ='Income Statement'!L54 -> 26576.419
B7: Common Dividends Declared | C7: -1347 | D7: -1387 | E7: -1452 | F7: -1567 | G7: -1611
B8: Additional Balance | C8: 0 | D8: 0 | E8: 66 | F8: 0 | G8: 0 | H8: =G8 -> 0 | I8: =H8 -> 0 | J8: =I8 -> 0 | K8: =J8 -> 0 | L8: =K8 -> 0
B9: Ending Balance | C9: =SUM(C5:C7) -> 32593 | D9: =SUM(D5:D7) -> 37874 | E9: =SUM(E5:E8) -> 41652 | F9: =SUM(F5:F7) -> 43519 | G9: =SUM(G5:G7) -> 47865 | H9: =SUM(H5:H7) -> 51876.584 | I9: =SUM(I5:I7) -> 60372.402 | J9: =SUM(J5:J7) -> 75236.733 | K9: =SUM(K5:K7) -> 99399.826 | L9: =SUM(L5:L7) -> 125976.25
B10: Real From BS | C10: ='Balance Sheet'!C75 -> 32593 | D10: ='Balance Sheet'!D75 -> 37874 | E10: ='Balance Sheet'!E75 -> 41652 | F10: ='Balance Sheet'!F75 -> 43519 | G10: ='Balance Sheet'!G75 -> 47865 | H10: =G7/'Income Statement'!G54 -> -0.27043814
A12: x | B12: PP&E
B13: Beginning Balance | C13: 4205 | D13: =C16 -> 3984 | E13: =D16 -> 3948 | F13: =E16 -> 4305 | G13: =F16 -> 4379 | H13: =G16 -> 4299 | I13: =H16 -> 4321.6993 | J13: =I16 -> 4326.5317 | K13: =J16 -> 4226.9421 | L13: =K16 -> 3951.0496
B14: Capital Expenditures | C14: 1154 | D14: 1295 | E14: 1573 | F14: 1406 | G14: 1212 | H14: ='Income Statement'!H38*AVERAGE(Assumptions!C52:G52) -> 1972.5859 | I14: ='Income Statement'!I38*AVERAGE(Assumptions!D52:H52) -> 2169.1845 | J14: ='Income Statement'!J38*AVERAGE(Assumptions!E52:I52) -> 2261.1893 | K14: ='Income Statement'!K38*AVERAGE(Assumptions!F52:J52) -> 2277.7026 | L14: ='Income Statement'!L38*AVERAGE(Assumptions!G52:K52) -> 2459.376
B15: Depreciation | C15: =1097+253+25 -> 1375 | D15: =1068+251+12 -> 1331 | E15: =3035-'Income Statement'!E43 -> 1216 | F15: =3035-'Income Statement'!F43 -> 1332 | G15: =3035-'Income Statement'!G43 -> 1292 | H15: =Assumptions!L51*'Income Statement'!H38 -> 1949.8866 | I15: =Assumptions!M51*'Income Statement'!I38 -> 2164.3521 | J15: =Assumptions!N51*'Income Statement'!J38 -> 2360.779 | K15: =Assumptions!O51*'Income Statement'!K38 -> 2553.595 | L15: =Assumptions!P51*'Income Statement'!L38 -> 2766.1452
B16: Ending Balance | C16: =C13+C14-C15 -> 3984 | D16: =D13+D14-D15 -> 3948 | E16: =E13+E14-E15 -> 4305 | F16: =F13+F14-F15 -> 4379 | G16: =G13+G14-G15 -> 4299 | H16: =H13+H14-H15 -> 4321.6993 | I16: =I13+I14-I15 -> 4326.5317 | J16: =J13+J14-J15 -> 4226.9421 | ... L16: =L13+L14-L15 -> 3644.2804
B17: Real From BS | C17: ='Balance Sheet'!C15 -> 3692 | D17: ='Balance Sheet'!D15 -> 3774 | E17: ='Balance Sheet'!E15 -> 3695 | F17: ='Balance Sheet'!F15 -> 3654 | G17: ='Balance Sheet'!G15 -> 3651
G18: =G15/'Income Statement'!G38 -> 0.0046998909
A19: x | B19: Operating Working Capital
B20: Current Assets:
B21: Receivables | C21: ='Balance Sheet'!C8 -> 15071 | D21: ='Balance Sheet'!D8 -> 17218 | E21: ='Balance Sheet'!E8 -> 17722 | F21: ='Balance Sheet'!F8 -> 24227 | G21: ='Balance Sheet'!G8 -> 28768 | H21: ='Balance Sheet'!H8 -> 29319.781 | I21: ='Balance Sheet'!I8 -> 33401.063 | J21: ='Balance Sheet'!J8 -> 37366.557 | ... L21: ='Balance Sheet'!L8 -> 44877.288
B22: Inventories | C22: ='Balance Sheet'!C9 -> 3722 | D22: ='Balance Sheet'!D9 -> 4777 | E22: ='Balance Sheet'!E9 -> 5645 | F22: ='Balance Sheet'!F9 -> 6692 | G22: ='Balance Sheet'!G9 -> 7338 | H22: ='Balance Sheet'!H9 -> 7129.3363 | I22: ='Balance Sheet'!I9 -> 8331.4241 | J22: ='Balance Sheet'!J9 -> 9528.4721 | ... L22: ='Balance Sheet'!L9 -> 12145.327
B23: Investments | C23: ='Balance Sheet'!C7 -> 920 | D23: ='Balance Sheet'!D7 -> 905 | E23: ='Balance Sheet'!E7 -> 925 | F23: ='Balance Sheet'!F7 -> 665 | G23: ='Balance Sheet'!G7 -> 1056 | H23: ='Balance Sheet'!H7 -> 925.88783 | I23: ='Balance Sheet'!I7 -> 1199.0125 | J23: ='Balance Sheet'!J7 -> 1307.8295 | ... L23: ='Balance Sheet'!L7 -> 1751.3088
B24: Prepaid Expenses and Other | C24: ='Balance Sheet'!C10 -> 1283 | D24: ='Balance Sheet'!D10 -> 1296 | E24: ='Balance Sheet'!E10 -> 2169 | F24: ='Balance Sheet'!F10 -> 2732 | G24: ='Balance Sheet'!G10 -> 2976 | H24: ='Balance Sheet'!H10 -> 3086.2928 | I24: ='Balance Sheet'!I10 -> 3528.5225 | J24: ='Balance Sheet'!J10 -> 3960.8551 | ... L24: ='Balance Sheet'!L10 -> 4903.6646
A25: x | B25: Total Operating Assets | C25: =SUM(C21:C24) -> 20996 | D25: =SUM(D21:D24) -> 24196 | E25: =SUM(E21:E24) -> 26461 | F25: =SUM(F21:F24) -> 34316 | G25: =SUM(G21:G24) -> 40138 | H25: =SUM(H21:H24) -> 40461.298 | I25: =SUM(I21:I24) -> 46460.022 | J25: =SUM(J21:J24) -> 52163.714 | ... L25: =SUM(L21:L24) -> 63677.588
A27: x | B27: Current Liabilities:
B28: Current Insurance and contract holder | C28: ='Balance Sheet'!C23 -> 5318 | D28: ='Balance Sheet'!D23 -> 5385 | E28: ='Balance Sheet'!E23 -> 5514 | F28: ='Balance Sheet'!F23 -> 5388 | G28: ='Balance Sheet'!G23 -> 5710 | H28: ='Balance Sheet'!H23 -> 6326.9002 | I28: ='Balance Sheet'!I23 -> 6851.5001 | J28: ='Balance Sheet'!J23 -> 7286.4786 | ... L28: ='Balance Sheet'!L23 -> 8318.7168
B29: Pharmacy and other service costs payable | C29: ='Balance Sheet'!C24 -> 15309 | D29: ='Balance Sheet'!D24 -> 17070 | E29: ='Balance Sheet'!E24 -> 19815 | F29: ='Balance Sheet'!F24 -> 28465 | G29: ='Balance Sheet'!G24 -> 30333 | H29: ='Balance Sheet'!H24 -> 31449.323 | I29: ='Balance Sheet'!I24 -> 34908.393 | J29: ='Balance Sheet'!J24 -> 38076.522 | ... L29: ='Balance Sheet'!L24 -> 44614.592
B30: Accounts payable | C30: ='Balance Sheet'!C25 -> 6655 | D30: ='Balance Sheet'!D25 -> 7775 | E30: ='Balance Sheet'!E25 -> 8553 | F30: ='Balance Sheet'!F25 -> 9294 | G30: ='Balance Sheet'!G25 -> 10659 | H30: ='Balance Sheet'!H25 -> 9505.7817 | I30: ='Balance Sheet'!I25 -> 10674.637 | J30: ='Balance Sheet'!J25 -> 11770.466 | ... L30: ='Balance Sheet'!L25 -> 14063.01
B31: Accrued expenses | C31: ='Balance Sheet'!C27 -> 7322 | D31: ='Balance Sheet'!D27 -> 8006 | E31: ='Balance Sheet'!E27 -> 9955 | F31: ='Balance Sheet'!F27 -> 9387 | G31: ='Balance Sheet'!G27 -> 9048 | H31: ='Balance Sheet'!H27 -> 12345.171 | I31: ='Balance Sheet'!I27 -> 13703 | J31: ='Balance Sheet'!J27 -> 14946.623 | ... L31: ='Balance Sheet'!L27 -> 17513.088
B32: Liabilities of businesses held for sale | C32: ='Balance Sheet'!C31 -> 6423 | D32: ='Balance Sheet'!D31 -> 0 | E32: ='Balance Sheet'!E31 -> 2104 | F32: ='Balance Sheet'!F31 -> 2410 | G32: ='Balance Sheet'!G31 -> 0 | H32: ='Balance Sheet'!H31 -> 0 | I32: ='Balance Sheet'!I31 -> 0 | J32: ='Balance Sheet'!J31 -> 0 | ... L32: ='Balance Sheet'!L31 -> 0
A33: x | B33: Total Operating Liabilities | C33: =SUM(C28:C32) -> 41027 | D33: =SUM(D28:D32) -> 38236 | E33: =SUM(E28:E32) -> 45941 | F33: =SUM(F28:F32) -> 54944 | G33: =SUM(G28:G32) -> 55750 | H33: =SUM(H28:H32) -> 59627.176 | I33: =SUM(I28:I32) -> 66137.53 | J33: =SUM(J28:J32) -> 72080.089 | ... L33: =SUM(L28:L32) -> 84509.406
B35: Changes In Operating Assets(cash flow) | D35: =-(D25-C25) -> -3200 | E35: =-(E25-D25) -> -2265 | F35: =-(F25-E25) -> -7855 | G35: =-(G25-F25) -> -5822 | H35: =-(H25-G25) -> -323.29804 | I35: =-(I25-H25) -> -5998.7239 | J35: =-(J25-I25) -> -5703.6919 | K35: =-(K25-J25) -> -6055.0384 | L35: =-(L25-K25) -> -5458.8357
B36: Changes in Operating Liabilities(Cash Flow) | D36: =(D33-C33) -> -2791 | E36: =(E33-D33) -> 7705 | F36: =(F33-E33) -> 9003 | G36: =(G33-F33) -> 806 | H36: =(H33-G33) -> 3877.1761 | I36: =(I33-H33) -> 6510.3541 | J36: =(J33-I33) -> 5942.5587 | K36: =(K33-J33) -> 5814.3706 | L36: =(L33-K33) -> 6614.9467
A37: x | B37: Changes Operating Working Capital | D37: =SUM(D35:D36) -> -5991 | E37: =SUM(E35:E36) -> 5440 | F37: =SUM(F35:F36) -> 1148 | G37: =SUM(G35:G36) -> -5016 | H37: =SUM(H35:H36) -> 3553.878 | I37: =SUM(I35:I36) -> 511.63017 | J37: =SUM(J35:J36) -> 238.86679 | K37: =SUM(K35:K36) -> -240.66782 | L37: =SUM(L35:L36) -> 1156.111
A39: x | B39: Non Working Capital Analysis
B40: Goodwill | C40: ='Balance Sheet'!C16 -> 45811 | D40: ='Balance Sheet'!D16 -> 45811 | E40: ='Balance Sheet'!E16 -> 44259 | F40: ='Balance Sheet'!F16 -> 44370 | G40: ='Balance Sheet'!G16 -> 44924 | H40: ='Balance Sheet'!H16 -> 44924 | I40: ='Balance Sheet'!I16 -> 44924 | J40: ='Balance Sheet'!J16 -> 44924 | ... L40: ='Balance Sheet'!L16 -> 44924
B41: Other intangible assets, net | C41: ='Balance Sheet'!C17 -> 34102 | D41: ='Balance Sheet'!D17 -> 32492 | E41: ='Balance Sheet'!E17 -> 30863 | F41: ='Balance Sheet'!F17 -> 29417 | G41: ='Balance Sheet'!G17 -> 28560 | H41: ='Balance Sheet'!H17 -> 32406.074 | I41: ='Balance Sheet'!I17 -> 36826.813 | J41: ='Balance Sheet'!J17 -> 41103.213 | ... L41: ='Balance Sheet'!L17 -> 50350.128
B42: Separate account assets | C42: ='Balance Sheet'!C19 -> 8337 | D42: ='Balance Sheet'!D19 -> 7278 | E42: ='Balance Sheet'!E19 -> 7430 | F42: ='Balance Sheet'!F19 -> 7278 | G42: ='Balance Sheet'!G19 -> 7511 | H42: ='Balance Sheet'!H19 -> 8178.6758 | I42: ='Balance Sheet'!I19 -> 8906.9501 | J42: ='Balance Sheet'!J19 -> 9528.4721 | ... L42: ='Balance Sheet'!L19 -> 10945.68
B43: Other long-term assets | C43: ='Balance Sheet'!C18 -> 3405 | D43: ='Balance Sheet'!D18 -> 3426 | E43: ='Balance Sheet'!E18 -> 3421 | F43: ='Balance Sheet'!F18 -> 2786 | G43: ='Balance Sheet'!G18 -> 2885 | H43: ='Balance Sheet'!H18 -> 3086.2928 | I43: ='Balance Sheet'!I18 -> 3083.175 | J43: ='Balance Sheet'!J18 -> 2989.3246 | ... L43: ='Balance Sheet'!L18 -> 2845.8768
A44: x | B44: Total Non Working Assets | C44: =SUM(C40:C43) -> 91655 | D44: =SUM(D40:D43) -> 89007 | E44: =SUM(E40:E43) -> 85973 | F44: =SUM(F40:F43) -> 83851 | G44: =SUM(G40:G43) -> 83880 | H44: =SUM(H40:H43) -> 88595.043 | I44: =SUM(I40:I43) -> 93740.938 | J44: =SUM(J40:J43) -> 98545.01 | ... L44: =SUM(L40:L43) -> 109065.68
A46: x | B46: Liabilities
B47: Deferred tax liabilities | C47: ='Balance Sheet'!C34 -> 8346 | D47: ='Balance Sheet'!D34 -> 7751 | E47: ='Balance Sheet'!E34 -> 7173 | F47: ='Balance Sheet'!F34 -> 6975 | G47: ='Balance Sheet'!G34 -> 7145 | H47: ='Balance Sheet'!H34 -> 7715.7319 | I47: ='Balance Sheet'!I34 -> 8221.8001 | J47: ='Balance Sheet'!J34 -> 8594.3082 | ... L47: ='Balance Sheet'!L34 -> 9851.112
B48: Other long-term liabilities | C48: ='Balance Sheet'!C35 -> 3762 | D48: ='Balance Sheet'!D35 -> 3142 | E48: ='Balance Sheet'!E35 -> 3441 | F48: ='Balance Sheet'!F35 -> 3215 | G48: ='Balance Sheet'!G35 -> 4238 | H48: ='Balance Sheet'!H35 -> 4629.4391 | I48: ='Balance Sheet'!I35 -> 5070.11 | J48: ='Balance Sheet'!J35 -> 5418.1508 | ... L48: ='Balance Sheet'!L35 -> 6348.4944
B49: Non-current insurance and contractholder liabilities | C49: ='Balance Sheet'!C33 -> 12563 | D49: ='Balance Sheet'!D33 -> 11481 | E49: ='Balance Sheet'!E33 -> 10904 | F49: ='Balance Sheet'!F33 -> 10254 | G49: ='Balance Sheet'!G33 -> 9938 | H49: ='Balance Sheet'!H33 -> 10802.025 | I49: ='Balance Sheet'!I33 -> 11647.55 | J49: ='Balance Sheet'!J33 -> 12330.964 | ... L49: ='Balance Sheet'!L33 -> 14229.384
B50: Liabilities of businesses held for sale, non-current | C50: ='Balance Sheet'!C68 -> 0 | D50: ='Balance Sheet'!D68 -> 0 | E50: ='Balance Sheet'!E68 -> 591 | F50: ='Balance Sheet'!F68 -> 0 | G50: ='Balance Sheet'!G68 -> 0 | H50: ='Balance Sheet'!H68 -> 0 | I50: ='Balance Sheet'!I68 -> 0 | J50: ='Balance Sheet'!J68 -> 0 | ... L50: ='Balance Sheet'!L68 -> 0
B51: Separate account liabilities | C51: ='Balance Sheet'!C67 -> 8337 | D51: ='Balance Sheet'!D67 -> 7278 | E51: ='Balance Sheet'!E67 -> 7430 | F51: ='Balance Sheet'!F67 -> 7278 | G51: ='Balance Sheet'!G67 -> 7511 | H51: ='Balance Sheet'!H67 -> 8178.6758 | I51: ='Balance Sheet'!I67 -> 8906.9501 | J51: ='Balance Sheet'!J67 -> 9528.4721 | ... L51: ='Balance Sheet'!L67 -> 10945.68
A52: x | B52: Total Non Working Liabilities | C52: =SUM(C47:C51) -> 33008 | D52: =SUM(D47:D51) -> 29652 | E52: =SUM(E47:E51) -> 29539 | F52: =SUM(F47:F51) -> 27722 | G52: =SUM(G47:G51) -> 28832 | H52: =SUM(H47:H51) -> 31325.871 | I52: =SUM(I47:I51) -> 33846.41 | J52: =SUM(J47:J51) -> 35871.895 | ... L52: =SUM(L47:L51) -> 41374.67
B54: Changes In Non Working Assets | D54: =-(D44-C44) -> 2648 | E54: =-(E44-D44) -> 3034 | F54: =-(F44-E44) -> 2122 | G54: =-(G44-F44) -> -29 | H54: =-(H44-G44) -> -4715.0425 | I54: =-(I44-H44) -> -5145.8955 | J54: =-(J44-I44) -> -4804.0716 | K54: =-(K44-J44) -> -4783.6676 | L54: =-(L44-K44) -> -5737.0076
B55: Changes In Non Working Liabilites | D55: =D52-C52 -> -3356 | E55: =E52-D52 -> -113 | F55: =F52-E52 -> -1817 | G55: =G52-F52 -> 1110 | H55: =H52-G52 -> 2493.8715 | I55: =I52-H52 -> 2520.5388 | J55: =J52-I52 -> 2025.4846 | K55: =K52-J52 -> 2323.5514 | L55: =L52-K52 -> 3179.2241
A56: x | B56: Changes In Non Operating Working Capital | D56: =SUM(D54:D55) -> -708 | E56: =SUM(E54:E55) -> 2921 | F56: =SUM(F54:F55) -> 305 | G56: =SUM(G54:G55) -> 1081 | H56: =SUM(H54:H55) -> -2221.171 | I56: =SUM(I54:I55) -> -2625.3566 | J56: =SUM(J54:J55) -> -2778.587 | K56: =SUM(K54:K55) -> -2460.1162 | L56: =SUM(L54:L55) -> -2557.7835

Sheet Debt Schedule
B2: CI Debt Schedule | F2: Projected
B3: (in $millions) | E3: 2025 | F3: 2026 | G3: 2027 | H3: 2028 | I3: 2029 | J3: 2030
B4: Short Term Debt
B6: March 2026 Beginning Balance | F6: =E8 -> 549
B7: Paydown 2026 | F7: =$E$8/1 -> 549
B8: March 2026 Ending Balance | E8: 549 | F8: =F6-F7 -> 0
B10: Interest Rate | F10: 0.0125
B11: Average Balance | F11: =AVERAGE(E8:F8) -> 274.5
B12: Interest Expense | F12: =F10*F11 -> 3.43125
B14: Other, Including Finance Leases Beginning Balance | F14: =E16 -> 43 | G14: =F16 -> 41 | H14: =G16 -> 39 | I14: =H16 -> 37 | J14: =I16 -> 35
B15: Paydown | F15: 2 | G15: 2 | H15: 2 | I15: 2 | J15: 2
B16: Other, Including Finance Leases Ending Balance | E16: 43 | F16: =F14-F15 -> 41 | G16: =G14-G15 -> 39 | H16: =H14-H15 -> 37 | I16: =I14-I15 -> 35 | J16: =J14-J15 -> 33
B18: Interest Rate | F18: 0.0509 | G18: 0.0509 | H18: 0.0509 | I18: 0.0509 | J18: 0.0509
B19: Average Balance | F19: =AVERAGE(E16:F16) -> 42 | G19: =AVERAGE(F16:G16) -> 40 | H19: =AVERAGE(G16:H16) -> 38 | I19: =AVERAGE(H16:I16) -> 36 | J19: =AVERAGE(I16:J16) -> 34
B20: Interest Expense | F20: =F18*F19 -> 2.1378 | G20: =G18*G19 -> 2.036 | H20: =H18*H19 -> 1.9342 | I20: =I18*I19 -> 1.8324 | J20: =J18*J19 -> 1.7306
B23: Revolver | F23: ='Balance Sheet'!H26 -> 8038.1749 | G23: ='Balance Sheet'!I26 -> 11022.902 | H23: ='Balance Sheet'!J26 -> 6114.0237 | I23: ='Balance Sheet'!K26 -> 0 | J23: ='Balance Sheet'!L26 -> 0
B25: Interest Rate | F25: 0.0509 | G25: 0.0509 | H25: 0.0509 | I25: 0.0509 | J25: 0.0509
B27: Average Balance | F27: =AVERAGE(E23:F23) -> 8038.1749 | G27: =AVERAGE(F23:G23) -> 9530.5383 | H27: =AVERAGE(G23:H23) -> 8568.4627 | I27: =AVERAGE(H23:I23) -> 3057.0119 | J27: =AVERAGE(I23:J23) -> 0
B28: Interest Expense | F28: =F27*F25 -> 409.1431 | G28: =G27*G25 -> 485.1044 | H28: =H27*H25 -> 436.13475 | I28: =I27*I25 -> 155.6019 | J28: =J27*J25 -> 0
B30: Long Term Debt
B32: March 2027 Term Loan Beginning Balance | F32: =E34 -> 1481 | G32: =F34 -> 740.5
B33: Paydown (2026-2027) | F33: =$F$32/2 -> 740.5 | G33: =$F$32/2 -> 740.5
B34: March 2027 Term Loan Ending Balance | E34: 1481 | F34: =F32-F33 -> 740.5 | G34: =G32-G33 -> 0
B36: Interest Rate | E36: 0.034 | F36: 0.034 | G36: 0.034
B37: Average Balance | F37: =AVERAGE(E34:F34) -> 1110.75 | G37: =AVERAGE(F34:G34) -> 370.25
B38: Interest Expense | F38: =F37*F36 -> 37.7655 | G38: =G37*G36 -> 12.5885
B40: May 2027 Term Loan Beginning Balance | F40: =E42 -> 260 | G40: =F42 -> 130
B41: Paydown (2026-2027) | F41: =$F$40/2 -> 130 | G41: =$F$40/2 -> 130
B42: May 2027 Term Loan Ending Balance | E42: 260 | F42: =F40-F41 -> 130 | G42: =G40-G41 -> 0
B44: Interest Rate | E44: 0.07875 | F44: 0.07875 | G44: 0.07875
B45: Average Balance | F45: =AVERAGE(E42:F42) -> 195 | G45: =AVERAGE(F42:G42) -> 65
B46: Interest Expense | F46: =F45*F44 -> 15.35625 | G46: =G45*G44 -> 5.11875
B48: October 2027 Term Loan Beginning Balance | F48: =E50 -> 599 | G48: =F50 -> 299.5
B49: Paydown (2026-2027) | F49: =$F$48/2 -> 299.5 | G49: =$F$48/2 -> 299.5
B50: October 2027 Term Loan Ending Balance | E50: 599 | F50: =F48-F49 -> 299.5 | G50: =G48-G49 -> 0
B52: Interest Rate | E52: 0.0305 | F52: 0.0305 | G52: 0.0305
B53: Average Balance | F53: =AVERAGE(E50:F50) -> 449.25 | G53: =AVERAGE(F50:G50) -> 149.75
B54: Interest Expense | F54: =F53*F52 -> 13.702125 | G54: =G53*G52 -> 4.567375
B56: October 2028 Term Loan Beginning Balance | F56: =E58 -> 3792 | G56: =F58 -> 2528 | H56: =G58 -> 1264
B57: Paydown (2026-2028) | F57: =$F$56/3 -> 1264 | G57: =$F$56/3 -> 1264 | H57: =$F$56/3 -> 1264
B58: October 2028 Term Loan Ending Balance | E58: 3792 | F58: =F56-F57 -> 2528 | G58: =G56-G57 -> 1264 | H58: =H56-H57 -> 0
B60: Interest Rate | E60: 0.04375 | F60: 0.04375 | G60: 0.04375
B61: Average Balance | F61: =AVERAGE(E58:F58) -> 3160 | G61: =AVERAGE(F58:G58) -> 1896 | H61: =AVERAGE(G58:H58) -> 632
B62: Interest Expense | F62: =F61*E60 -> 138.25 | G62: =G61*F60 -> 82.95 | H62: =H61*G60 -> 27.65
B64: May 2029 Term Loan Beginning Balance | F64: =E66 -> 996 | G64: =F66 -> 747 | H64: =G66 -> 498 | I64: =H66 -> 249
B65: Paydown (2026-2029) | F65: =$F$64/4 -> 249 | G65: =$F$64/4 -> 249 | H65: =$F$64/4 -> 249 | I65: =$F$64/4 -> 249
B66: May 2029 Term Loan Ending Balance | E66: 996 | F66: =F64-F65 -> 747 | G66: =G64-G65 -> 498 | H66: =H64-H65 -> 249 | I66: =I64-I65 -> 0
B68: Interest Rate | E68: 0.05 | F68: 0.05 | G68: 0.05 | H68: 0.05
B69: Average Balance | F69: =AVERAGE(E66:F66) -> 871.5 | G69: =AVERAGE(F66:G66) -> 622.5 | H69: =AVERAGE(G66:H66) -> 373.5 | I69: =AVERAGE(H66:I66) -> 124.5
B70: Interest Expense | F70: =F69*E68 -> 43.575 | G70: =G69*F68 -> 31.125 | H70: =H69*G68 -> 18.675 | I70: =I69*H68 -> 6.225
B72: March 2030 Term Loan Beginning Balance | F72: =E74 -> 1406 | G72: =F74 -> 1124.8 | H72: =G74 -> 843.6 | I72: =H74 -> 562.4 | J72: =I74 -> 281.2
B73: Paydown (2026-2030) | F73: =$F$72/5 -> 281.2 | G73: =$F$72/5 -> 281.2 | H73: =$F$72/5 -> 281.2 | I73: =$F$72/5 -> 281.2 | J73: =$F$72/5 -> 281.2
B74: March 2030 Term Loan Ending Balance | E74: 1406 | F74: =F72-F73 -> 1124.8 | G74: =G72-G73 -> 843.6 | H74: =H72-H73 -> 562.4 | I74: =I72-I73 -> 281.2 | J74: =J72-J73 -> 0
B76: Interest Rate | E76: 0.024 | F76: 0.024 | G76: 0.024 | H76: 0.024 | I76: 0.024
B77: Average Balance | F77: =AVERAGE(E74:F74) -> 1265.4 | G77: =AVERAGE(F74:G74) -> 984.2 | H77: =AVERAGE(G74:H74) -> 703 | I77: =AVERAGE(H74:I74) -> 421.8 | J77: =AVERAGE(I74:J74) -> 140.6
B78: Interest Expense | F78: =F77*E76 -> 30.3696 | G78: =G77*F76 -> 23.6208 | H78: =H77*G76 -> 16.872 | I78: =I77*H76 -> 10.1232 | J78: =J77*I76 -> 3.3744
B80: September 2030 Term Loan Beginning Balance | F80: =E82 -> 993 | G80: =F82 -> 794.4 | H80: =G82 -> 595.8 | I80: =H82 -> 397.2 | J80: =I82 -> 198.6
B81: Paydown (2026-2030) | F81: =$F$80/5 -> 198.6 | G81: =$F$80/5 -> 198.6 | H81: =$F$80/5 -> 198.6 | I81: =$F$80/5 -> 198.6 | J81: =$F$80/5 -> 198.6
B82: September 2030 Term Loan Ending Balance | E82: 993 | F82: =F80-F81 -> 794.4 | G82: =G80-G81 -> 595.8 | H82: =H80-H81 -> 397.2 | I82: =I80-I81 -> 198.6 | J82: =J80-J81 -> 0
B84: Interest Rate | E84: 0.045 | F84: 0.045 | G84: 0.045 | H84: 0.045 | I84: 0.045
B85: Average Balance | F85: =AVERAGE(E82:F82) -> 893.7 | G85: =AVERAGE(F82:G82) -> 695.1 | H85: =AVERAGE(G82:H82) -> 496.5 | I85: =AVERAGE(H82:I82) -> 297.9 | J85: =AVERAGE(I82:J82) -> 99.3
B86: Interest Expense | F86: =F85*E84 -> 40.2165 | G86: =G85*F84 -> 31.2795 | H86: =H85*G84 -> 22.3425 | I86: =I85*H84 -> 13.4055 | J86: =J85*I84 -> 4.4685
B88: March 2031 Term Loan Beginning Balance | F88: =E90 -> 1420 | G88: =F90 -> 1183.3333 | H88: =G90 -> 946.66667 | I88: =H90 -> 710 | J88: =I90 -> 473.33333
B89: Paydown (2026-2031) | F89: =$F$88/6 -> 236.66667 | G89: =$F$88/6 -> 236.66667 | H89: =$F$88/6 -> 236.66667 | I89: =$F$88/6 -> 236.66667 | J89: =$F$88/6 -> 236.66667
B90: March 2031 Term Loan Ending Balance | E90: 1420 | F90: =F88-F89 -> 1183.3333 | G90: =G88-G89 -> 946.66667 | H90: =H88-H89 -> 710 | I90: =I88-I89 -> 473.33333 | J90: =J88-J89 -> 236.66667
B92: Interest Rate | E92: 0.02375 | F92: 0.02375 | G92: 0.02375 | H92: 0.02375 | I92: 0.02375 | J92: 0.02375
B93: Average Balance | F93: =AVERAGE(E90:F90) -> 1301.6667 | G93: =AVERAGE(F90:G90) -> 1065 | H93: =AVERAGE(G90:H90) -> 828.33333 | I93: =AVERAGE(H90:I90) -> 591.66667 | J93: =AVERAGE(I90:J90) -> 355
B94: Interest Expense | F94: =F93*E92 -> 30.914583 | G94: =G93*F92 -> 25.29375 | H94: =H93*G92 -> 19.672917 | I94: =I93*H92 -> 14.052083 | J94: =J93*I92 -> 8.43125
B96: May 2031 Term Loan Beginning Balance | F96: =E98 -> 750 | G96: =F98 -> 625 | H96: =G98 -> 500 | I96: =H98 -> 375 | J96: =I98 -> 250
B97: Paydown (2026-2031) | F97: =$F$96/6 -> 125 | G97: =$F$96/6 -> 125 | H97: =$F$96/6 -> 125 | I97: =$F$96/6 -> 125 | J97: =$F$96/6 -> 125
B98: May 2031 Term Loan Ending Balance | E98: 750 | F98: =F96-F97 -> 625 | G98: =G96-G97 -> 500 | H98: =H96-H97 -> 375 | I98: =I96-I97 -> 250 | J98: =J96-J97 -> 125
B100: Interest Rate | E100: 0.05125 | F100: 0.05125 | G100: 0.05125 | H100: 0.05125 | I100: 0.05125 | J100: 0.05125
B101: Average Balance | F101: =AVERAGE(E98:F98) -> 687.5 | G101: =AVERAGE(F98:G98) -> 562.5 | H101: =AVERAGE(G98:H98) -> 437.5 | I101: =AVERAGE(H98:I98) -> 312.5 | J101: =AVERAGE(I98:J98) -> 187.5
B102: Interest Expense | F102: =F101*E100 -> 35.234375 | G102: =G101*F100 -> 28.828125 | H102: =H101*G100 -> 22.421875 | I102: =I101*H100 -> 16.015625 | J102: =J101*I100 -> 9.609375
B104: September 2032 Term Loan Beginning Balance | F104: =E106 -> 1243 | G104: =F106 -> 1065.4286 | H104: =G106 -> 887.85714 | I104: =H106 -> 710.28571 | J104: =I106 -> 532.71429
B105: Paydown (2026-2032) | F105: =$F$104/7 -> 177.57143 | G105: =$F$104/7 -> 177.57143 | H105: =$F$104/7 -> 177.57143 | I105: =$F$104/7 -> 177.57143 | J105: =$F$104/7 -> 177.57143
B106: September 2032 Term Loan Ending Balance | E106: 1243 | F106: =F104-F105 -> 1065.4286 | G106: =G104-G105 -> 887.85714 | H106: =H104-H105 -> 710.28571 | I106: =I104-I105 -> 532.71429 | J106: =J104-J105 -> 355.14286
B108: Interest Rate | E108: 0.04875 | F108: 0.04875 | G108: 0.04875 | H108: 0.04875 | I108: 0.04875 | J108: 0.04875
B109: Average Balance | F109: =AVERAGE(E106:F106) -> 1154.2143 | G109: =AVERAGE(F106:G106) -> 976.64286 | H109: =AVERAGE(G106:H106) -> 799.07143 | I109: =AVERAGE(H106:I106) -> 621.5 | J109: =AVERAGE(I106:J106) -> 443.92857
B110: Interest Expense | F110: =F109*E108 -> 56.267946 | G110: =G109*F108 -> 47.611339 | H110: =H109*G108 -> 38.954732 | I110: =I109*H108 -> 30.298125 | J110: =J109*I108 -> 21.641518
B112: January 2033 Term Loan Beginning Balance | F112: =E114 -> 45 | G112: =F114 -> 39.375 | H112: =G114 -> 33.75 | I112: =H114 -> 28.125 | J112: =I114 -> 22.5
B113: Paydown (2026-2033) | F113: =$F$112/8 -> 5.625 | G113: =$F$112/8 -> 5.625 | H113: =$F$112/8 -> 5.625 | I113: =$F$112/8 -> 5.625 | J113: =$F$112/8 -> 5.625
B114: January 2033 Term Loan Ending Balance | E114: 45 | F114: =F112-F113 -> 39.375 | G114: =G112-G113 -> 33.75 | H114: =H112-H113 -> 28.125 | I114: =I112-I113 -> 22.5 | J114: =J112-J113 -> 16.875
B116: Interest Rate | E116: 0.0808 | F116: 0.0808 | G116: 0.0808 | H116: 0.0808 | I116: 0.0808 | J116: 0.0808
B117: Average Balance | F117: =AVERAGE(E114:F114) -> 42.1875 | G117: =AVERAGE(F114:G114) -> 36.5625 | H117: =AVERAGE(G114:H114) -> 30.9375 | I117: =AVERAGE(H114:I114) -> 25.3125 | J117: =AVERAGE(I114:J114) -> 19.6875
B118: Interest Expense | F118: =F117*E116 -> 3.40875 | G118: =G117*F116 -> 2.95425 | H118: =H117*G116 -> 2.49975 | I118: =I117*H116 -> 2.04525 | J118: =J117*I116 -> 1.59075
B120: March 2033 Term Loan Beginning Balance | F120: =E122 -> 796 | G120: =F122 -> 696.5 | H120: =G122 -> 597 | I120: =H122 -> 497.5 | J120: =I122 -> 398
B121: Paydown (2026-2033) | F121: =$F$120/8 -> 99.5 | G121: =$F$120/8 -> 99.5 | H121: =$F$120/8 -> 99.5 | I121: =$F$120/8 -> 99.5 | J121: =$F$120/8 -> 99.5
B122: March 2033 Term Loan Ending Balance | E122: 796 | F122: =F120-F121 -> 696.5 | G122: =G120-G121 -> 597 | H122: =H120-H121 -> 497.5 | I122: =I120-I121 -> 398 | J122: =J120-J121 -> 298.5
B124: Interest Rate | E124: 0.054 | F124: 0.054 | G124: 0.054 | H124: 0.054 | I124: 0.054 | J124: 0.054
B125: Average Balance | F125: =AVERAGE(E122:F122) -> 746.25 | G125: =AVERAGE(F122:G122) -> 646.75 | H125: =AVERAGE(G122:H122) -> 547.25 | I125: =AVERAGE(H122:I122) -> 447.75 | J125: =AVERAGE(I122:J122) -> 348.25
B126: Interest Expense | F126: =F125*E124 -> 40.2975 | G126: =G125*F124 -> 34.9245 | H126: =H125*G124 -> 29.5515 | I126: =I125*H124 -> 24.1785 | J126: =J125*I124 -> 18.8055
B128: February 2034 Term Loan Beginning Balance | F128: =E130 -> 1250 | G128: =F130 -> 1111.1111 | H128: =G130 -> 972.22222 | I128: =H130 -> 833.33333 | J128: =I130 -> 694.44444
B129: Paydown (2026-2034) | F129: =$F$128/9 -> 138.88889 | G129: =$F$128/9 -> 138.88889 | H129: =$F$128/9 -> 138.88889 | I129: =$F$128/9 -> 138.88889 | J129: =$F$128/9 -> 138.88889
B130: February 2034 Term Loan Ending Balance | E130: 1250 | F130: =F128-F129 -> 1111.1111 | G130: =G128-G129 -> 972.22222 | H130: =H128-H129 -> 833.33333 | I130: =I128-I129 -> 694.44444 | J130: =J128-J129 -> 555.55556
B132: Interest Rate | E132: 0.0525 | F132: 0.0525 | G132: 0.0525 | H132: 0.0525 | I132: 0.0525 | J132: 0.0525
B133: Average Balance | F133: =AVERAGE(E130:F130) -> 1180.5556 | G133: =AVERAGE(F130:G130) -> 1041.6667 | H133: =AVERAGE(G130:H130) -> 902.77778 | I133: =AVERAGE(H130:I130) -> 763.88889 | J133: =AVERAGE(I130:J130) -> 625
B134: Interest Expense | F134: =F133*E132 -> 61.979167 | G134: =G133*F132 -> 54.6875 | H134: =H133*G132 -> 47.395833 | I134: =I133*H132 -> 40.104167 | J134: =J133*I132 -> 32.8125
B136: January 2036 Term Loan Beginning Balance | F136: =E138 -> 1488 | G136: =F138 -> 1352.7273 | H136: =G138 -> 1217.4545 | I136: =H138 -> 1082.1818 | J136: =I138 -> 946.90909
B137: Paydown (2026-2036) | F137: =$F$136/11 -> 135.27273 | G137: =$F$136/11 -> 135.27273 | H137: =$F$136/11 -> 135.27273 | I137: =$F$136/11 -> 135.27273 | J137: =$F$136/11 -> 135.27273
...

Sheet LTMS
A1: LTMs
A2: (In Millions of $, except per share data)
B4: Cigna Group
B5: in millions
C6: FY 2025
B7: Revenue | C7: 274900
B8: Operating Income | C8: 7781
B9: D&A | C9: 2775
B10: EBITDA | C10: =C8+C9 -> 10556
B12: Net Income | C12: 6288
B13: CapEx | C13: 1200
B14: FCF | C14: =C12+C13 -> 7488
B16: UnitedHealth Group Inc (UNH) | E16: Elevance Health Inc (ELV) | H16: CVS Health Corp (CVS) | K16: EPS CALCS
B17: in millions | E17: in millions | H17: in millions | K17: in millions
C18: FY2025 | F18: FY2025 | I18: FY2025 | L18: FY2025 | M18: LTM
B19: Revenue | C19: 447567 | E19: Revenue | F19: 199125 | H19: Revenue | I19: 1728 | K19: CI | L19: 22.18 | M19: =L19 -> 22.18
B20: Operating Income | C20: 18964 | E20: Operating Income | F20: 7199 | H20: Operating Income | I20: 4660 | K20: UNH | L20: 13.23 | M20: 24365
B21: D&A | C21: 4361 | E21: D&A | F21: 1546 | H21: D&A | I21: 4606 | K21: MOH | L21: 9.84 | M21: =L21 -> 9.84
B22: EBITDA | C22: =SUM(C20:C21) -> 23325 | E22: EBITDA | F22: =F21+F20 -> 8745 | H22: EBITDA | I22: =I20+I21 -> 9266 | K22: ELV | L22: 25.28 | M22: =L22 -> 25.28
K23: HUM | L23: 9.84 | M23: =L23 -> 9.84
B24: Net Income | C24: 12056 | E24: Net Income | F24: 5662 | H24: Net Income | I24: 1728 | K24: CVS | L24: 1.39 | M24: =L24 -> 1.39
B25: CapEx | C25: 10762 | E25: CapEx | F25: 1116 | H25: CapEx | I25: -2832 | K25: HCA | L25: 239.5 | M25: =L25 -> 239.5
B26: FCF | C26: =C24+C25 -> 22818 | E26: FCF | F26: =F24+F25 -> 6778 | H26: FCF | I26: =I24+I25 -> -1104
B28: Molina Healthcare Inc (MOH) | E28: Humana Inc (HUM) | H28: UnitedHealth Group Inc (UNH) | K28: Total Debt & Cash
B29: in millions | E29: in millions | H29: in millions
C30: FY2025 | F30: FY2025 | I30: FY2025 | L30: Short Term | M30: Long Term | N30: Total Debt | O30: Cash
B31: Revenue | C31: 45426 | E31: Revenue | F31: 129664 | H31: Revenue | I31: 75600 | K31: CI | L31: 592 | M31: 30871 | N31: =L31+M31 -> 31463 | O31: ='Balance Sheet'!G5 -> 7676
B32: Operating Income | C32: 781 | E32: Operating Income | F32: 129960 | H32: Operating Income | I32: 9832 | K32: UNH | L32: 6069 | M32: 72320 | N32: 77681 | O32: 24365
B33: D&A | C33: 195 | E33: D&A | F33: 698 | H33: D&A | I33: 3523 | K33: MOH | L33: 0 | M33: 3766 | N33: 3766 | O33: 4248
B34: EBITDA | C34: =SUM(C32:C33) -> 976 | E34: EBITDA | F34: =SUM(F32:F33) -> 130658 | H34: EBITDA | I34: =I32+I33 -> 13355 | K34: ELV | L34: 150 | M34: 30797 | N34: =L34+M34 -> 30947 | O34: 9491
K35: HUM | L35: 0 | M35: 12369 | N35: =M35 -> 12369 | O35: 1328
B36: Net Income | C36: 472 | E36: Net Income | F36: 1203 | H36: Net Income | I36: 7782 | K36: CVS | L36: 0 | M36: 60502 | N36: =L36+M36 -> 60502 | O36: 8453
B37: CapEx | C37: 301 | E37: CapEx | F37: 2231 | H37: CapEx | I37: -4944 | K37: HCA | L37: 4889 | M37: 41603 | N37: 46492 | O37: 1040
B38: FCF | C38: =C36+C37 -> 773 | E38: FCF | F38: =F36+F37 -> 3434 | H38: FCF | I38: =I36+I37 -> 2838

Sheet Comps
B2: Public Company Comparables | I2: EV/
B3: Company | C3: Ticker | D3: Share Price | E3: Shares Out | F3: Equity Value | G3: Net Debt | H3: Enterprise Value | I3: LTM Sales | J3: LTM EBITDA | K3: LTM EBIT | L3: LTM Net Income | M3: P/E
B4: Cigna Group | C4: CI | D4: 271.25 | E4: 2635 | F4: =E4*D4 -> 714743.75 | G4: =LTMS!N31-LTMS!O31 -> 23787 | H4: =F4+LTMS!N31-LTMS!O31 -> 738530.75 | I4: =H4/LTMS!C7 -> 2.6865433 | J4: =H4/LTMS!C10 -> 69.963125 | K4: =H4/LTMS!C8 -> 94.914632 | L4: =H4/LTMS!C12 -> 117.45082 | M4: =D4/LTMS!M19 -> 12.229486
B5: United Healthcare | C5: UNH | D5: 304.33 | E5: 907 | F5: =E5*D5 -> 276027.31 | G5: =LTMS!N32-LTMS!O32 -> 53316 | H5: =F5+LTMS!N32-LTMS!O32 -> 329343.31 | I5: =H5/LTMS!I31 -> 4.356393 | J5: =H5/LTMS!I34 -> 24.660675 | K5: =H5/LTMS!I32 -> 33.497082 | L5: =H5/LTMS!I36 -> 42.321166 | M5: =D5/LTMS!L20 -> 23.003023
B6: Elevance Health | C6: ELV | D6: 311.53 | E6: 220 | F6: =E6*D6 -> 68536.6 | G6: =LTMS!N34-LTMS!O34 -> 21456 | H6: =F6+LTMS!N34-LTMS!O34 -> 89992.6 | I6: =LTMS!F19/LTMS!F19 -> 1 | J6: =H6/LTMS!F22 -> 10.290749 | K6: =H6/LTMS!I20 -> 19.311717 | L6: =H6/LTMS!F24 -> 15.894136 | M6: =D6/LTMS!L22 -> 12.32318
B7: CVS Health | C7: CVS | D7: 79.33 | E7: 1272 | F7: =E7*D7 -> 100907.76 | G7: =LTMS!N36-LTMS!O36 -> 52049 | H7: =F7+LTMS!N36-LTMS!O36 -> 152956.76 | I7: =H7/LTMS!I19 -> 88.516644 | J7: =H7/LTMS!I22 -> 16.507313 | K7: =H7/LTMS!I20 -> 32.823339 | L7: =H7/LTMS!I24 -> 88.516644 | M7: =D7/LTMS!L24 -> 57.071942
B8: Molina Healthcare Inc | C8: MOH | D8: 145.88 | E8: 51 | F8: =E8*D8 -> 7439.88 | G8: =LTMS!N33-LTMS!O33 -> -482 | H8: =F8+G8 -> 6957.88 | I8: =H8/LTMS!C31 -> 0.15316955 | J8: =H8/LTMS!C34 -> 7.1289754 | K8: =H8/LTMS!C32 -> 8.9089373 | L8: =H8/LTMS!C36 -> 14.741271 | M8: =D8/LTMS!M21 -> 14.825203
B9: Humana Inc | C9: HUM | D9: 192.15 | E9: 120 | F9: =E9*D9 -> 23058 | G9: =LTMS!N35-LTMS!O35 -> 11041 | H9: =F9+G9 -> 34099 | I9: =H9/LTMS!F31 -> 0.2629797 | J9: =H9/LTMS!F34 -> 0.26097904 | K9: =H9/LTMS!F32 -> 0.26238073 | L9: =H9/LTMS!F36 -> 28.344971 | M9: =D9/LTMS!M23 -> 19.527439
B10: HCA Healthcare Inc | C10: HCA | D10: 495.47 | E10: 223 | F10: =E10*D10 -> 110489.81 | G10: =LTMS!N37-LTMS!O37 -> 45452 | H10: =F10+G10 -> 155941.81 | I10: =H10/LTMS!I31 -> 2.0627224 | J10: =H10/LTMS!I34 -> 11.676661 | K10: =H10/LTMS!I32 -> 15.86064 | L10: =H10/LTMS!I36 -> 20.038783 | M10: =D10/LTMS!L25 -> 2.0687683
B11: Max | I11: =MAX(I4:I10) -> 88.516644 | J11: =MAX(J4:J10) -> 69.963125 | K11: =MAX(K4:K10) -> 94.914632 | L11: =MAX(L4:L10) -> 117.45082 | M11: =MAX(M4:M10) -> 57.071942
B12: Min | I12: =MIN(I4:I10) -> 0.15316955 | J12: =MIN(J4:J10) -> 0.26097904 | K12: =MIN(K4:K10) -> 0.26238073 | L12: =MIN(L4:L10) -> 14.741271 | M12: =MIN(M4:M10) -> 2.0687683
B13: Median | I13: =MEDIAN(I4:I10) -> 2.0627224 | J13: =MEDIAN(J4:J10) -> 11.676661 | K13: =MEDIAN(K4:K10) -> 19.311717 | L13: =MEDIAN(L4:L10) -> 28.344971 | M13: =MEDIAN(M4:M10) -> 14.825203
B14: Mean | I14: =AVERAGE(I4:I10) -> 14.14835 | J14: =AVERAGE(J4:J10) -> 20.069782 | K14: =AVERAGE(K4:K10) -> 29.36839 | L14: =AVERAGE(L4:L10) -> 46.758256 | M14: =AVERAGE(M4:M10) -> 20.149863
G21: 271
G22: 22.18

Sheet WACC
P2: Current
O3: CI Share Price 4/14/26 | P3: =Comps!D4 -> 271.25
B4: KE | C4: KD | D4: WACC | E4: Tax Rate | F4: Debt | G4: Equity | H4: TGT Equity | I4: Total Cap | J4: RFR | K4: Beta | L4: ERP | M4: Growth Rate | O4: Shares Out | P4: =Comps!E4 -> 2635
B5: =J5+K5*L5 -> 0.054832 | C5: =J5+1.11% -> 0.05389 | D5: =(B5*H5)+(C5*(1-H5)) -> 0.054831633 | E5: =Assumptions!L47 -> 0.17 | F5: =LTMS!N31 -> 31463 | G5: =P5 -> 714743.75 | H5: =AVERAGE(C29:E29) -> 0.99961022 | I5: =SUM(F5:G5) -> 746206.75 | J5: 0.04279 | K5: 0.27 | L5: 0.0446 | M5: 0.021 | O5: Market Cap | P5: =P3*P4 -> 714743.75
B7: Terminal Value: Exit Multiple
B8: Final Year EBIT | C8: =LTMS!C10 -> 10556
B9: EV/EBIT | C9: =Comps!K13 -> 19.311717
B10: Terminal Value | C10: =C8*C9 -> 203854.48 | N10: Debt: | P10: Ending Balance | Q10: Rate
N11: Term March 2026 | P11: ='Debt Schedule'!F8 -> 0 | Q11: 0.0125
N12: Term March 2027 | P12: ='Debt Schedule'!F34 -> 740.5 | Q12: 0.034
N13: Term May 2027 | P13: ='Debt Schedule'!F42 -> 130 | Q13: 0.07875
N14: Term October 2027 | P14: ='Debt Schedule'!F50 -> 299.5 | Q14: 0.0305
N15: Term October 2028 | P15: ='Debt Schedule'!F58 -> 2528 | Q15: 0.04375
N16: Term May 2029 | P16: ='Debt Schedule'!F66 -> 747 | Q16: 0.05
N17: Term March 2030 | P17: ='Debt Schedule'!F74 -> 1124.8 | Q17: 0.024
N18: Term September 2030 | P18: ='Debt Schedule'!F82 -> 794.4 | Q18: 0.045
N19: Term March 2031 | P19: ='Debt Schedule'!F90 -> 1183.3333 | Q19: 0.02375
N20: Term May 2031 | P20: ='Debt Schedule'!F98 -> 625 | Q20: 0.05125
N21: Term September 2032 | P21: ='Debt Schedule'!F106 -> 1065.4286 | Q21: 0.04875
B22: Capital Structure | C22: 2023 | D22: 2024 | E22: 2025 | N22: Term January 2033 | P22: ='Debt Schedule'!F114 -> 39.375 | Q22: 0.0808
B23: Diluted Shares | C23: 296882 | D23: 283218 | E23: 268563 | N23: Term March 2033 | P23: ='Debt Schedule'!F122 -> 696.5 | Q23: 0.054
B24: Stock Price | C24: 299.45 | D24: 280.7 | E24: 279.12 | N24: Term February 2034 | P24: ='Debt Schedule'!F130 -> 1111.1111 | Q24: 0.0525
B25: Market Cap | C25: =C23*C24 -> 88901315 | D25: =D23*D24 -> 79499293 | E25: =E23*E24 -> 74961305 | N25: Term January 2036 | P25: ='Debt Schedule'!F138 -> 1352.7273 | Q25: 0.0525
B26: Debt | C26: =28155+2775 -> 30930 | D26: =3035+28937 -> 31972 | E26: =592+30871 -> 31463 | N26: Term November 2036 | P26: ='Debt Schedule'!F146 -> 172.72727 | Q26: 0.0615
B27: Total | C27: =C26+C25 -> 88932245 | D27: =D26+D25 -> 79531265 | E27: =E26+E25 -> 74992768 | N27: Term August 2038 | P27: ='Debt Schedule'!F154 -> 2025.2308 | Q27: 0.048
B28: Debt | C28: =C26/C27 -> 0.00034779286 | D28: =D26/D27 -> 0.00040200543 | E28: =E26/E27 -> 0.00041954712 | N28: Term March 2040 | P28: ='Debt Schedule'!F162 -> 698.13333 | Q28: 0.032
B29: Equity | C29: =1-C28 -> 0.99965221 | D29: =1-D28 -> 0.99959799 | E29: =1-E28 -> 0.99958045 | N29: Term March 2041 | P29: ='Debt Schedule'!F170 -> 111.5625 | Q29: 0.05875
N30: Term November 2041 | P30: ='Debt Schedule'!F178 -> 453.75 | Q30: 0.06125
N31: Term February 2042 | P31: ='Debt Schedule'!F186 -> 296.47059 | Q31: 0.05375
N32: Term July 2046 | P32: ='Debt Schedule'!F194 -> 1399.0476 | Q32: 0.048
N33: Term October 2047 | P33: ='Debt Schedule'!F202 -> 945 | Q33: 0.03875
N34: Term December 2048 | P34: ='Debt Schedule'!F210 -> 2842.7826 | Q34: 0.049
N35: Term March 2050 | P35: ='Debt Schedule'!F218 -> 1125.12 | Q35: 0.034
N36: Term March 2051 | P36: ='Debt Schedule'!F226 -> 1355.7692 | Q36: 0.034
N37: Term February 2054 | P37: ='Debt Schedule'!F234 -> 1434.7586 | Q37: 0.056
N38: Term January 2056 | P38: ='Debt Schedule'!F242 -> 711.29032 | Q38: 0.06
N39: Other, including finance leases | P39: ='Debt Schedule'!F254 -> 65
N40: Other, including finance leases | P40: ='Debt Schedule'!F16 -> 41
N41: Total Debt | P41: =SUM(P11:P39) -> 26074.318 | Q41: =SUMPRODUCT(P11:P38,Q11:Q38)/P41 -> 0.044808876

Sheet DCF
B2: Discounted Cash Flow | C2: Historical | H2: Projected | P2: Historical | U2: Projected
B3: Shares in Thousands, $ in Millions | C3: 2021 | D3: =C3+1 -> 2022 | E3: =D3+1 -> 2023 | F3: =E3+1 -> 2024 | G3: =F3+1 -> 2025 | H3: =G3+1 -> 2026 | I3: =H3+1 -> 2027 | J3: =I3+1 -> 2028 | K3: =J3+1 -> 2029 | L3: =K3+1 -> 2030 | P3: 2021 | Q3: 2022 | R3: 2023 | S3: 2024 | T3: 2025 | U3: 2026 | V3: 2027 | W3: 2028 | X3: 2029 | Y3: 2030
B4: Net Sales | C4: ='Income Statement'!C38 -> 174078 | D4: ='Income Statement'!D38 -> 180516 | E4: ='Income Statement'!E38 -> 195265 | F4: ='Income Statement'!F38 -> 247121 | G4: ='Income Statement'!G38 -> 274900 | H4: ='Income Statement'!H38 -> 308629.28 | I4: ='Income Statement'!I38 -> 342575 | J4: ='Income Statement'!J38 -> 373665.57 | ... L4: ='Income Statement'!L38 -> 437827.2 | O4: Net Sales | P4: 174078 | Q4: 180516 | R4: 195265 | S4: 247121 | T4: 274900 | U4: 313231.79 | V4: 350806.38 | W4: 385853.44 | X4: 420159.02 | Y4: 459026.7
B5: Pharmacy and other service costs | C5: ='Income Statement'!C40 -> 117553 | D5: ='Income Statement'!D40 -> 124834 | E5: ='Income Statement'!E40 -> 133801 | F5: ='Income Statement'!F40 -> 182509 | G5: ='Income Statement'!G40 -> 214991 | H5: ='Income Statement'!H40 -> 237644.54 | I5: ='Income Statement'!I40 -> 260357 | J5: ='Income Statement'!J40 -> 280249.18 | ... L5: ='Income Statement'!L40 -> 319613.86 | O5: Pharmacy and other service costs | P5: 117553 | Q5: 124834 | R5: 133801 | S5: 182509 | T5: 214991 | U5: 234923.85 | V5: 257842.69 | W5: 279743.74 | X5: 302514.49 | Y5: 328204.09
B6: Gross Proft | C6: =C4-C5 -> 56525 | D6: =D4-D5 -> 55682 | E6: =E4-E5 -> 61464 | F6: =F4-F5 -> 64612 | G6: =G4-G5 -> 59909 | H6: =H4-H5 -> 70984.733 | I6: =I4-I5 -> 82218.001 | J6: =J4-J5 -> 93416.393 | ... L6: =L4-L5 -> 118213.34 | O6: Gross Proft | P6: 56525 | Q6: 55682 | R6: 61464 | S6: 64612 | T6: 59909 | U6: 78307.948 | V6: 92963.691 | W6: 106109.7 | X6: 117644.52 | Y6: 130822.61
B7: Operating Expenses | C7: =SUM('Income Statement'!C41:C43) -> 48590 | D7: =SUM('Income Statement'!D41:D43) -> 47268 | E7: =SUM('Income Statement'!E41:E43) -> 52928 | F7: =SUM('Income Statement'!F41:F43) -> 55195 | G7: =SUM('Income Statement'!G41:G43) -> 50709 | H7: =SUM('Income Statement'!H41:H43) -> 63639.357 | I7: =SUM('Income Statement'!I41:I43) -> 71598.176 | J7: =SUM('Income Statement'!J41:J43) -> 73911.05 | ... L7: =SUM('Income Statement'!L41:L43) -> 81698.555 | O7: Operating Expenses | P7: 48590 | Q7: 47268 | R7: 52928 | S7: 55195 | T7: 50709 | U7: 56914.217 | V7: 62443.536 | W7: 67254.254 | X7: 72099.287 | Y7: 78768.981
B8: EBIT | C8: =C6-C7 -> 7935 | D8: =D6-D7 -> 8414 | E8: =E6-E7 -> 8536 | F8: =F6-F7 -> 9417 | G8: =G6-G7 -> 9200 | H8: =H6-H7 -> 7345.3768 | I8: =I6-I7 -> 10619.825 | J8: =J6-J7 -> 19505.343 | ... L8: =L6-L7 -> 36514.788 | O8: EBIT | P8: 7935 | Q8: 8414 | R8: 8536 | S8: 9417 | T8: 9200 | U8: 21393.732 | V8: 30520.155 | W8: 38855.441 | X8: 45545.237 | Y8: 52053.627
B10: Free Cash Flow Calculations | C10: 2021 | D10: =C10+1 -> 2022 | E10: =D10+1 -> 2023 | F10: =E10+1 -> 2024 | G10: =F10+1 -> 2025 | H10: =G10+1 -> 2026 | I10: =H10+1 -> 2027 | J10: =I10+1 -> 2028 | K10: =J10+1 -> 2029 | L10: =K10+1 -> 2030 | O10: Free Cash Flow Calculations | P10: 2021 | Q10: =P10+1 -> 2022 | R10: =Q10+1 -> 2023 | S10: =R10+1 -> 2024 | T10: =S10+1 -> 2025 | U10: =T10+1 -> 2026 | V10: =U10+1 -> 2027 | W10: =V10+1 -> 2028 | X10: =W10+1 -> 2029 | Y10: =X10+1 -> 2030 | AA10: Exit Multiple | AB10: 2021 | AC10: 2022 | AD10: 2023 | AE10: 2024 | AF10: 2025 | AG10: 2026 | AH10: 2027 | AI10: 2028 | AJ10: 2029 | AK10: 2030
B11: EBIT | C11: =C8 -> 7935 | D11: =D8 -> 8414 | E11: =E8 -> 8536 | F11: =F8 -> 9417 | G11: =G8 -> 9200 | H11: =H8 -> 7345.3768 | I11: =I8 -> 10619.825 | J11: =J8 -> 19505.343 | ... L11: =L8 -> 36514.788 | O11: EBIT | P11: =P8 -> 7935 | Q11: =Q8 -> 8414 | R11: =R8 -> 8536 | S11: =S8 -> 9417 | T11: =T8 -> 9200 | U11: =U8 -> 21393.732 | V11: =V8 -> 30520.155 | W11: =W8 -> 38855.441 | ... Y11: =Y8 -> 52053.627 | AA11: EBIT | AB11: 7935 | AC11: 8414 | AD11: 8536 | AE11: 9417 | AF11: 9200 | AG11: 21393.732 | AH11: 30520.155 | AI11: 38855.441 | AJ11: 45545.237 | AK11: 52053.627
B12: (Taxes) | C12: ='Income Statement'!C51 -> 1367 | D12: ='Income Statement'!D51 -> 1607 | E12: ='Income Statement'!E51 -> 141 | F12: ='Income Statement'!F51 -> 1491 | G12: ='Income Statement'!G51 -> 1493 | H12: ='Income Statement'!H51 -> 864.89452 | I12: ='Income Statement'!I51 -> 1864.2437 | J12: ='Income Statement'!J51 -> 3318.9893 | ... L12: ='Income Statement'!L51 -> 6140.8928 | O12: (Taxes) | P12: =1-WACC!$E5 -> 0.83 | Q12: =1-WACC!$E5 -> 0.83 | R12: =1-WACC!$E5 -> 0.83 | S12: =1-WACC!$E5 -> 0.83 | T12: =1-WACC!$E5 -> 0.83 | U12: =1-WACC!$E5 -> 0.83 | V12: =1-WACC!$E5 -> 0.83 | W12: =1-WACC!$E5 -> 0.83 | ... Y12: =1-WACC!$E5 -> 0.83 | AA12: Terminal Value | AK12: =AK11*C41 -> 607812.57
B13: NOPAT | C13: =C11-C12 -> 6568 | D13: =D11-D12 -> 6807 | E13: =E11-E12 -> 8395 | F13: =F11-F12 -> 7926 | G13: =G11-G12 -> 7707 | H13: =H11-H12 -> 6480.4822 | I13: =I11-I12 -> 8755.5814 | J13: =J11-J12 -> 16186.354 | ... L13: =L11-L12 -> 30373.896 | O13: NOPAT | P13: =P11*P12 -> 6586.05 | Q13: =Q11*Q12 -> 6983.62 | R13: =R11*R12 -> 7084.88 | S13: =S11*S12 -> 7816.11 | T13: =T11*T12 -> 7636 | U13: =U11*U12 -> 17756.797 | V13: =V11*V12 -> 25331.729 | W13: =W11*W12 -> 32250.016 | ... Y13: =Y11*Y12 -> 43204.511 | AA13: Discount Factor | AK13: =1/(1+C39)^5 -> 0.76574518
B14: +D&A | C14: =+Calcs!C15 -> 1375 | D14: =+Calcs!D15 -> 1331 | E14: =+Calcs!E15 -> 1216 | F14: =+Calcs!F15 -> 1332 | G14: =+Calcs!G15 -> 1292 | H14: =+Calcs!H15 -> 1949.8866 | I14: =+Calcs!I15 -> 2164.3521 | J14: =+Calcs!J15 -> 2360.779 | ... L14: =+Calcs!L15 -> 2766.1452 | O14: +D&A | P14: =Calcs!C15 -> 1375 | Q14: =Calcs!D15 -> 1331 | R14: =Calcs!E15 -> 1216 | S14: =Calcs!F15 -> 1332 | T14: =Calcs!G15 -> 1292 | U14: =Calcs!H15 -> 1949.8866 | V14: =Calcs!I15 -> 2164.3521 | W14: =Calcs!J15 -> 2360.779 | ... Y14: =Calcs!L15 -> 2766.1452 | AA14: Discounted Terminal Value | AK14: =AK12*AK13 -> 465429.55
B15: (CapEx) | C15: =-Calcs!C14 -> -1154 | D15: =-Calcs!D14 -> -1295 | E15: =-Calcs!E14 -> -1573 | F15: =-Calcs!F14 -> -1406 | G15: =-Calcs!G14 -> -1212 | H15: =-Calcs!H14 -> -1972.5859 | I15: =-Calcs!I14 -> -2169.1845 | J15: =-Calcs!J14 -> -2261.1893 | ... L15: =-Calcs!L14 -> -2459.376 | O15: (CapEx) | P15: =-Calcs!C14 -> -1154 | Q15: =-Calcs!D14 -> -1295 | R15: =-Calcs!E14 -> -1573 | S15: =-Calcs!F14 -> -1406 | T15: =-Calcs!G14 -> -1212 | U15: =-Calcs!H14 -> -1972.5859 | V15: =-Calcs!I14 -> -2169.1845 | W15: =-Calcs!J14 -> -2261.1893 | ... Y15: =-Calcs!L14 -> -2459.376 | AA15: (Total Debt) | AK15: =-Y32 -> -31463
B16: (Changes in NWC) | D16: =-Calcs!D37 -> 5991 | E16: =-Calcs!E37 -> -5440 | F16: =-Calcs!F37 -> -1148 | G16: =-Calcs!G37 -> 5016 | H16: =-Calcs!H37 -> -3553.878 | I16: =-Calcs!I37 -> -511.63017 | J16: =-Calcs!J37 -> -238.86679 | K16: =-Calcs!K37 -> 240.66782 | L16: =-Calcs!L37 -> -1156.111 | O16: (Changes in NWC) | Q16: =-Calcs!D37 -> 5991 | R16: =-Calcs!E37 -> -5440 | S16: =-Calcs!F37 -> -1148 | T16: =-Calcs!G37 -> 5016 | U16: =-Calcs!H37 -> -3553.878 | V16: =-Calcs!I37 -> -511.63017 | W16: =-Calcs!J37 -> -238.86679 | X16: =-Calcs!K37 -> 240.66782 | Y16: =-Calcs!L37 -> -1156.111 | AA16: +Total Cash | AK16: =Y36 -> #REF!
B17: Unlevered Free Cash Flow | C17: =C13+C14+C15-C16 -> 6789 | D17: =D13+D14+D15-D16 -> 852 | E17: =E13+E14+E15-E16 -> 13478 | F17: =F13+F14+F15-F16 -> 9000 | G17: =G13+G14+G15-G16 -> 2771 | H17: =H13+H14+H15-H16 -> 10011.661 | I17: =I13+I14+I15-I16 -> 9262.3792 | J17: =J13+J14+J15-J16 -> 16524.81 | ... L17: =L13+L14+L15-L16 -> 31836.776 | O17: Unlevered Free Cash Flow | P17: =P13+P14+P15-P16 -> 6807.05 | Q17: =Q13+Q14+Q15-Q16 -> 1028.62 | R17: =R13+R14+R15-R16 -> 12167.88 | S17: =S13+S14+S15-S16 -> 8890.11 | T17: =T13+T14+T15-T16 -> 2700 | U17: =U13+U14+U15-U16 -> 21287.976 | V17: =V13+V14+V15-V16 -> 25838.527 | W17: =W13+W14+W15-W16 -> 32588.473 | ... Y17: =Y13+Y14+Y15-Y16 -> 44667.391 | AA17: Equity Value | AK17: =SUM(AK14:AK16) -> #REF!
B18: Mid Year Convention | C18: NO | O18: Mid Year Convention | P18: NO | AA18: Shares Outstanding | AK18: =Y39 -> 2635
B19: Terminal Value | L19: =(L17*(1+C40)/((C39-C40))) -> 960797.5 | O19: Year | U19: 1 | V19: 2 | W19: 3 | X19: 4 | Y19: 5 | AA19: Implied Share Price | AK19: =AK17/AK18 -> #REF!
B20: Growth Rate | L20: =WACC!M5 -> 0.021 | AA20: Current Share Price | AK20: =Comps!D4 -> 271.25
B21: Discount Rate (WACC) | L21: =WACC!D5 -> 0.054831633 | O21: Growth Rate | Y21: =WACC!M5 -> 0.021 | AA21: Implied Upside/Down Side | AK21: =(AK19-AK20)/AK20 -> #REF!
B22: Total Cash Flows | H22: =H17 -> 10011.661 | I22: =I17 -> 9262.3792 | J22: =J17 -> 16524.81 | K22: =K17 -> 27042.691 | L22: =L17 -> 31836.776 | O22: Discount Rate (WACC) | Y22: =WACC!D5 -> 0.054831633
B23: Discount Factor | H23: =1/(1+$C$39)^1 -> 0.94801859 | I23: =1/(1+$C$39)^2 -> 0.89873925 | J23: =1/(1+$C$39)^3 -> 0.85202152 | K23: =1/(1+$C$39)^4 -> 0.80773224 | L23: =1/(1+$C$39)^5 -> 0.76574518 | O23: Terminal Value | Y23: =(Y17*(1+Y21))/(Y22-Y21) -> 1348010.8
B24: Discounted Free Cash Flow | H24: =H23*H22 -> 9491.2407 | I24: =I23*I22 -> 8324.4637 | J24: =J23*J22 -> 14079.494 | K24: =K23*K22 -> 21843.254 | L24: =L23*L22 -> 24378.858
B25: Discounted Terminal Value | L25: =L19*L23 -> 735726.06 | O25: Discount Rate | U25: =1/(1+$C$39)^U19 -> 0.94801859 | V25: =1/(1+$C$39)^V19 -> 0.89873925 | W25: =1/(1+$C$39)^W19 -> 0.85202152 | X25: =1/(1+$C$39)^X19 -> 0.80773224 | Y25: =1/(1+$C$39)^Y19 -> 0.76574518
O26: PV of FCFs | U26: =U17*U25 -> 20181.397 | V26: =V17*V25 -> 23222.098 | W26: =W17*W25 -> 27766.08 | X26: =X17*X25 -> 30562.788 | Y26: =Y17*Y25 -> 34203.84
B27: Implied Share Price Analysis | G27: Growth Rate | O27: PV of terminal value | Y27: =Y23*Y25 -> 1032232.8
B28: Enterprise Value | C28: =SUM(H24:L24,L25) -> 813843.37 | F28: =C33 -> 296.91855 | G28: =H28-0.15% -> 0.018 | H28: =I28-0.15% -> 0.0195 | I28: 0.021 | J28: =I28+0.15% -> 0.0225 | K28: =J28+0.15% -> 0.024 | O28: TEV (Total Enterprise Value)
B29: +Cash | C29: =-Y32 -> -31463 | F29: =F30-0.25% -> 0.049831633 | G29: 321.20864 | H29: 336.66141 | I29: 353.72208 | J29: 372.65538 | K29: 393.78752
B30: -Debt | F30: =F31-0.25% -> 0.052331633 | G30: 295.56912 | H30: 308.68032 | I30: 323.04691 | J30: 338.85827 | K30: 356.34387 | O30: Short-Term Debt | Y30: =LTMS!L31 -> 592
B31: Equity Value | C31: =SUM(C28:C29) -> 782380.37 | E31: WACC | F31: 0.054831633 | G31: 273.42259 | H31: 284.67181 | I31: 296.91855 | J31: 310.30164 | K31: 324.98695 | O31: Long-Term Debt | Y31: =LTMS!M31 -> 30871
B32: Shares Outstanding | C32: =Y39 -> 2635 | F32: =F31+0.25% -> 0.057331633 | G32: 254.10282 | H32: 263.84818 | I32: 274.39824 | J32: 285.85695 | K32: 298.34701 | O32: Total Debt | Y32: =Y30+Y31 -> 31463
B33: Implied Share Price Analysis | C33: =C31/C32 -> 296.91855 | F33: =F32+0.25% -> 0.059831633 | G33: 237.10289 | H33: 245.61704 | I33: 254.78897 | J33: 264.69797 | K33: 275.43659
B34: Current Share Price | C34: =Comps!D4 -> 271.25 | O34: Required Cash | Y34: =#REF! -> #REF!
B35: Implied Upside/Downside | C35: =(C33-C34)/C34 -> 0.094630584 | O35: Excess Cash | Y35: =#REF! -> #REF!
B36: Rating | C36: {=_xlfn.IFS(C35<-5%,"SELL",C35<=5%,"HOLD",C35>5%,"BUY")} -> BUY | O36: Total Cash | Y36: =Y34+Y35 -> #REF!
B38: Valuation Calculations | O38: Equity Value | Y38: =Y36-Y32+Y27 -> #REF!
B39: WACC | C39: =WACC!D5 -> 0.054831633 | O39: Diluted Shares Outstanding | Y39: =Comps!E4 -> 2635
B40: Growth Rate | C40: =WACC!M5 -> 0.021 | O40: Value per Share | Y40: =Y38/Y39 -> #REF!
B41: Exit Multiple | C41: =Comps!J13 -> 11.676661 | O41: Current Price | Y41: 272
O42: Premium / (Discount) to Intrinsic Value | Y42: =(Y40-Y41)/Y40 -> #REF!
Q46: Exit Multiple (EV/EBITDA)
P47: =AK19 -> #REF! | Q47: =R47-0.25 -> 9.790749 | R47: =S47-0.25 -> 10.040749 | S47: 10.290749 | T47: =S47+0.25 -> 10.540749 | U47: =T47+0.25 -> 10.790749
P48: =P49-0.25% -> 0.049831633 | Q48: #REF! | R48: #REF! | S48: #REF! | T48: #REF! | U48: #REF!
P49: =P50-0.25% -> 0.052331633 | Q49: #REF! | R49: #REF! | S49: #REF! | T49: #REF! | U49: #REF!
O50: WACC | P50: 0.054831633 | Q50: #REF! | R50: #REF! | S50: #REF! | T50: #REF! | U50: #REF!
P51: =P50+0.15% -> 0.056331633 | Q51: #REF! | R51: #REF! | S51: #REF! | T51: #REF! | U51: #REF!
P52: =P51+0.15% -> 0.057831633 | Q52: #REF! | R52: #REF! | S52: #REF! | T52: #REF! | U52: #REF!

Sheet Summary
B2: Equities
C4: Healthcare
C5: Pharmaceutical Services
C8: NYSE: CI | E8: BUY
C10: Price (4/14/26): | E10: =Comps!D4 -> 271.25
C11: Price Target: | E11: =DCF!C33 -> 296.91855
C12: Implied Upside/ Downside: | E12: =(E11-E10)/E10 -> 0.094630584
C15: Senior Analyst(s) | E15: NetID
C16: Ohm Shah | E16: os254
C17: Steven Soza | E17: ss3250
C18: Junior Analysts
C19: Ninaad Hadge | E19: nnh40
C20: Nicholas Wan | E20: nkw25
C21: Matthew DiCarlo | E21: md2109
C22: Karishma Shah | E22: ks2278
C23: Zohaib Sheikh | E23: zs602
C26: Estimates | D26: Consensus | E26: RU-N SMF
C27: Price Tgt | D27: 338.79 | E27: =E11 -> 296.91855
C28: FY26E Revenue (mm) | D28: 280000 | E28: ='Income Statement'!H38 -> 308629.28
C29: FY27E Revenue (mm) | D29: 308400 | E29: ='Income Statement'!I38 -> 342575
C30: FY26E EPS | D30: 30.25 | E30: ='Income Statement'!H57 -> 22.18
C31: FY27E EPS | D31: 33.4 | E31: ='Income Statement'!I57 -> 22.18
C34: Trading Overview
C35: 52-Week High / Low | E35: $239.51-$350.00
C36: Shares Out. (MM) | E36: =Comps!E4 -> 2635
C37: Market Cap (MM) | E37: =Comps!F4 -> 714743.75
C38: EV/EBITDA | E38: =Comps!K4 -> 94.914632
C39: P/E | E39: 12.3
C40: Debt to Total Capital | E40: 0.43
C41: Fiscal Year End | E41: 2025
C44: Price Performance - Year to Date
C51: Source - Yahoo Finance
